Workbook

Sheet Loans
A1: Dinio Capital | Loan Tracker
A2: Blue text = you type it. Black text = formula. Grey fill = calculated column (do not type over it). Costo de Equipo is the base for all three fees.
A3: Loans 1 to 3 are SAMPLES (placeholder names, assumed dates, 8.99% and 60 months where not given). Replace them with real loans.
B4: Fee Rates | E4: Notes / Open Items
B5: Origination Fee % | C5: 0.01 | E5: 1. SAMPLE DATA: loans 1 to 3 are placeholders. Replace client names, dates, rates and terms with real values. 2. OPEN: the bank's invoice requirements are unknown (Bill To, Invoice #, payment instructions, layout). Confirm them. 3. OPEN: confirm the referral fee method and base against the agreement (modeled as the interest of a separate loan on Costo de Equipo, same term, at the yearly rate in the Fee Rates box). 4. First Payment Date defaults to 1 month after Closing Date. Type over it if the real date differs.
B6: Legal/Closing Fee % | C6: 0.01
B7: Referral Fee % (yearly) | C7: 0.005
B8: Today (automatic) | C8: =TODAY() -> 46296
A10: INPUTS (type in blue cells) | J10: CALCULATED | S10: HELPER COLUMNS (feed other tabs, do not edit)
A11: Loan # | B11: Client or Company | C11: Status | D11: Closing Date (expected if Pipeline) | E11: First Payment Date (auto, can overwrite) | F11: Costo de Equipo | G11: Pronto % | H11: Interes | I11: Termino (mo.) | J11: Pronto $ | K11: Monto a Financiar | L11: Pago Mensual | M11: Origination Fee | N11: Legal/Closing Fee | O11: Referral Fee over life of loan | P11: Referral Fee earned to date | Q11: Payments Made | R11: Next Payment Date | S11: Months from 1st Pmt to Today | T11: Payments Due to Date (uncapped) | U11: Closing Month | V11: Closing Fees (Orig + Legal) | W11: Closing Fees if Closed | X11: Closing Fees if Pipeline | Y11: Pipeline Counter
A12: 1 | B12: SAMPLE Client A (replace) | C12: Closed | D12: 46218 | E12: =IF(D12="","",EDATE(D12,1)) -> 46249 | F12: 38127.43 | G12: 0 | H12: 0.0899 | I12: 60 | J12: =IF(F12="","",F12*G12) -> 0 | K12: =IF(F12="","",F12-J12) -> 38127.43 | L12: =IF(OR(K12="",I12=""),"",PMT(H12/12,I12,-K12)) -> 791.2777 | M12: =IF(F12="","",IF(C12="Dead",0,F12*C5)) -> 381.2743 | N12: =IF(F12="","",IF(C12="Dead",0,F12*C6)) -> 381.2743 | O12: =IF(OR(F12="",I12=""),"",IF(C12="Dead",0,I12*PMT(C7/12,I12,-F12)-F12)) -> 486.52091 | P12: =IF(F12="","",IF(C12<>"Closed",0,SUMIF('Referral Fees'!I11:BP11,"<="&Q12,'Referral Fees'!I12:BP12))) -> 31.511325 | Q12: =IF(F12="","",IF(C12<>"Closed",0,IF(T12="",0,IF(T12<=0,0,IF(T12>I12,I12,T12))))) -> 2 | R12: =IF(C12<>"Closed","",IF(OR(E12="",I12=""),"",IF(Q12>=I12,"Paid off",EDATE(E12,Q12)))) -> 46310 | S12: =IF(OR(F12="",E12=""),"",(YEAR(C8)-YEAR(E12))*12+MONTH(C8)-MONTH(E12)) -> 2 | T12: =IF(S12="","",S12+IF(EDATE(E12,S12)<=C8,1,0)) -> 2 | U12: =IF(D12="","",DATE(YEAR(D12),MONTH(D12),1)) -> 46204 | V12: =IF(F12="","",M12+N12) -> 762.5486 | W12: =IF(C12="Closed",SUM(V12),0) -> 762.5486 | X12: =IF(C12="Pipeline",SUM(V12),0) -> 0 | Y12: =IF(C12="Pipeline",COUNTIF(C12:C12,"Pipeline"),"")
A13: 2 | B13: SAMPLE Client B (replace) | C13: Pipeline | D13: 46341 | E13: =IF(D13="","",EDATE(D13,1)) -> 46371 | F13: 58000 | G13: 0 | H13: 0.0899 | I13: 60 | J13: =IF(F13="","",F13*G13) -> 0 | K13: =IF(F13="","",F13-J13) -> 58000 | L13: =IF(OR(K13="",I13=""),"",PMT(H13/12,I13,-K13)) -> 1203.7031 | M13: =IF(F13="","",IF(C13="Dead",0,F13*C5)) -> 580 | N13: =IF(F13="","",IF(C13="Dead",0,F13*C6)) -> 580 | O13: =IF(OR(F13="",I13=""),"",IF(C13="Dead",0,I13*PMT(C7/12,I13,-F13)-F13)) -> 740.10267 | P13: =IF(F13="","",IF(C13<>"Closed",0,SUMIF('Referral Fees'!I11:BP11,"<="&Q13,'Referral Fees'!I13:BP13))) -> 0 | Q13: =IF(F13="","",IF(C13<>"Closed",0,IF(T13="",0,IF(T13<=0,0,IF(T13>I13,I13,T13))))) -> 0 | R13: =IF(C13<>"Closed","",IF(OR(E13="",I13=""),"",IF(Q13>=I13,"Paid off",EDATE(E13,Q13)))) | S13: =IF(OR(F13="",E13=""),"",(YEAR(C8)-YEAR(E13))*12+MONTH(C8)-MONTH(E13)) -> -2 | T13: =IF(S13="","",S13+IF(EDATE(E13,S13)<=C8,1,0)) -> -2 | U13: =IF(D13="","",DATE(YEAR(D13),MONTH(D13),1)) -> 46327 | V13: =IF(F13="","",M13+N13) -> 1160 | W13: =IF(C13="Closed",SUM(V13),0) -> 0 | X13: =IF(C13="Pipeline",SUM(V13),0) -> 1160 | Y13: =IF(C13="Pipeline",COUNTIF(C12:C13,"Pipeline"),"") -> 1
A14: 3 | B14: SAMPLE Client C (replace) | C14: Pipeline | D14: 46366 | E14: =IF(D14="","",EDATE(D14,1)) -> 46397 | F14: 17500 | G14: 0 | H14: 0.0899 | I14: 60 | J14: =IF(F14="","",F14*G14) -> 0 | K14: =IF(F14="","",F14-J14) -> 17500 | L14: =IF(OR(K14="",I14=""),"",PMT(H14/12,I14,-K14)) -> 363.18629 | M14: =IF(F14="","",IF(C14="Dead",0,F14*C5)) -> 175 | N14: =IF(F14="","",IF(C14="Dead",0,F14*C6)) -> 175 | O14: =IF(OR(F14="",I14=""),"",IF(C14="Dead",0,I14*PMT(C7/12,I14,-F14)-F14)) -> 223.30684 | P14: =IF(F14="","",IF(C14<>"Closed",0,SUMIF('Referral Fees'!I11:BP11,"<="&Q14,'Referral Fees'!I14:BP14))) -> 0 | Q14: =IF(F14="","",IF(C14<>"Closed",0,IF(T14="",0,IF(T14<=0,0,IF(T14>I14,I14,T14))))) -> 0 | R14: =IF(C14<>"Closed","",IF(OR(E14="",I14=""),"",IF(Q14>=I14,"Paid off",EDATE(E14,Q14)))) | S14: =IF(OR(F14="",E14=""),"",(YEAR(C8)-YEAR(E14))*12+MONTH(C8)-MONTH(E14)) -> -3 | T14: =IF(S14="","",S14+IF(EDATE(E14,S14)<=C8,1,0)) -> -3 | U14: =IF(D14="","",DATE(YEAR(D14),MONTH(D14),1)) -> 46357 | V14: =IF(F14="","",M14+N14) -> 350 | W14: =IF(C14="Closed",SUM(V14),0) -> 0 | X14: =IF(C14="Pipeline",SUM(V14),0) -> 350 | Y14: =IF(C14="Pipeline",COUNTIF(C12:C14,"Pipeline"),"") -> 2
E15: =IF(D15="","",EDATE(D15,1)) | J15: =IF(F15="","",F15*G15) | K15: =IF(F15="","",F15-J15) | L15: =IF(OR(K15="",I15=""),"",PMT(H15/12,I15,-K15)) | M15: =IF(F15="","",IF(C15="Dead",0,F15*C5)) | N15: =IF(F15="","",IF(C15="Dead",0,F15*C6)) | O15: =IF(OR(F15="",I15=""),"",IF(C15="Dead",0,I15*PMT(C7/12,I15,-F15)-F15)) | P15: =IF(F15="","",IF(C15<>"Closed",0,SUMIF('Referral Fees'!I11:BP11,"<="&Q15,'Referral Fees'!I15:BP15))) | Q15: =IF(F15="","",IF(C15<>"Closed",0,IF(T15="",0,IF(T15<=0,0,IF(T15>I15,I15,T15))))) | R15: =IF(C15<>"Closed","",IF(OR(E15="",I15=""),"",IF(Q15>=I15,"Paid off",EDATE(E15,Q15)))) | S15: =IF(OR(F15="",E15=""),"",(YEAR(C8)-YEAR(E15))*12+MONTH(C8)-MONTH(E15)) | T15: =IF(S15="","",S15+IF(EDATE(E15,S15)<=C8,1,0)) | U15: =IF(D15="","",DATE(YEAR(D15),MONTH(D15),1)) | V15: =IF(F15="","",M15+N15) | W15: =IF(C15="Closed",SUM(V15),0) -> 0 | X15: =IF(C15="Pipeline",SUM(V15),0) -> 0 | Y15: =IF(C15="Pipeline",COUNTIF(C12:C15,"Pipeline"),"")
E16: =IF(D16="","",EDATE(D16,1)) | J16: =IF(F16="","",F16*G16) | K16: =IF(F16="","",F16-J16) | L16: =IF(OR(K16="",I16=""),"",PMT(H16/12,I16,-K16)) | M16: =IF(F16="","",IF(C16="Dead",0,F16*C5)) | N16: =IF(F16="","",IF(C16="Dead",0,F16*C6)) | O16: =IF(OR(F16="",I16=""),"",IF(C16="Dead",0,I16*PMT(C7/12,I16,-F16)-F16)) | P16: =IF(F16="","",IF(C16<>"Closed",0,SUMIF('Referral Fees'!I11:BP11,"<="&Q16,'Referral Fees'!I16:BP16))) | Q16: =IF(F16="","",IF(C16<>"Closed",0,IF(T16="",0,IF(T16<=0,0,IF(T16>I16,I16,T16))))) | R16: =IF(C16<>"Closed","",IF(OR(E16="",I16=""),"",IF(Q16>=I16,"Paid off",EDATE(E16,Q16)))) | S16: =IF(OR(F16="",E16=""),"",(YEAR(C8)-YEAR(E16))*12+MONTH(C8)-MONTH(E16)) | T16: =IF(S16="","",S16+IF(EDATE(E16,S16)<=C8,1,0)) | U16: =IF(D16="","",DATE(YEAR(D16),MONTH(D16),1)) | V16: =IF(F16="","",M16+N16) | W16: =IF(C16="Closed",SUM(V16),0) -> 0 | X16: =IF(C16="Pipeline",SUM(V16),0) -> 0 | Y16: =IF(C16="Pipeline",COUNTIF(C12:C16,"Pipeline"),"")
E17: =IF(D17="","",EDATE(D17,1)) | J17: =IF(F17="","",F17*G17) | K17: =IF(F17="","",F17-J17) | L17: =IF(OR(K17="",I17=""),"",PMT(H17/12,I17,-K17)) | M17: =IF(F17="","",IF(C17="Dead",0,F17*C5)) | N17: =IF(F17="","",IF(C17="Dead",0,F17*C6)) | O17: =IF(OR(F17="",I17=""),"",IF(C17="Dead",0,I17*PMT(C7/12,I17,-F17)-F17)) | P17: =IF(F17="","",IF(C17<>"Closed",0,SUMIF('Referral Fees'!I11:BP11,"<="&Q17,'Referral Fees'!I17:BP17))) | Q17: =IF(F17="","",IF(C17<>"Closed",0,IF(T17="",0,IF(T17<=0,0,IF(T17>I17,I17,T17))))) | R17: =IF(C17<>"Closed","",IF(OR(E17="",I17=""),"",IF(Q17>=I17,"Paid off",EDATE(E17,Q17)))) | S17: =IF(OR(F17="",E17=""),"",(YEAR(C8)-YEAR(E17))*12+MONTH(C8)-MONTH(E17)) | T17: =IF(S17="","",S17+IF(EDATE(E17,S17)<=C8,1,0)) | U17: =IF(D17="","",DATE(YEAR(D17),MONTH(D17),1)) | V17: =IF(F17="","",M17+N17) | W17: =IF(C17="Closed",SUM(V17),0) -> 0 | X17: =IF(C17="Pipeline",SUM(V17),0) -> 0 | Y17: =IF(C17="Pipeline",COUNTIF(C12:C17,"Pipeline"),"")
E18: =IF(D18="","",EDATE(D18,1)) | J18: =IF(F18="","",F18*G18) | K18: =IF(F18="","",F18-J18) | L18: =IF(OR(K18="",I18=""),"",PMT(H18/12,I18,-K18)) | M18: =IF(F18="","",IF(C18="Dead",0,F18*C5)) | N18: =IF(F18="","",IF(C18="Dead",0,F18*C6)) | O18: =IF(OR(F18="",I18=""),"",IF(C18="Dead",0,I18*PMT(C7/12,I18,-F18)-F18)) | P18: =IF(F18="","",IF(C18<>"Closed",0,SUMIF('Referral Fees'!I11:BP11,"<="&Q18,'Referral Fees'!I18:BP18))) | Q18: =IF(F18="","",IF(C18<>"Closed",0,IF(T18="",0,IF(T18<=0,0,IF(T18>I18,I18,T18))))) | R18: =IF(C18<>"Closed","",IF(OR(E18="",I18=""),"",IF(Q18>=I18,"Paid off",EDATE(E18,Q18)))) | S18: =IF(OR(F18="",E18=""),"",(YEAR(C8)-YEAR(E18))*12+MONTH(C8)-MONTH(E18)) | T18: =IF(S18="","",S18+IF(EDATE(E18,S18)<=C8,1,0)) | U18: =IF(D18="","",DATE(YEAR(D18),MONTH(D18),1)) | V18: =IF(F18="","",M18+N18) | W18: =IF(C18="Closed",SUM(V18),0) -> 0 | X18: =IF(C18="Pipeline",SUM(V18),0) -> 0 | Y18: =IF(C18="Pipeline",COUNTIF(C12:C18,"Pipeline"),"")
E19: =IF(D19="","",EDATE(D19,1)) | J19: =IF(F19="","",F19*G19) | K19: =IF(F19="","",F19-J19) | L19: =IF(OR(K19="",I19=""),"",PMT(H19/12,I19,-K19)) | M19: =IF(F19="","",IF(C19="Dead",0,F19*C5)) | N19: =IF(F19="","",IF(C19="Dead",0,F19*C6)) | O19: =IF(OR(F19="",I19=""),"",IF(C19="Dead",0,I19*PMT(C7/12,I19,-F19)-F19)) | P19: =IF(F19="","",IF(C19<>"Closed",0,SUMIF('Referral Fees'!I11:BP11,"<="&Q19,'Referral Fees'!I19:BP19))) | Q19: =IF(F19="","",IF(C19<>"Closed",0,IF(T19="",0,IF(T19<=0,0,IF(T19>I19,I19,T19))))) | R19: =IF(C19<>"Closed","",IF(OR(E19="",I19=""),"",IF(Q19>=I19,"Paid off",EDATE(E19,Q19)))) | S19: =IF(OR(F19="",E19=""),"",(YEAR(C8)-YEAR(E19))*12+MONTH(C8)-MONTH(E19)) | T19: =IF(S19="","",S19+IF(EDATE(E19,S19)<=C8,1,0)) | U19: =IF(D19="","",DATE(YEAR(D19),MONTH(D19),1)) | V19: =IF(F19="","",M19+N19) | W19: =IF(C19="Closed",SUM(V19),0) -> 0 | X19: =IF(C19="Pipeline",SUM(V19),0) -> 0 | Y19: =IF(C19="Pipeline",COUNTIF(C12:C19,"Pipeline"),"")
E20: =IF(D20="","",EDATE(D20,1)) | J20: =IF(F20="","",F20*G20) | K20: =IF(F20="","",F20-J20) | L20: =IF(OR(K20="",I20=""),"",PMT(H20/12,I20,-K20)) | M20: =IF(F20="","",IF(C20="Dead",0,F20*C5)) | N20: =IF(F20="","",IF(C20="Dead",0,F20*C6)) | O20: =IF(OR(F20="",I20=""),"",IF(C20="Dead",0,I20*PMT(C7/12,I20,-F20)-F20)) | P20: =IF(F20="","",IF(C20<>"Closed",0,SUMIF('Referral Fees'!I11:BP11,"<="&Q20,'Referral Fees'!I20:BP20))) | Q20: =IF(F20="","",IF(C20<>"Closed",0,IF(T20="",0,IF(T20<=0,0,IF(T20>I20,I20,T20))))) | R20: =IF(C20<>"Closed","",IF(OR(E20="",I20=""),"",IF(Q20>=I20,"Paid off",EDATE(E20,Q20)))) | S20: =IF(OR(F20="",E20=""),"",(YEAR(C8)-YEAR(E20))*12+MONTH(C8)-MONTH(E20)) | T20: =IF(S20="","",S20+IF(EDATE(E20,S20)<=C8,1,0)) | U20: =IF(D20="","",DATE(YEAR(D20),MONTH(D20),1)) | V20: =IF(F20="","",M20+N20) | W20: =IF(C20="Closed",SUM(V20),0) -> 0 | X20: =IF(C20="Pipeline",SUM(V20),0) -> 0 | Y20: =IF(C20="Pipeline",COUNTIF(C12:C20,"Pipeline"),"")
E21: =IF(D21="","",EDATE(D21,1)) | J21: =IF(F21="","",F21*G21) | K21: =IF(F21="","",F21-J21) | L21: =IF(OR(K21="",I21=""),"",PMT(H21/12,I21,-K21)) | M21: =IF(F21="","",IF(C21="Dead",0,F21*C5)) | N21: =IF(F21="","",IF(C21="Dead",0,F21*C6)) | O21: =IF(OR(F21="",I21=""),"",IF(C21="Dead",0,I21*PMT(C7/12,I21,-F21)-F21)) | P21: =IF(F21="","",IF(C21<>"Closed",0,SUMIF('Referral Fees'!I11:BP11,"<="&Q21,'Referral Fees'!I21:BP21))) | Q21: =IF(F21="","",IF(C21<>"Closed",0,IF(T21="",0,IF(T21<=0,0,IF(T21>I21,I21,T21))))) | R21: =IF(C21<>"Closed","",IF(OR(E21="",I21=""),"",IF(Q21>=I21,"Paid off",EDATE(E21,Q21)))) | S21: =IF(OR(F21="",E21=""),"",(YEAR(C8)-YEAR(E21))*12+MONTH(C8)-MONTH(E21)) | T21: =IF(S21="","",S21+IF(EDATE(E21,S21)<=C8,1,0)) | U21: =IF(D21="","",DATE(YEAR(D21),MONTH(D21),1)) | V21: =IF(F21="","",M21+N21) | W21: =IF(C21="Closed",SUM(V21),0) -> 0 | X21: =IF(C21="Pipeline",SUM(V21),0) -> 0 | Y21: =IF(C21="Pipeline",COUNTIF(C12:C21,"Pipeline"),"")
E22: =IF(D22="","",EDATE(D22,1)) | J22: =IF(F22="","",F22*G22) | K22: =IF(F22="","",F22-J22) | L22: =IF(OR(K22="",I22=""),"",PMT(H22/12,I22,-K22)) | M22: =IF(F22="","",IF(C22="Dead",0,F22*C5)) | N22: =IF(F22="","",IF(C22="Dead",0,F22*C6)) | O22: =IF(OR(F22="",I22=""),"",IF(C22="Dead",0,I22*PMT(C7/12,I22,-F22)-F22)) | P22: =IF(F22="","",IF(C22<>"Closed",0,SUMIF('Referral Fees'!I11:BP11,"<="&Q22,'Referral Fees'!I22:BP22))) | Q22: =IF(F22="","",IF(C22<>"Closed",0,IF(T22="",0,IF(T22<=0,0,IF(T22>I22,I22,T22))))) | R22: =IF(C22<>"Closed","",IF(OR(E22="",I22=""),"",IF(Q22>=I22,"Paid off",EDATE(E22,Q22)))) | S22: =IF(OR(F22="",E22=""),"",(YEAR(C8)-YEAR(E22))*12+MONTH(C8)-MONTH(E22)) | T22: =IF(S22="","",S22+IF(EDATE(E22,S22)<=C8,1,0)) | U22: =IF(D22="","",DATE(YEAR(D22),MONTH(D22),1)) | V22: =IF(F22="","",M22+N22) | W22: =IF(C22="Closed",SUM(V22),0) -> 0 | X22: =IF(C22="Pipeline",SUM(V22),0) -> 0 | Y22: =IF(C22="Pipeline",COUNTIF(C12:C22,"Pipeline"),"")
E23: =IF(D23="","",EDATE(D23,1)) | J23: =IF(F23="","",F23*G23) | K23: =IF(F23="","",F23-J23) | L23: =IF(OR(K23="",I23=""),"",PMT(H23/12,I23,-K23)) | M23: =IF(F23="","",IF(C23="Dead",0,F23*C5)) | N23: =IF(F23="","",IF(C23="Dead",0,F23*C6)) | O23: =IF(OR(F23="",I23=""),"",IF(C23="Dead",0,I23*PMT(C7/12,I23,-F23)-F23)) | P23: =IF(F23="","",IF(C23<>"Closed",0,SUMIF('Referral Fees'!I11:BP11,"<="&Q23,'Referral Fees'!I23:BP23))) | Q23: =IF(F23="","",IF(C23<>"Closed",0,IF(T23="",0,IF(T23<=0,0,IF(T23>I23,I23,T23))))) | R23: =IF(C23<>"Closed","",IF(OR(E23="",I23=""),"",IF(Q23>=I23,"Paid off",EDATE(E23,Q23)))) | S23: =IF(OR(F23="",E23=""),"",(YEAR(C8)-YEAR(E23))*12+MONTH(C8)-MONTH(E23)) | T23: =IF(S23="","",S23+IF(EDATE(E23,S23)<=C8,1,0)) | U23: =IF(D23="","",DATE(YEAR(D23),MONTH(D23),1)) | V23: =IF(F23="","",M23+N23) | W23: =IF(C23="Closed",SUM(V23),0) -> 0 | X23: =IF(C23="Pipeline",SUM(V23),0) -> 0 | Y23: =IF(C23="Pipeline",COUNTIF(C12:C23,"Pipeline"),"")
E24: =IF(D24="","",EDATE(D24,1)) | J24: =IF(F24="","",F24*G24) | K24: =IF(F24="","",F24-J24) | L24: =IF(OR(K24="",I24=""),"",PMT(H24/12,I24,-K24)) | M24: =IF(F24="","",IF(C24="Dead",0,F24*C5)) | N24: =IF(F24="","",IF(C24="Dead",0,F24*C6)) | O24: =IF(OR(F24="",I24=""),"",IF(C24="Dead",0,I24*PMT(C7/12,I24,-F24)-F24)) | P24: =IF(F24="","",IF(C24<>"Closed",0,SUMIF('Referral Fees'!I11:BP11,"<="&Q24,'Referral Fees'!I24:BP24))) | Q24: =IF(F24="","",IF(C24<>"Closed",0,IF(T24="",0,IF(T24<=0,0,IF(T24>I24,I24,T24))))) | R24: =IF(C24<>"Closed","",IF(OR(E24="",I24=""),"",IF(Q24>=I24,"Paid off",EDATE(E24,Q24)))) | S24: =IF(OR(F24="",E24=""),"",(YEAR(C8)-YEAR(E24))*12+MONTH(C8)-MONTH(E24)) | T24: =IF(S24="","",S24+IF(EDATE(E24,S24)<=C8,1,0)) | U24: =IF(D24="","",DATE(YEAR(D24),MONTH(D24),1)) | V24: =IF(F24="","",M24+N24) | W24: =IF(C24="Closed",SUM(V24),0) -> 0 | X24: =IF(C24="Pipeline",SUM(V24),0) -> 0 | Y24: =IF(C24="Pipeline",COUNTIF(C12:C24,"Pipeline"),"")
E25: =IF(D25="","",EDATE(D25,1)) | J25: =IF(F25="","",F25*G25) | K25: =IF(F25="","",F25-J25) | L25: =IF(OR(K25="",I25=""),"",PMT(H25/12,I25,-K25)) | M25: =IF(F25="","",IF(C25="Dead",0,F25*C5)) | N25: =IF(F25="","",IF(C25="Dead",0,F25*C6)) | O25: =IF(OR(F25="",I25=""),"",IF(C25="Dead",0,I25*PMT(C7/12,I25,-F25)-F25)) | P25: =IF(F25="","",IF(C25<>"Closed",0,SUMIF('Referral Fees'!I11:BP11,"<="&Q25,'Referral Fees'!I25:BP25))) | Q25: =IF(F25="","",IF(C25<>"Closed",0,IF(T25="",0,IF(T25<=0,0,IF(T25>I25,I25,T25))))) | R25: =IF(C25<>"Closed","",IF(OR(E25="",I25=""),"",IF(Q25>=I25,"Paid off",EDATE(E25,Q25)))) | S25: =IF(OR(F25="",E25=""),"",(YEAR(C8)-YEAR(E25))*12+MONTH(C8)-MONTH(E25)) | T25: =IF(S25="","",S25+IF(EDATE(E25,S25)<=C8,1,0)) | U25: =IF(D25="","",DATE(YEAR(D25),MONTH(D25),1)) | V25: =IF(F25="","",M25+N25) | W25: =IF(C25="Closed",SUM(V25),0) -> 0 | X25: =IF(C25="Pipeline",SUM(V25),0) -> 0 | Y25: =IF(C25="Pipeline",COUNTIF(C12:C25,"Pipeline"),"")
E26: =IF(D26="","",EDATE(D26,1)) | J26: =IF(F26="","",F26*G26) | K26: =IF(F26="","",F26-J26) | L26: =IF(OR(K26="",I26=""),"",PMT(H26/12,I26,-K26)) | M26: =IF(F26="","",IF(C26="Dead",0,F26*C5)) | N26: =IF(F26="","",IF(C26="Dead",0,F26*C6)) | O26: =IF(OR(F26="",I26=""),"",IF(C26="Dead",0,I26*PMT(C7/12,I26,-F26)-F26)) | P26: =IF(F26="","",IF(C26<>"Closed",0,SUMIF('Referral Fees'!I11:BP11,"<="&Q26,'Referral Fees'!I26:BP26))) | Q26: =IF(F26="","",IF(C26<>"Closed",0,IF(T26="",0,IF(T26<=0,0,IF(T26>I26,I26,T26))))) | R26: =IF(C26<>"Closed","",IF(OR(E26="",I26=""),"",IF(Q26>=I26,"Paid off",EDATE(E26,Q26)))) | S26: =IF(OR(F26="",E26=""),"",(YEAR(C8)-YEAR(E26))*12+MONTH(C8)-MONTH(E26)) | T26: =IF(S26="","",S26+IF(EDATE(E26,S26)<=C8,1,0)) | U26: =IF(D26="","",DATE(YEAR(D26),MONTH(D26),1)) | V26: =IF(F26="","",M26+N26) | W26: =IF(C26="Closed",SUM(V26),0) -> 0 | X26: =IF(C26="Pipeline",SUM(V26),0) -> 0 | Y26: =IF(C26="Pipeline",COUNTIF(C12:C26,"Pipeline"),"")
E27: =IF(D27="","",EDATE(D27,1)) | J27: =IF(F27="","",F27*G27) | K27: =IF(F27="","",F27-J27) | L27: =IF(OR(K27="",I27=""),"",PMT(H27/12,I27,-K27)) | M27: =IF(F27="","",IF(C27="Dead",0,F27*C5)) | N27: =IF(F27="","",IF(C27="Dead",0,F27*C6)) | O27: =IF(OR(F27="",I27=""),"",IF(C27="Dead",0,I27*PMT(C7/12,I27,-F27)-F27)) | P27: =IF(F27="","",IF(C27<>"Closed",0,SUMIF('Referral Fees'!I11:BP11,"<="&Q27,'Referral Fees'!I27:BP27))) | Q27: =IF(F27="","",IF(C27<>"Closed",0,IF(T27="",0,IF(T27<=0,0,IF(T27>I27,I27,T27))))) | R27: =IF(C27<>"Closed","",IF(OR(E27="",I27=""),"",IF(Q27>=I27,"Paid off",EDATE(E27,Q27)))) | S27: =IF(OR(F27="",E27=""),"",(YEAR(C8)-YEAR(E27))*12+MONTH(C8)-MONTH(E27)) | T27: =IF(S27="","",S27+IF(EDATE(E27,S27)<=C8,1,0)) | U27: =IF(D27="","",DATE(YEAR(D27),MONTH(D27),1)) | V27: =IF(F27="","",M27+N27) | W27: =IF(C27="Closed",SUM(V27),0) -> 0 | X27: =IF(C27="Pipeline",SUM(V27),0) -> 0 | Y27: =IF(C27="Pipeline",COUNTIF(C12:C27,"Pipeline"),"")
E28: =IF(D28="","",EDATE(D28,1)) | J28: =IF(F28="","",F28*G28) | K28: =IF(F28="","",F28-J28) | L28: =IF(OR(K28="",I28=""),"",PMT(H28/12,I28,-K28)) | M28: =IF(F28="","",IF(C28="Dead",0,F28*C5)) | N28: =IF(F28="","",IF(C28="Dead",0,F28*C6)) | O28: =IF(OR(F28="",I28=""),"",IF(C28="Dead",0,I28*PMT(C7/12,I28,-F28)-F28)) | P28: =IF(F28="","",IF(C28<>"Closed",0,SUMIF('Referral Fees'!I11:BP11,"<="&Q28,'Referral Fees'!I28:BP28))) | Q28: =IF(F28="","",IF(C28<>"Closed",0,IF(T28="",0,IF(T28<=0,0,IF(T28>I28,I28,T28))))) | R28: =IF(C28<>"Closed","",IF(OR(E28="",I28=""),"",IF(Q28>=I28,"Paid off",EDATE(E28,Q28)))) | S28: =IF(OR(F28="",E28=""),"",(YEAR(C8)-YEAR(E28))*12+MONTH(C8)-MONTH(E28)) | T28: =IF(S28="","",S28+IF(EDATE(E28,S28)<=C8,1,0)) | U28: =IF(D28="","",DATE(YEAR(D28),MONTH(D28),1)) | V28: =IF(F28="","",M28+N28) | W28: =IF(C28="Closed",SUM(V28),0) -> 0 | X28: =IF(C28="Pipeline",SUM(V28),0) -> 0 | Y28: =IF(C28="Pipeline",COUNTIF(C12:C28,"Pipeline"),"")
E29: =IF(D29="","",EDATE(D29,1)) | J29: =IF(F29="","",F29*G29) | K29: =IF(F29="","",F29-J29) | L29: =IF(OR(K29="",I29=""),"",PMT(H29/12,I29,-K29)) | M29: =IF(F29="","",IF(C29="Dead",0,F29*C5)) | N29: =IF(F29="","",IF(C29="Dead",0,F29*C6)) | O29: =IF(OR(F29="",I29=""),"",IF(C29="Dead",0,I29*PMT(C7/12,I29,-F29)-F29)) | P29: =IF(F29="","",IF(C29<>"Closed",0,SUMIF('Referral Fees'!I11:BP11,"<="&Q29,'Referral Fees'!I29:BP29))) | Q29: =IF(F29="","",IF(C29<>"Closed",0,IF(T29="",0,IF(T29<=0,0,IF(T29>I29,I29,T29))))) | R29: =IF(C29<>"Closed","",IF(OR(E29="",I29=""),"",IF(Q29>=I29,"Paid off",EDATE(E29,Q29)))) | S29: =IF(OR(F29="",E29=""),"",(YEAR(C8)-YEAR(E29))*12+MONTH(C8)-MONTH(E29)) | T29: =IF(S29="","",S29+IF(EDATE(E29,S29)<=C8,1,0)) | U29: =IF(D29="","",DATE(YEAR(D29),MONTH(D29),1)) | V29: =IF(F29="","",M29+N29) | W29: =IF(C29="Closed",SUM(V29),0) -> 0 | X29: =IF(C29="Pipeline",SUM(V29),0) -> 0 | Y29: =IF(C29="Pipeline",COUNTIF(C12:C29,"Pipeline"),"")
E30: =IF(D30="","",EDATE(D30,1)) | J30: =IF(F30="","",F30*G30) | K30: =IF(F30="","",F30-J30) | L30: =IF(OR(K30="",I30=""),"",PMT(H30/12,I30,-K30)) | M30: =IF(F30="","",IF(C30="Dead",0,F30*C5)) | N30: =IF(F30="","",IF(C30="Dead",0,F30*C6)) | O30: =IF(OR(F30="",I30=""),"",IF(C30="Dead",0,I30*PMT(C7/12,I30,-F30)-F30)) | P30: =IF(F30="","",IF(C30<>"Closed",0,SUMIF('Referral Fees'!I11:BP11,"<="&Q30,'Referral Fees'!I30:BP30))) | Q30: =IF(F30="","",IF(C30<>"Closed",0,IF(T30="",0,IF(T30<=0,0,IF(T30>I30,I30,T30))))) | R30: =IF(C30<>"Closed","",IF(OR(E30="",I30=""),"",IF(Q30>=I30,"Paid off",EDATE(E30,Q30)))) | S30: =IF(OR(F30="",E30=""),"",(YEAR(C8)-YEAR(E30))*12+MONTH(C8)-MONTH(E30)) | T30: =IF(S30="","",S30+IF(EDATE(E30,S30)<=C8,1,0)) | U30: =IF(D30="","",DATE(YEAR(D30),MONTH(D30),1)) | V30: =IF(F30="","",M30+N30) | W30: =IF(C30="Closed",SUM(V30),0) -> 0 | X30: =IF(C30="Pipeline",SUM(V30),0) -> 0 | Y30: =IF(C30="Pipeline",COUNTIF(C12:C30,"Pipeline"),"")
E31: =IF(D31="","",EDATE(D31,1)) | J31: =IF(F31="","",F31*G31) | K31: =IF(F31="","",F31-J31) | L31: =IF(OR(K31="",I31=""),"",PMT(H31/12,I31,-K31)) | M31: =IF(F31="","",IF(C31="Dead",0,F31*C5)) | N31: =IF(F31="","",IF(C31="Dead",0,F31*C6)) | O31: =IF(OR(F31="",I31=""),"",IF(C31="Dead",0,I31*PMT(C7/12,I31,-F31)-F31)) | P31: =IF(F31="","",IF(C31<>"Closed",0,SUMIF('Referral Fees'!I11:BP11,"<="&Q31,'Referral Fees'!I31:BP31))) | Q31: =IF(F31="","",IF(C31<>"Closed",0,IF(T31="",0,IF(T31<=0,0,IF(T31>I31,I31,T31))))) | R31: =IF(C31<>"Closed","",IF(OR(E31="",I31=""),"",IF(Q31>=I31,"Paid off",EDATE(E31,Q31)))) | S31: =IF(OR(F31="",E31=""),"",(YEAR(C8)-YEAR(E31))*12+MONTH(C8)-MONTH(E31)) | T31: =IF(S31="","",S31+IF(EDATE(E31,S31)<=C8,1,0)) | U31: =IF(D31="","",DATE(YEAR(D31),MONTH(D31),1)) | V31: =IF(F31="","",M31+N31) | W31: =IF(C31="Closed",SUM(V31),0) -> 0 | X31: =IF(C31="Pipeline",SUM(V31),0) -> 0 | Y31: =IF(C31="Pipeline",COUNTIF(C12:C31,"Pipeline"),"")
E32: =IF(D32="","",EDATE(D32,1)) | J32: =IF(F32="","",F32*G32) | K32: =IF(F32="","",F32-J32) | L32: =IF(OR(K32="",I32=""),"",PMT(H32/12,I32,-K32)) | M32: =IF(F32="","",IF(C32="Dead",0,F32*C5)) | N32: =IF(F32="","",IF(C32="Dead",0,F32*C6)) | O32: =IF(OR(F32="",I32=""),"",IF(C32="Dead",0,I32*PMT(C7/12,I32,-F32)-F32)) | P32: =IF(F32="","",IF(C32<>"Closed",0,SUMIF('Referral Fees'!I11:BP11,"<="&Q32,'Referral Fees'!I32:BP32))) | Q32: =IF(F32="","",IF(C32<>"Closed",0,IF(T32="",0,IF(T32<=0,0,IF(T32>I32,I32,T32))))) | R32: =IF(C32<>"Closed","",IF(OR(E32="",I32=""),"",IF(Q32>=I32,"Paid off",EDATE(E32,Q32)))) | S32: =IF(OR(F32="",E32=""),"",(YEAR(C8)-YEAR(E32))*12+MONTH(C8)-MONTH(E32)) | T32: =IF(S32="","",S32+IF(EDATE(E32,S32)<=C8,1,0)) | U32: =IF(D32="","",DATE(YEAR(D32),MONTH(D32),1)) | V32: =IF(F32="","",M32+N32) | W32: =IF(C32="Closed",SUM(V32),0) -> 0 | X32: =IF(C32="Pipeline",SUM(V32),0) -> 0 | Y32: =IF(C32="Pipeline",COUNTIF(C12:C32,"Pipeline"),"")
E33: =IF(D33="","",EDATE(D33,1)) | J33: =IF(F33="","",F33*G33) | K33: =IF(F33="","",F33-J33) | L33: =IF(OR(K33="",I33=""),"",PMT(H33/12,I33,-K33)) | M33: =IF(F33="","",IF(C33="Dead",0,F33*C5)) | N33: =IF(F33="","",IF(C33="Dead",0,F33*C6)) | O33: =IF(OR(F33="",I33=""),"",IF(C33="Dead",0,I33*PMT(C7/12,I33,-F33)-F33)) | P33: =IF(F33="","",IF(C33<>"Closed",0,SUMIF('Referral Fees'!I11:BP11,"<="&Q33,'Referral Fees'!I33:BP33))) | Q33: =IF(F33="","",IF(C33<>"Closed",0,IF(T33="",0,IF(T33<=0,0,IF(T33>I33,I33,T33))))) | R33: =IF(C33<>"Closed","",IF(OR(E33="",I33=""),"",IF(Q33>=I33,"Paid off",EDATE(E33,Q33)))) | S33: =IF(OR(F33="",E33=""),"",(YEAR(C8)-YEAR(E33))*12+MONTH(C8)-MONTH(E33)) | T33: =IF(S33="","",S33+IF(EDATE(E33,S33)<=C8,1,0)) | U33: =IF(D33="","",DATE(YEAR(D33),MONTH(D33),1)) | V33: =IF(F33="","",M33+N33) | W33: =IF(C33="Closed",SUM(V33),0) -> 0 | X33: =IF(C33="Pipeline",SUM(V33),0) -> 0 | Y33: =IF(C33="Pipeline",COUNTIF(C12:C33,"Pipeline"),"")
E34: =IF(D34="","",EDATE(D34,1)) | J34: =IF(F34="","",F34*G34) | K34: =IF(F34="","",F34-J34) | L34: =IF(OR(K34="",I34=""),"",PMT(H34/12,I34,-K34)) | M34: =IF(F34="","",IF(C34="Dead",0,F34*C5)) | N34: =IF(F34="","",IF(C34="Dead",0,F34*C6)) | O34: =IF(OR(F34="",I34=""),"",IF(C34="Dead",0,I34*PMT(C7/12,I34,-F34)-F34)) | P34: =IF(F34="","",IF(C34<>"Closed",0,SUMIF('Referral Fees'!I11:BP11,"<="&Q34,'Referral Fees'!I34:BP34))) | Q34: =IF(F34="","",IF(C34<>"Closed",0,IF(T34="",0,IF(T34<=0,0,IF(T34>I34,I34,T34))))) | R34: =IF(C34<>"Closed","",IF(OR(E34="",I34=""),"",IF(Q34>=I34,"Paid off",EDATE(E34,Q34)))) | S34: =IF(OR(F34="",E34=""),"",(YEAR(C8)-YEAR(E34))*12+MONTH(C8)-MONTH(E34)) | T34: =IF(S34="","",S34+IF(EDATE(E34,S34)<=C8,1,0)) | U34: =IF(D34="","",DATE(YEAR(D34),MONTH(D34),1)) | V34: =IF(F34="","",M34+N34) | W34: =IF(C34="Closed",SUM(V34),0) -> 0 | X34: =IF(C34="Pipeline",SUM(V34),0) -> 0 | Y34: =IF(C34="Pipeline",COUNTIF(C12:C34,"Pipeline"),"")
E35: =IF(D35="","",EDATE(D35,1)) | J35: =IF(F35="","",F35*G35) | K35: =IF(F35="","",F35-J35) | L35: =IF(OR(K35="",I35=""),"",PMT(H35/12,I35,-K35)) | M35: =IF(F35="","",IF(C35="Dead",0,F35*C5)) | N35: =IF(F35="","",IF(C35="Dead",0,F35*C6)) | O35: =IF(OR(F35="",I35=""),"",IF(C35="Dead",0,I35*PMT(C7/12,I35,-F35)-F35)) | P35: =IF(F35="","",IF(C35<>"Closed",0,SUMIF('Referral Fees'!I11:BP11,"<="&Q35,'Referral Fees'!I35:BP35))) | Q35: =IF(F35="","",IF(C35<>"Closed",0,IF(T35="",0,IF(T35<=0,0,IF(T35>I35,I35,T35))))) | R35: =IF(C35<>"Closed","",IF(OR(E35="",I35=""),"",IF(Q35>=I35,"Paid off",EDATE(E35,Q35)))) | S35: =IF(OR(F35="",E35=""),"",(YEAR(C8)-YEAR(E35))*12+MONTH(C8)-MONTH(E35)) | T35: =IF(S35="","",S35+IF(EDATE(E35,S35)<=C8,1,0)) | U35: =IF(D35="","",DATE(YEAR(D35),MONTH(D35),1)) | V35: =IF(F35="","",M35+N35) | W35: =IF(C35="Closed",SUM(V35),0) -> 0 | X35: =IF(C35="Pipeline",SUM(V35),0) -> 0 | Y35: =IF(C35="Pipeline",COUNTIF(C12:C35,"Pipeline"),"")
E36: =IF(D36="","",EDATE(D36,1)) | J36: =IF(F36="","",F36*G36) | K36: =IF(F36="","",F36-J36) | L36: =IF(OR(K36="",I36=""),"",PMT(H36/12,I36,-K36)) | M36: =IF(F36="","",IF(C36="Dead",0,F36*C5)) | N36: =IF(F36="","",IF(C36="Dead",0,F36*C6)) | O36: =IF(OR(F36="",I36=""),"",IF(C36="Dead",0,I36*PMT(C7/12,I36,-F36)-F36)) | P36: =IF(F36="","",IF(C36<>"Closed",0,SUMIF('Referral Fees'!I11:BP11,"<="&Q36,'Referral Fees'!I36:BP36))) | Q36: =IF(F36="","",IF(C36<>"Closed",0,IF(T36="",0,IF(T36<=0,0,IF(T36>I36,I36,T36))))) | R36: =IF(C36<>"Closed","",IF(OR(E36="",I36=""),"",IF(Q36>=I36,"Paid off",EDATE(E36,Q36)))) | S36: =IF(OR(F36="",E36=""),"",(YEAR(C8)-YEAR(E36))*12+MONTH(C8)-MONTH(E36)) | T36: =IF(S36="","",S36+IF(EDATE(E36,S36)<=C8,1,0)) | U36: =IF(D36="","",DATE(YEAR(D36),MONTH(D36),1)) | V36: =IF(F36="","",M36+N36) | W36: =IF(C36="Closed",SUM(V36),0) -> 0 | X36: =IF(C36="Pipeline",SUM(V36),0) -> 0 | Y36: =IF(C36="Pipeline",COUNTIF(C12:C36,"Pipeline"),"")
E37: =IF(D37="","",EDATE(D37,1)) | J37: =IF(F37="","",F37*G37) | K37: =IF(F37="","",F37-J37) | L37: =IF(OR(K37="",I37=""),"",PMT(H37/12,I37,-K37)) | M37: =IF(F37="","",IF(C37="Dead",0,F37*C5)) | N37: =IF(F37="","",IF(C37="Dead",0,F37*C6)) | O37: =IF(OR(F37="",I37=""),"",IF(C37="Dead",0,I37*PMT(C7/12,I37,-F37)-F37)) | P37: =IF(F37="","",IF(C37<>"Closed",0,SUMIF('Referral Fees'!I11:BP11,"<="&Q37,'Referral Fees'!I37:BP37))) | Q37: =IF(F37="","",IF(C37<>"Closed",0,IF(T37="",0,IF(T37<=0,0,IF(T37>I37,I37,T37))))) | R37: =IF(C37<>"Closed","",IF(OR(E37="",I37=""),"",IF(Q37>=I37,"Paid off",EDATE(E37,Q37)))) | S37: =IF(OR(F37="",E37=""),"",(YEAR(C8)-YEAR(E37))*12+MONTH(C8)-MONTH(E37)) | T37: =IF(S37="","",S37+IF(EDATE(E37,S37)<=C8,1,0)) | U37: =IF(D37="","",DATE(YEAR(D37),MONTH(D37),1)) | V37: =IF(F37="","",M37+N37) | W37: =IF(C37="Closed",SUM(V37),0) -> 0 | X37: =IF(C37="Pipeline",SUM(V37),0) -> 0 | Y37: =IF(C37="Pipeline",COUNTIF(C12:C37,"Pipeline"),"")
E38: =IF(D38="","",EDATE(D38,1)) | J38: =IF(F38="","",F38*G38) | K38: =IF(F38="","",F38-J38) | L38: =IF(OR(K38="",I38=""),"",PMT(H38/12,I38,-K38)) | M38: =IF(F38="","",IF(C38="Dead",0,F38*C5)) | N38: =IF(F38="","",IF(C38="Dead",0,F38*C6)) | O38: =IF(OR(F38="",I38=""),"",IF(C38="Dead",0,I38*PMT(C7/12,I38,-F38)-F38)) | P38: =IF(F38="","",IF(C38<>"Closed",0,SUMIF('Referral Fees'!I11:BP11,"<="&Q38,'Referral Fees'!I38:BP38))) | Q38: =IF(F38="","",IF(C38<>"Closed",0,IF(T38="",0,IF(T38<=0,0,IF(T38>I38,I38,T38))))) | R38: =IF(C38<>"Closed","",IF(OR(E38="",I38=""),"",IF(Q38>=I38,"Paid off",EDATE(E38,Q38)))) | S38: =IF(OR(F38="",E38=""),"",(YEAR(C8)-YEAR(E38))*12+MONTH(C8)-MONTH(E38)) | T38: =IF(S38="","",S38+IF(EDATE(E38,S38)<=C8,1,0)) | U38: =IF(D38="","",DATE(YEAR(D38),MONTH(D38),1)) | V38: =IF(F38="","",M38+N38) | W38: =IF(C38="Closed",SUM(V38),0) -> 0 | X38: =IF(C38="Pipeline",SUM(V38),0) -> 0 | Y38: =IF(C38="Pipeline",COUNTIF(C12:C38,"Pipeline"),"")
E39: =IF(D39="","",EDATE(D39,1)) | J39: =IF(F39="","",F39*G39) | K39: =IF(F39="","",F39-J39) | L39: =IF(OR(K39="",I39=""),"",PMT(H39/12,I39,-K39)) | M39: =IF(F39="","",IF(C39="Dead",0,F39*C5)) | N39: =IF(F39="","",IF(C39="Dead",0,F39*C6)) | O39: =IF(OR(F39="",I39=""),"",IF(C39="Dead",0,I39*PMT(C7/12,I39,-F39)-F39)) | P39: =IF(F39="","",IF(C39<>"Closed",0,SUMIF('Referral Fees'!I11:BP11,"<="&Q39,'Referral Fees'!I39:BP39))) | Q39: =IF(F39="","",IF(C39<>"Closed",0,IF(T39="",0,IF(T39<=0,0,IF(T39>I39,I39,T39))))) | R39: =IF(C39<>"Closed","",IF(OR(E39="",I39=""),"",IF(Q39>=I39,"Paid off",EDATE(E39,Q39)))) | S39: =IF(OR(F39="",E39=""),"",(YEAR(C8)-YEAR(E39))*12+MONTH(C8)-MONTH(E39)) | T39: =IF(S39="","",S39+IF(EDATE(E39,S39)<=C8,1,0)) | U39: =IF(D39="","",DATE(YEAR(D39),MONTH(D39),1)) | V39: =IF(F39="","",M39+N39) | W39: =IF(C39="Closed",SUM(V39),0) -> 0 | X39: =IF(C39="Pipeline",SUM(V39),0) -> 0 | Y39: =IF(C39="Pipeline",COUNTIF(C12:C39,"Pipeline"),"")
E40: =IF(D40="","",EDATE(D40,1)) | J40: =IF(F40="","",F40*G40) | K40: =IF(F40="","",F40-J40) | L40: =IF(OR(K40="",I40=""),"",PMT(H40/12,I40,-K40)) | M40: =IF(F40="","",IF(C40="Dead",0,F40*C5)) | N40: =IF(F40="","",IF(C40="Dead",0,F40*C6)) | O40: =IF(OR(F40="",I40=""),"",IF(C40="Dead",0,I40*PMT(C7/12,I40,-F40)-F40)) | P40: =IF(F40="","",IF(C40<>"Closed",0,SUMIF('Referral Fees'!I11:BP11,"<="&Q40,'Referral Fees'!I40:BP40))) | Q40: =IF(F40="","",IF(C40<>"Closed",0,IF(T40="",0,IF(T40<=0,0,IF(T40>I40,I40,T40))))) | R40: =IF(C40<>"Closed","",IF(OR(E40="",I40=""),"",IF(Q40>=I40,"Paid off",EDATE(E40,Q40)))) | S40: =IF(OR(F40="",E40=""),"",(YEAR(C8)-YEAR(E40))*12+MONTH(C8)-MONTH(E40)) | T40: =IF(S40="","",S40+IF(EDATE(E40,S40)<=C8,1,0)) | U40: =IF(D40="","",DATE(YEAR(D40),MONTH(D40),1)) | V40: =IF(F40="","",M40+N40) | W40: =IF(C40="Closed",SUM(V40),0) -> 0 | X40: =IF(C40="Pipeline",SUM(V40),0) -> 0 | Y40: =IF(C40="Pipeline",COUNTIF(C12:C40,"Pipeline"),"")
E41: =IF(D41="","",EDATE(D41,1)) | J41: =IF(F41="","",F41*G41) | K41: =IF(F41="","",F41-J41) | L41: =IF(OR(K41="",I41=""),"",PMT(H41/12,I41,-K41)) | M41: =IF(F41="","",IF(C41="Dead",0,F41*C5)) | N41: =IF(F41="","",IF(C41="Dead",0,F41*C6)) | O41: =IF(OR(F41="",I41=""),"",IF(C41="Dead",0,I41*PMT(C7/12,I41,-F41)-F41)) | P41: =IF(F41="","",IF(C41<>"Closed",0,SUMIF('Referral Fees'!I11:BP11,"<="&Q41,'Referral Fees'!I41:BP41))) | Q41: =IF(F41="","",IF(C41<>"Closed",0,IF(T41="",0,IF(T41<=0,0,IF(T41>I41,I41,T41))))) | R41: =IF(C41<>"Closed","",IF(OR(E41="",I41=""),"",IF(Q41>=I41,"Paid off",EDATE(E41,Q41)))) | S41: =IF(OR(F41="",E41=""),"",(YEAR(C8)-YEAR(E41))*12+MONTH(C8)-MONTH(E41)) | T41: =IF(S41="","",S41+IF(EDATE(E41,S41)<=C8,1,0)) | U41: =IF(D41="","",DATE(YEAR(D41),MONTH(D41),1)) | V41: =IF(F41="","",M41+N41) | W41: =IF(C41="Closed",SUM(V41),0) -> 0 | X41: =IF(C41="Pipeline",SUM(V41),0) -> 0 | Y41: =IF(C41="Pipeline",COUNTIF(C12:C41,"Pipeline"),"")
E42: =IF(D42="","",EDATE(D42,1)) | J42: =IF(F42="","",F42*G42) | K42: =IF(F42="","",F42-J42) | L42: =IF(OR(K42="",I42=""),"",PMT(H42/12,I42,-K42)) | M42: =IF(F42="","",IF(C42="Dead",0,F42*C5)) | N42: =IF(F42="","",IF(C42="Dead",0,F42*C6)) | O42: =IF(OR(F42="",I42=""),"",IF(C42="Dead",0,I42*PMT(C7/12,I42,-F42)-F42)) | P42: =IF(F42="","",IF(C42<>"Closed",0,SUMIF('Referral Fees'!I11:BP11,"<="&Q42,'Referral Fees'!I42:BP42))) | Q42: =IF(F42="","",IF(C42<>"Closed",0,IF(T42="",0,IF(T42<=0,0,IF(T42>I42,I42,T42))))) | R42: =IF(C42<>"Closed","",IF(OR(E42="",I42=""),"",IF(Q42>=I42,"Paid off",EDATE(E42,Q42)))) | S42: =IF(OR(F42="",E42=""),"",(YEAR(C8)-YEAR(E42))*12+MONTH(C8)-MONTH(E42)) | T42: =IF(S42="","",S42+IF(EDATE(E42,S42)<=C8,1,0)) | U42: =IF(D42="","",DATE(YEAR(D42),MONTH(D42),1)) | V42: =IF(F42="","",M42+N42) | W42: =IF(C42="Closed",SUM(V42),0) -> 0 | X42: =IF(C42="Pipeline",SUM(V42),0) -> 0 | Y42: =IF(C42="Pipeline",COUNTIF(C12:C42,"Pipeline"),"")
E43: =IF(D43="","",EDATE(D43,1)) | J43: =IF(F43="","",F43*G43) | K43: =IF(F43="","",F43-J43) | L43: =IF(OR(K43="",I43=""),"",PMT(H43/12,I43,-K43)) | M43: =IF(F43="","",IF(C43="Dead",0,F43*C5)) | N43: =IF(F43="","",IF(C43="Dead",0,F43*C6)) | O43: =IF(OR(F43="",I43=""),"",IF(C43="Dead",0,I43*PMT(C7/12,I43,-F43)-F43)) | P43: =IF(F43="","",IF(C43<>"Closed",0,SUMIF('Referral Fees'!I11:BP11,"<="&Q43,'Referral Fees'!I43:BP43))) | Q43: =IF(F43="","",IF(C43<>"Closed",0,IF(T43="",0,IF(T43<=0,0,IF(T43>I43,I43,T43))))) | R43: =IF(C43<>"Closed","",IF(OR(E43="",I43=""),"",IF(Q43>=I43,"Paid off",EDATE(E43,Q43)))) | S43: =IF(OR(F43="",E43=""),"",(YEAR(C8)-YEAR(E43))*12+MONTH(C8)-MONTH(E43)) | T43: =IF(S43="","",S43+IF(EDATE(E43,S43)<=C8,1,0)) | U43: =IF(D43="","",DATE(YEAR(D43),MONTH(D43),1)) | V43: =IF(F43="","",M43+N43) | W43: =IF(C43="Closed",SUM(V43),0) -> 0 | X43: =IF(C43="Pipeline",SUM(V43),0) -> 0 | Y43: =IF(C43="Pipeline",COUNTIF(C12:C43,"Pipeline"),"")
E44: =IF(D44="","",EDATE(D44,1)) | J44: =IF(F44="","",F44*G44) | K44: =IF(F44="","",F44-J44) | L44: =IF(OR(K44="",I44=""),"",PMT(H44/12,I44,-K44)) | M44: =IF(F44="","",IF(C44="Dead",0,F44*C5)) | N44: =IF(F44="","",IF(C44="Dead",0,F44*C6)) | O44: =IF(OR(F44="",I44=""),"",IF(C44="Dead",0,I44*PMT(C7/12,I44,-F44)-F44)) | P44: =IF(F44="","",IF(C44<>"Closed",0,SUMIF('Referral Fees'!I11:BP11,"<="&Q44,'Referral Fees'!I44:BP44))) | Q44: =IF(F44="","",IF(C44<>"Closed",0,IF(T44="",0,IF(T44<=0,0,IF(T44>I44,I44,T44))))) | R44: =IF(C44<>"Closed","",IF(OR(E44="",I44=""),"",IF(Q44>=I44,"Paid off",EDATE(E44,Q44)))) | S44: =IF(OR(F44="",E44=""),"",(YEAR(C8)-YEAR(E44))*12+MONTH(C8)-MONTH(E44)) | T44: =IF(S44="","",S44+IF(EDATE(E44,S44)<=C8,1,0)) | U44: =IF(D44="","",DATE(YEAR(D44),MONTH(D44),1)) | V44: =IF(F44="","",M44+N44) | W44: =IF(C44="Closed",SUM(V44),0) -> 0 | X44: =IF(C44="Pipeline",SUM(V44),0) -> 0 | Y44: =IF(C44="Pipeline",COUNTIF(C12:C44,"Pipeline"),"")
E45: =IF(D45="","",EDATE(D45,1)) | J45: =IF(F45="","",F45*G45) | K45: =IF(F45="","",F45-J45) | L45: =IF(OR(K45="",I45=""),"",PMT(H45/12,I45,-K45)) | M45: =IF(F45="","",IF(C45="Dead",0,F45*C5)) | N45: =IF(F45="","",IF(C45="Dead",0,F45*C6)) | O45: =IF(OR(F45="",I45=""),"",IF(C45="Dead",0,I45*PMT(C7/12,I45,-F45)-F45)) | P45: =IF(F45="","",IF(C45<>"Closed",0,SUMIF('Referral Fees'!I11:BP11,"<="&Q45,'Referral Fees'!I45:BP45))) | Q45: =IF(F45="","",IF(C45<>"Closed",0,IF(T45="",0,IF(T45<=0,0,IF(T45>I45,I45,T45))))) | R45: =IF(C45<>"Closed","",IF(OR(E45="",I45=""),"",IF(Q45>=I45,"Paid off",EDATE(E45,Q45)))) | S45: =IF(OR(F45="",E45=""),"",(YEAR(C8)-YEAR(E45))*12+MONTH(C8)-MONTH(E45)) | T45: =IF(S45="","",S45+IF(EDATE(E45,S45)<=C8,1,0)) | U45: =IF(D45="","",DATE(YEAR(D45),MONTH(D45),1)) | V45: =IF(F45="","",M45+N45) | W45: =IF(C45="Closed",SUM(V45),0) -> 0 | X45: =IF(C45="Pipeline",SUM(V45),0) -> 0 | Y45: =IF(C45="Pipeline",COUNTIF(C12:C45,"Pipeline"),"")
E46: =IF(D46="","",EDATE(D46,1)) | J46: =IF(F46="","",F46*G46) | K46: =IF(F46="","",F46-J46) | L46: =IF(OR(K46="",I46=""),"",PMT(H46/12,I46,-K46)) | M46: =IF(F46="","",IF(C46="Dead",0,F46*C5)) | N46: =IF(F46="","",IF(C46="Dead",0,F46*C6)) | O46: =IF(OR(F46="",I46=""),"",IF(C46="Dead",0,I46*PMT(C7/12,I46,-F46)-F46)) | P46: =IF(F46="","",IF(C46<>"Closed",0,SUMIF('Referral Fees'!I11:BP11,"<="&Q46,'Referral Fees'!I46:BP46))) | Q46: =IF(F46="","",IF(C46<>"Closed",0,IF(T46="",0,IF(T46<=0,0,IF(T46>I46,I46,T46))))) | R46: =IF(C46<>"Closed","",IF(OR(E46="",I46=""),"",IF(Q46>=I46,"Paid off",EDATE(E46,Q46)))) | S46: =IF(OR(F46="",E46=""),"",(YEAR(C8)-YEAR(E46))*12+MONTH(C8)-MONTH(E46)) | T46: =IF(S46="","",S46+IF(EDATE(E46,S46)<=C8,1,0)) | U46: =IF(D46="","",DATE(YEAR(D46),MONTH(D46),1)) | V46: =IF(F46="","",M46+N46) | W46: =IF(C46="Closed",SUM(V46),0) -> 0 | X46: =IF(C46="Pipeline",SUM(V46),0) -> 0 | Y46: =IF(C46="Pipeline",COUNTIF(C12:C46,"Pipeline"),"")
E47: =IF(D47="","",EDATE(D47,1)) | J47: =IF(F47="","",F47*G47) | K47: =IF(F47="","",F47-J47) | L47: =IF(OR(K47="",I47=""),"",PMT(H47/12,I47,-K47)) | M47: =IF(F47="","",IF(C47="Dead",0,F47*C5)) | N47: =IF(F47="","",IF(C47="Dead",0,F47*C6)) | O47: =IF(OR(F47="",I47=""),"",IF(C47="Dead",0,I47*PMT(C7/12,I47,-F47)-F47)) | P47: =IF(F47="","",IF(C47<>"Closed",0,SUMIF('Referral Fees'!I11:BP11,"<="&Q47,'Referral Fees'!I47:BP47))) | Q47: =IF(F47="","",IF(C47<>"Closed",0,IF(T47="",0,IF(T47<=0,0,IF(T47>I47,I47,T47))))) | R47: =IF(C47<>"Closed","",IF(OR(E47="",I47=""),"",IF(Q47>=I47,"Paid off",EDATE(E47,Q47)))) | S47: =IF(OR(F47="",E47=""),"",(YEAR(C8)-YEAR(E47))*12+MONTH(C8)-MONTH(E47)) | T47: =IF(S47="","",S47+IF(EDATE(E47,S47)<=C8,1,0)) | U47: =IF(D47="","",DATE(YEAR(D47),MONTH(D47),1)) | V47: =IF(F47="","",M47+N47) | W47: =IF(C47="Closed",SUM(V47),0) -> 0 | X47: =IF(C47="Pipeline",SUM(V47),0) -> 0 | Y47: =IF(C47="Pipeline",COUNTIF(C12:C47,"Pipeline"),"")
E48: =IF(D48="","",EDATE(D48,1)) | J48: =IF(F48="","",F48*G48) | K48: =IF(F48="","",F48-J48) | L48: =IF(OR(K48="",I48=""),"",PMT(H48/12,I48,-K48)) | M48: =IF(F48="","",IF(C48="Dead",0,F48*C5)) | N48: =IF(F48="","",IF(C48="Dead",0,F48*C6)) | O48: =IF(OR(F48="",I48=""),"",IF(C48="Dead",0,I48*PMT(C7/12,I48,-F48)-F48)) | P48: =IF(F48="","",IF(C48<>"Closed",0,SUMIF('Referral Fees'!I11:BP11,"<="&Q48,'Referral Fees'!I48:BP48))) | Q48: =IF(F48="","",IF(C48<>"Closed",0,IF(T48="",0,IF(T48<=0,0,IF(T48>I48,I48,T48))))) | R48: =IF(C48<>"Closed","",IF(OR(E48="",I48=""),"",IF(Q48>=I48,"Paid off",EDATE(E48,Q48)))) | S48: =IF(OR(F48="",E48=""),"",(YEAR(C8)-YEAR(E48))*12+MONTH(C8)-MONTH(E48)) | T48: =IF(S48="","",S48+IF(EDATE(E48,S48)<=C8,1,0)) | U48: =IF(D48="","",DATE(YEAR(D48),MONTH(D48),1)) | V48: =IF(F48="","",M48+N48) | W48: =IF(C48="Closed",SUM(V48),0) -> 0 | X48: =IF(C48="Pipeline",SUM(V48),0) -> 0 | Y48: =IF(C48="Pipeline",COUNTIF(C12:C48,"Pipeline"),"")
E49: =IF(D49="","",EDATE(D49,1)) | J49: =IF(F49="","",F49*G49) | K49: =IF(F49="","",F49-J49) | L49: =IF(OR(K49="",I49=""),"",PMT(H49/12,I49,-K49)) | M49: =IF(F49="","",IF(C49="Dead",0,F49*C5)) | N49: =IF(F49="","",IF(C49="Dead",0,F49*C6)) | O49: =IF(OR(F49="",I49=""),"",IF(C49="Dead",0,I49*PMT(C7/12,I49,-F49)-F49)) | P49: =IF(F49="","",IF(C49<>"Closed",0,SUMIF('Referral Fees'!I11:BP11,"<="&Q49,'Referral Fees'!I49:BP49))) | Q49: =IF(F49="","",IF(C49<>"Closed",0,IF(T49="",0,IF(T49<=0,0,IF(T49>I49,I49,T49))))) | R49: =IF(C49<>"Closed","",IF(OR(E49="",I49=""),"",IF(Q49>=I49,"Paid off",EDATE(E49,Q49)))) | S49: =IF(OR(F49="",E49=""),"",(YEAR(C8)-YEAR(E49))*12+MONTH(C8)-MONTH(E49)) | T49: =IF(S49="","",S49+IF(EDATE(E49,S49)<=C8,1,0)) | U49: =IF(D49="","",DATE(YEAR(D49),MONTH(D49),1)) | V49: =IF(F49="","",M49+N49) | W49: =IF(C49="Closed",SUM(V49),0) -> 0 | X49: =IF(C49="Pipeline",SUM(V49),0) -> 0 | Y49: =IF(C49="Pipeline",COUNTIF(C12:C49,"Pipeline"),"")
E50: =IF(D50="","",EDATE(D50,1)) | J50: =IF(F50="","",F50*G50) | K50: =IF(F50="","",F50-J50) | L50: =IF(OR(K50="",I50=""),"",PMT(H50/12,I50,-K50)) | M50: =IF(F50="","",IF(C50="Dead",0,F50*C5)) | N50: =IF(F50="","",IF(C50="Dead",0,F50*C6)) | O50: =IF(OR(F50="",I50=""),"",IF(C50="Dead",0,I50*PMT(C7/12,I50,-F50)-F50)) | P50: =IF(F50="","",IF(C50<>"Closed",0,SUMIF('Referral Fees'!I11:BP11,"<="&Q50,'Referral Fees'!I50:BP50))) | Q50: =IF(F50="","",IF(C50<>"Closed",0,IF(T50="",0,IF(T50<=0,0,IF(T50>I50,I50,T50))))) | R50: =IF(C50<>"Closed","",IF(OR(E50="",I50=""),"",IF(Q50>=I50,"Paid off",EDATE(E50,Q50)))) | S50: =IF(OR(F50="",E50=""),"",(YEAR(C8)-YEAR(E50))*12+MONTH(C8)-MONTH(E50)) | T50: =IF(S50="","",S50+IF(EDATE(E50,S50)<=C8,1,0)) | U50: =IF(D50="","",DATE(YEAR(D50),MONTH(D50),1)) | V50: =IF(F50="","",M50+N50) | W50: =IF(C50="Closed",SUM(V50),0) -> 0 | X50: =IF(C50="Pipeline",SUM(V50),0) -> 0 | Y50: =IF(C50="Pipeline",COUNTIF(C12:C50,"Pipeline"),"")
E51: =IF(D51="","",EDATE(D51,1)) | J51: =IF(F51="","",F51*G51) | K51: =IF(F51="","",F51-J51) | L51: =IF(OR(K51="",I51=""),"",PMT(H51/12,I51,-K51)) | M51: =IF(F51="","",IF(C51="Dead",0,F51*C5)) | N51: =IF(F51="","",IF(C51="Dead",0,F51*C6)) | O51: =IF(OR(F51="",I51=""),"",IF(C51="Dead",0,I51*PMT(C7/12,I51,-F51)-F51)) | P51: =IF(F51="","",IF(C51<>"Closed",0,SUMIF('Referral Fees'!I11:BP11,"<="&Q51,'Referral Fees'!I51:BP51))) | Q51: =IF(F51="","",IF(C51<>"Closed",0,IF(T51="",0,IF(T51<=0,0,IF(T51>I51,I51,T51))))) | R51: =IF(C51<>"Closed","",IF(OR(E51="",I51=""),"",IF(Q51>=I51,"Paid off",EDATE(E51,Q51)))) | S51: =IF(OR(F51="",E51=""),"",(YEAR(C8)-YEAR(E51))*12+MONTH(C8)-MONTH(E51)) | T51: =IF(S51="","",S51+IF(EDATE(E51,S51)<=C8,1,0)) | U51: =IF(D51="","",DATE(YEAR(D51),MONTH(D51),1)) | V51: =IF(F51="","",M51+N51) | W51: =IF(C51="Closed",SUM(V51),0) -> 0 | X51: =IF(C51="Pipeline",SUM(V51),0) -> 0 | Y51: =IF(C51="Pipeline",COUNTIF(C12:C51,"Pipeline"),"")
E52: =IF(D52="","",EDATE(D52,1)) | J52: =IF(F52="","",F52*G52) | K52: =IF(F52="","",F52-J52) | L52: =IF(OR(K52="",I52=""),"",PMT(H52/12,I52,-K52)) | M52: =IF(F52="","",IF(C52="Dead",0,F52*C5)) | N52: =IF(F52="","",IF(C52="Dead",0,F52*C6)) | O52: =IF(OR(F52="",I52=""),"",IF(C52="Dead",0,I52*PMT(C7/12,I52,-F52)-F52)) | P52: =IF(F52="","",IF(C52<>"Closed",0,SUMIF('Referral Fees'!I11:BP11,"<="&Q52,'Referral Fees'!I52:BP52))) | Q52: =IF(F52="","",IF(C52<>"Closed",0,IF(T52="",0,IF(T52<=0,0,IF(T52>I52,I52,T52))))) | R52: =IF(C52<>"Closed","",IF(OR(E52="",I52=""),"",IF(Q52>=I52,"Paid off",EDATE(E52,Q52)))) | S52: =IF(OR(F52="",E52=""),"",(YEAR(C8)-YEAR(E52))*12+MONTH(C8)-MONTH(E52)) | T52: =IF(S52="","",S52+IF(EDATE(E52,S52)<=C8,1,0)) | U52: =IF(D52="","",DATE(YEAR(D52),MONTH(D52),1)) | V52: =IF(F52="","",M52+N52) | W52: =IF(C52="Closed",SUM(V52),0) -> 0 | X52: =IF(C52="Pipeline",SUM(V52),0) -> 0 | Y52: =IF(C52="Pipeline",COUNTIF(C12:C52,"Pipeline"),"")
E53: =IF(D53="","",EDATE(D53,1)) | J53: =IF(F53="","",F53*G53) | K53: =IF(F53="","",F53-J53) | L53: =IF(OR(K53="",I53=""),"",PMT(H53/12,I53,-K53)) | M53: =IF(F53="","",IF(C53="Dead",0,F53*C5)) | N53: =IF(F53="","",IF(C53="Dead",0,F53*C6)) | O53: =IF(OR(F53="",I53=""),"",IF(C53="Dead",0,I53*PMT(C7/12,I53,-F53)-F53)) | P53: =IF(F53="","",IF(C53<>"Closed",0,SUMIF('Referral Fees'!I11:BP11,"<="&Q53,'Referral Fees'!I53:BP53))) | Q53: =IF(F53="","",IF(C53<>"Closed",0,IF(T53="",0,IF(T53<=0,0,IF(T53>I53,I53,T53))))) | R53: =IF(C53<>"Closed","",IF(OR(E53="",I53=""),"",IF(Q53>=I53,"Paid off",EDATE(E53,Q53)))) | S53: =IF(OR(F53="",E53=""),"",(YEAR(C8)-YEAR(E53))*12+MONTH(C8)-MONTH(E53)) | T53: =IF(S53="","",S53+IF(EDATE(E53,S53)<=C8,1,0)) | U53: =IF(D53="","",DATE(YEAR(D53),MONTH(D53),1)) | V53: =IF(F53="","",M53+N53) | W53: =IF(C53="Closed",SUM(V53),0) -> 0 | X53: =IF(C53="Pipeline",SUM(V53),0) -> 0 | Y53: =IF(C53="Pipeline",COUNTIF(C12:C53,"Pipeline"),"")
E54: =IF(D54="","",EDATE(D54,1)) | J54: =IF(F54="","",F54*G54) | K54: =IF(F54="","",F54-J54) | L54: =IF(OR(K54="",I54=""),"",PMT(H54/12,I54,-K54)) | M54: =IF(F54="","",IF(C54="Dead",0,F54*C5)) | N54: =IF(F54="","",IF(C54="Dead",0,F54*C6)) | O54: =IF(OR(F54="",I54=""),"",IF(C54="Dead",0,I54*PMT(C7/12,I54,-F54)-F54)) | P54: =IF(F54="","",IF(C54<>"Closed",0,SUMIF('Referral Fees'!I11:BP11,"<="&Q54,'Referral Fees'!I54:BP54))) | Q54: =IF(F54="","",IF(C54<>"Closed",0,IF(T54="",0,IF(T54<=0,0,IF(T54>I54,I54,T54))))) | R54: =IF(C54<>"Closed","",IF(OR(E54="",I54=""),"",IF(Q54>=I54,"Paid off",EDATE(E54,Q54)))) | S54: =IF(OR(F54="",E54=""),"",(YEAR(C8)-YEAR(E54))*12+MONTH(C8)-MONTH(E54)) | T54: =IF(S54="","",S54+IF(EDATE(E54,S54)<=C8,1,0)) | U54: =IF(D54="","",DATE(YEAR(D54),MONTH(D54),1)) | V54: =IF(F54="","",M54+N54) | W54: =IF(C54="Closed",SUM(V54),0) -> 0 | X54: =IF(C54="Pipeline",SUM(V54),0) -> 0 | Y54: =IF(C54="Pipeline",COUNTIF(C12:C54,"Pipeline"),"")
E55: =IF(D55="","",EDATE(D55,1)) | J55: =IF(F55="","",F55*G55) | K55: =IF(F55="","",F55-J55) | L55: =IF(OR(K55="",I55=""),"",PMT(H55/12,I55,-K55)) | M55: =IF(F55="","",IF(C55="Dead",0,F55*C5)) | N55: =IF(F55="","",IF(C55="Dead",0,F55*C6)) | O55: =IF(OR(F55="",I55=""),"",IF(C55="Dead",0,I55*PMT(C7/12,I55,-F55)-F55)) | P55: =IF(F55="","",IF(C55<>"Closed",0,SUMIF('Referral Fees'!I11:BP11,"<="&Q55,'Referral Fees'!I55:BP55))) | Q55: =IF(F55="","",IF(C55<>"Closed",0,IF(T55="",0,IF(T55<=0,0,IF(T55>I55,I55,T55))))) | R55: =IF(C55<>"Closed","",IF(OR(E55="",I55=""),"",IF(Q55>=I55,"Paid off",EDATE(E55,Q55)))) | S55: =IF(OR(F55="",E55=""),"",(YEAR(C8)-YEAR(E55))*12+MONTH(C8)-MONTH(E55)) | T55: =IF(S55="","",S55+IF(EDATE(E55,S55)<=C8,1,0)) | U55: =IF(D55="","",DATE(YEAR(D55),MONTH(D55),1)) | V55: =IF(F55="","",M55+N55) | W55: =IF(C55="Closed",SUM(V55),0) -> 0 | X55: =IF(C55="Pipeline",SUM(V55),0) -> 0 | Y55: =IF(C55="Pipeline",COUNTIF(C12:C55,"Pipeline"),"")
E56: =IF(D56="","",EDATE(D56,1)) | J56: =IF(F56="","",F56*G56) | K56: =IF(F56="","",F56-J56) | L56: =IF(OR(K56="",I56=""),"",PMT(H56/12,I56,-K56)) | M56: =IF(F56="","",IF(C56="Dead",0,F56*C5)) | N56: =IF(F56="","",IF(C56="Dead",0,F56*C6)) | O56: =IF(OR(F56="",I56=""),"",IF(C56="Dead",0,I56*PMT(C7/12,I56,-F56)-F56)) | P56: =IF(F56="","",IF(C56<>"Closed",0,SUMIF('Referral Fees'!I11:BP11,"<="&Q56,'Referral Fees'!I56:BP56))) | Q56: =IF(F56="","",IF(C56<>"Closed",0,IF(T56="",0,IF(T56<=0,0,IF(T56>I56,I56,T56))))) | R56: =IF(C56<>"Closed","",IF(OR(E56="",I56=""),"",IF(Q56>=I56,"Paid off",EDATE(E56,Q56)))) | S56: =IF(OR(F56="",E56=""),"",(YEAR(C8)-YEAR(E56))*12+MONTH(C8)-MONTH(E56)) | T56: =IF(S56="","",S56+IF(EDATE(E56,S56)<=C8,1,0)) | U56: =IF(D56="","",DATE(YEAR(D56),MONTH(D56),1)) | V56: =IF(F56="","",M56+N56) | W56: =IF(C56="Closed",SUM(V56),0) -> 0 | X56: =IF(C56="Pipeline",SUM(V56),0) -> 0 | Y56: =IF(C56="Pipeline",COUNTIF(C12:C56,"Pipeline"),"")
E57: =IF(D57="","",EDATE(D57,1)) | J57: =IF(F57="","",F57*G57) | K57: =IF(F57="","",F57-J57) | L57: =IF(OR(K57="",I57=""),"",PMT(H57/12,I57,-K57)) | M57: =IF(F57="","",IF(C57="Dead",0,F57*C5)) | N57: =IF(F57="","",IF(C57="Dead",0,F57*C6)) | O57: =IF(OR(F57="",I57=""),"",IF(C57="Dead",0,I57*PMT(C7/12,I57,-F57)-F57)) | P57: =IF(F57="","",IF(C57<>"Closed",0,SUMIF('Referral Fees'!I11:BP11,"<="&Q57,'Referral Fees'!I57:BP57))) | Q57: =IF(F57="","",IF(C57<>"Closed",0,IF(T57="",0,IF(T57<=0,0,IF(T57>I57,I57,T57))))) | R57: =IF(C57<>"Closed","",IF(OR(E57="",I57=""),"",IF(Q57>=I57,"Paid off",EDATE(E57,Q57)))) | S57: =IF(OR(F57="",E57=""),"",(YEAR(C8)-YEAR(E57))*12+MONTH(C8)-MONTH(E57)) | T57: =IF(S57="","",S57+IF(EDATE(E57,S57)<=C8,1,0)) | U57: =IF(D57="","",DATE(YEAR(D57),MONTH(D57),1)) | V57: =IF(F57="","",M57+N57) | W57: =IF(C57="Closed",SUM(V57),0) -> 0 | X57: =IF(C57="Pipeline",SUM(V57),0) -> 0 | Y57: =IF(C57="Pipeline",COUNTIF(C12:C57,"Pipeline"),"")
E58: =IF(D58="","",EDATE(D58,1)) | J58: =IF(F58="","",F58*G58) | K58: =IF(F58="","",F58-J58) | L58: =IF(OR(K58="",I58=""),"",PMT(H58/12,I58,-K58)) | M58: =IF(F58="","",IF(C58="Dead",0,F58*C5)) | N58: =IF(F58="","",IF(C58="Dead",0,F58*C6)) | O58: =IF(OR(F58="",I58=""),"",IF(C58="Dead",0,I58*PMT(C7/12,I58,-F58)-F58)) | P58: =IF(F58="","",IF(C58<>"Closed",0,SUMIF('Referral Fees'!I11:BP11,"<="&Q58,'Referral Fees'!I58:BP58))) | Q58: =IF(F58="","",IF(C58<>"Closed",0,IF(T58="",0,IF(T58<=0,0,IF(T58>I58,I58,T58))))) | R58: =IF(C58<>"Closed","",IF(OR(E58="",I58=""),"",IF(Q58>=I58,"Paid off",EDATE(E58,Q58)))) | S58: =IF(OR(F58="",E58=""),"",(YEAR(C8)-YEAR(E58))*12+MONTH(C8)-MONTH(E58)) | T58: =IF(S58="","",S58+IF(EDATE(E58,S58)<=C8,1,0)) | U58: =IF(D58="","",DATE(YEAR(D58),MONTH(D58),1)) | V58: =IF(F58="","",M58+N58) | W58: =IF(C58="Closed",SUM(V58),0) -> 0 | X58: =IF(C58="Pipeline",SUM(V58),0) -> 0 | Y58: =IF(C58="Pipeline",COUNTIF(C12:C58,"Pipeline"),"")
E59: =IF(D59="","",EDATE(D59,1)) | J59: =IF(F59="","",F59*G59) | K59: =IF(F59="","",F59-J59) | L59: =IF(OR(K59="",I59=""),"",PMT(H59/12,I59,-K59)) | M59: =IF(F59="","",IF(C59="Dead",0,F59*C5)) | N59: =IF(F59="","",IF(C59="Dead",0,F59*C6)) | O59: =IF(OR(F59="",I59=""),"",IF(C59="Dead",0,I59*PMT(C7/12,I59,-F59)-F59)) | P59: =IF(F59="","",IF(C59<>"Closed",0,SUMIF('Referral Fees'!I11:BP11,"<="&Q59,'Referral Fees'!I59:BP59))) | Q59: =IF(F59="","",IF(C59<>"Closed",0,IF(T59="",0,IF(T59<=0,0,IF(T59>I59,I59,T59))))) | R59: =IF(C59<>"Closed","",IF(OR(E59="",I59=""),"",IF(Q59>=I59,"Paid off",EDATE(E59,Q59)))) | S59: =IF(OR(F59="",E59=""),"",(YEAR(C8)-YEAR(E59))*12+MONTH(C8)-MONTH(E59)) | T59: =IF(S59="","",S59+IF(EDATE(E59,S59)<=C8,1,0)) | U59: =IF(D59="","",DATE(YEAR(D59),MONTH(D59),1)) | V59: =IF(F59="","",M59+N59) | W59: =IF(C59="Closed",SUM(V59),0) -> 0 | X59: =IF(C59="Pipeline",SUM(V59),0) -> 0 | Y59: =IF(C59="Pipeline",COUNTIF(C12:C59,"Pipeline"),"")
E60: =IF(D60="","",EDATE(D60,1)) | J60: =IF(F60="","",F60*G60) | K60: =IF(F60="","",F60-J60) | L60: =IF(OR(K60="",I60=""),"",PMT(H60/12,I60,-K60)) | M60: =IF(F60="","",IF(C60="Dead",0,F60*C5)) | N60: =IF(F60="","",IF(C60="Dead",0,F60*C6)) | O60: =IF(OR(F60="",I60=""),"",IF(C60="Dead",0,I60*PMT(C7/12,I60,-F60)-F60)) | P60: =IF(F60="","",IF(C60<>"Closed",0,SUMIF('Referral Fees'!I11:BP11,"<="&Q60,'Referral Fees'!I60:BP60))) | Q60: =IF(F60="","",IF(C60<>"Closed",0,IF(T60="",0,IF(T60<=0,0,IF(T60>I60,I60,T60))))) | R60: =IF(C60<>"Closed","",IF(OR(E60="",I60=""),"",IF(Q60>=I60,"Paid off",EDATE(E60,Q60)))) | S60: =IF(OR(F60="",E60=""),"",(YEAR(C8)-YEAR(E60))*12+MONTH(C8)-MONTH(E60)) | T60: =IF(S60="","",S60+IF(EDATE(E60,S60)<=C8,1,0)) | U60: =IF(D60="","",DATE(YEAR(D60),MONTH(D60),1)) | V60: =IF(F60="","",M60+N60) | W60: =IF(C60="Closed",SUM(V60),0) -> 0 | X60: =IF(C60="Pipeline",SUM(V60),0) -> 0 | Y60: =IF(C60="Pipeline",COUNTIF(C12:C60,"Pipeline"),"")
E61: =IF(D61="","",EDATE(D61,1)) | J61: =IF(F61="","",F61*G61) | K61: =IF(F61="","",F61-J61) | L61: =IF(OR(K61="",I61=""),"",PMT(H61/12,I61,-K61)) | M61: =IF(F61="","",IF(C61="Dead",0,F61*C5)) | N61: =IF(F61="","",IF(C61="Dead",0,F61*C6)) | O61: =IF(OR(F61="",I61=""),"",IF(C61="Dead",0,I61*PMT(C7/12,I61,-F61)-F61)) | P61: =IF(F61="","",IF(C61<>"Closed",0,SUMIF('Referral Fees'!I11:BP11,"<="&Q61,'Referral Fees'!I61:BP61))) | Q61: =IF(F61="","",IF(C61<>"Closed",0,IF(T61="",0,IF(T61<=0,0,IF(T61>I61,I61,T61))))) | R61: =IF(C61<>"Closed","",IF(OR(E61="",I61=""),"",IF(Q61>=I61,"Paid off",EDATE(E61,Q61)))) | S61: =IF(OR(F61="",E61=""),"",(YEAR(C8)-YEAR(E61))*12+MONTH(C8)-MONTH(E61)) | T61: =IF(S61="","",S61+IF(EDATE(E61,S61)<=C8,1,0)) | U61: =IF(D61="","",DATE(YEAR(D61),MONTH(D61),1)) | V61: =IF(F61="","",M61+N61) | W61: =IF(C61="Closed",SUM(V61),0) -> 0 | X61: =IF(C61="Pipeline",SUM(V61),0) -> 0 | Y61: =IF(C61="Pipeline",COUNTIF(C12:C61,"Pipeline"),"")
A62: TOTAL | B62: (Dead loans count in amounts, not in fees) | F62: =SUM(F12:F61) -> 113627.43 | J62: =SUM(J12:J61) -> 0 | K62: =SUM(K12:K61) -> 113627.43 | M62: =SUM(M12:M61) -> 1136.2743 | N62: =SUM(N12:N61) -> 1136.2743 | O62: =SUM(O12:O61) -> 1449.9304 | P62: =SUM(P12:P61) -> 31.511325

Sheet Loan Detail
A1: Loan Detail | Tabla de Amortizacion
A2: Pick a Loan # in the blue cell B3. Everything else on this tab is calculated.
A3: Loan # | B3: 1 | D3: Costo de Equipo | E3: =IF(B8="","",INDEX(Loans!F12:F61,B8)) -> 38127.43 | F3: Fee Table (base = Costo de Equipo)
A4: Client or Company | B4: =IF(B8="","",INDEX(Loans!B12:B61,B8)) -> SAMPLE Client A (replace) | D4: Pronto % | E4: =IF(B8="","",INDEX(Loans!G12:G61,B8)) -> 0 | F4: Origination Fee | H4: =IF(B8="","",INDEX(Loans!M12:M61,B8)) -> 381.2743
A5: Status | B5: =IF(B8="","",INDEX(Loans!C12:C61,B8)) -> Closed | D5: Pronto $ | E5: =IF(B8="","",INDEX(Loans!J12:J61,B8)) -> 0 | F5: Legal/Closing Fee | H5: =IF(B8="","",INDEX(Loans!N12:N61,B8)) -> 381.2743
A6: Closing Date | B6: =IF(B8="","",INDEX(Loans!D12:D61,B8)) -> 46218 | D6: Monto a Financiar | E6: =IF(B8="","",INDEX(Loans!K12:K61,B8)) -> 38127.43 | F6: Referral Fee, lifetime | H6: =SUM(G13:G72) -> 486.52091
A7: First Payment Date | B7: =IF(B8="","",INDEX(Loans!E12:E61,B8)) -> 46249 | D7: Interes | E7: =IF(B8="","",INDEX(Loans!H12:H61,B8)) -> 0.0899 | F7: Referral Fee, first 12 months | H7: =SUM(G13:G24) -> 173.35197
A8: Row in Loans (helper) | B8: =IF(COUNTIF(Loans!A12:A61,B3)=0,"",MATCH(B3,Loans!A12:A61,0)) -> 1 | D8: Termino (mo.) | E8: =IF(B8="","",INDEX(Loans!I12:I61,B8)) -> 60 | F8: Total Fees (lifetime) | H8: =SUM(H4:H6) -> 1249.0695
D9: Pago Mensual | E9: =IF(B8="","",INDEX(Loans!L12:L61,B8)) -> 791.2777 | F9: Referral loan payment (helper) | H9: =IF(B8="","",PMT(Loans!C7/12,E8,-E3)) -> 643.56585
A10: Referral Fee shows what the fee would be if the loan were Closed. Billing tabs only use Closed loans. | F10: Check: lifetime referral vs Loans tab | H10: =IF(B8="","",IF(B5="Dead","n/a (Dead)",IF(ABS(H6-INDEX(Loans!O12:O61,B8))<0.005,"OK","CHECK"))) -> OK
A12: Pmt # | B12: Pmt Date | C12: Principal | D12: Interest | E12: P&I Pmt | F12: Balance | G12: Referral Fee | H12: Ref. loan principal (helper) | I12: Ref. loan balance (helper)
A13: =IF(B8="","",IF(E6="","",IF(E8<1,"",1))) -> 1 | B13: =IF(OR(A13="",B7=""),"",EDATE(B7,A13-1)) -> 46249 | C13: =IF(A13="","",E13-D13) -> 505.63971 | D13: =IF(A13="","",E6*E7/12) -> 285.638 | E13: =IF(A13="","",E9) -> 791.2777 | F13: =IF(A13="","",IF(A13=E8,0,E6-C13)) -> 37621.79 | G13: =IF(A13="","",E3*Loans!C7/12) -> 15.886429 | H13: =IF(A13="","",H9-G13) -> 627.67942 | I13: =IF(A13="","",IF(A13=E8,0,E3-H13)) -> 37499.751
A14: =IF(A13="","",IF(A13<E8,A13+1,"")) -> 2 | B14: =IF(OR(A14="",B7=""),"",EDATE(B7,A14-1)) -> 46280 | C14: =IF(A14="","",E14-D14) -> 509.42779 | D14: =IF(A14="","",F13*E7/12) -> 281.84991 | E14: =IF(A14="","",E9) -> 791.2777 | F14: =IF(A14="","",IF(A14=E8,0,F13-C14)) -> 37112.363 | G14: =IF(A14="","",I13*Loans!C7/12) -> 15.624896 | H14: =IF(A14="","",H9-G14) -> 627.94095 | I14: =IF(A14="","",IF(A14=E8,0,I13-H14)) -> 36871.81
A15: =IF(A14="","",IF(A14<E8,A14+1,"")) -> 3 | B15: =IF(OR(A15="",B7=""),"",EDATE(B7,A15-1)) -> 46310 | C15: =IF(A15="","",E15-D15) -> 513.24426 | D15: =IF(A15="","",F14*E7/12) -> 278.03345 | E15: =IF(A15="","",E9) -> 791.2777 | F15: =IF(A15="","",IF(A15=E8,0,F14-C15)) -> 36599.118 | G15: =IF(A15="","",I14*Loans!C7/12) -> 15.363254 | H15: =IF(A15="","",H9-G15) -> 628.20259 | I15: =IF(A15="","",IF(A15=E8,0,I14-H15)) -> 36243.607
A16: =IF(A15="","",IF(A15<E8,A15+1,"")) -> 4 | B16: =IF(OR(A16="",B7=""),"",EDATE(B7,A16-1)) -> 46341 | C16: =IF(A16="","",E16-D16) -> 517.08931 | D16: =IF(A16="","",F15*E7/12) -> 274.18839 | E16: =IF(A16="","",E9) -> 791.2777 | F16: =IF(A16="","",IF(A16=E8,0,F15-C16)) -> 36082.029 | G16: =IF(A16="","",I15*Loans!C7/12) -> 15.101503 | H16: =IF(A16="","",H9-G16) -> 628.46435 | I16: =IF(A16="","",IF(A16=E8,0,I15-H16)) -> 35615.143
A17: =IF(A16="","",IF(A16<E8,A16+1,"")) -> 5 | B17: =IF(OR(A17="",B7=""),"",EDATE(B7,A17-1)) -> 46371 | C17: =IF(A17="","",E17-D17) -> 520.96317 | D17: =IF(A17="","",F16*E7/12) -> 270.31453 | E17: =IF(A17="","",E9) -> 791.2777 | F17: =IF(A17="","",IF(A17=E8,0,F16-C17)) -> 35561.066 | G17: =IF(A17="","",I16*Loans!C7/12) -> 14.839643 | H17: =IF(A17="","",H9-G17) -> 628.72621 | I17: =IF(A17="","",IF(A17=E8,0,I16-H17)) -> 34986.416
A18: =IF(A17="","",IF(A17<E8,A17+1,"")) -> 6 | B18: =IF(OR(A18="",B7=""),"",EDATE(B7,A18-1)) -> 46402 | C18: =IF(A18="","",E18-D18) -> 524.86605 | D18: =IF(A18="","",F17*E7/12) -> 266.41165 | E18: =IF(A18="","",E9) -> 791.2777 | F18: =IF(A18="","",IF(A18=E8,0,F17-C18)) -> 35036.2 | G18: =IF(A18="","",I17*Loans!C7/12) -> 14.577674 | H18: =IF(A18="","",H9-G18) -> 628.98817 | I18: =IF(A18="","",IF(A18=E8,0,I17-H18)) -> 34357.428
A19: =IF(A18="","",IF(A18<E8,A18+1,"")) -> 7 | B19: =IF(OR(A19="",B7=""),"",EDATE(B7,A19-1)) -> 46433 | C19: =IF(A19="","",E19-D19) -> 528.79817 | D19: =IF(A19="","",F18*E7/12) -> 262.47953 | E19: =IF(A19="","",E9) -> 791.2777 | F19: =IF(A19="","",IF(A19=E8,0,F18-C19)) -> 34507.402 | G19: =IF(A19="","",I18*Loans!C7/12) -> 14.315595 | H19: =IF(A19="","",H9-G19) -> 629.25025 | I19: =IF(A19="","",IF(A19=E8,0,I18-H19)) -> 33728.178
A20: =IF(A19="","",IF(A19<E8,A19+1,"")) -> 8 | B20: =IF(OR(A20="",B7=""),"",EDATE(B7,A20-1)) -> 46461 | C20: =IF(A20="","",E20-D20) -> 532.75975 | D20: =IF(A20="","",F19*E7/12) -> 258.51795 | E20: =IF(A20="","",E9) -> 791.2777 | F20: =IF(A20="","",IF(A20=E8,0,F19-C20)) -> 33974.642 | G20: =IF(A20="","",I19*Loans!C7/12) -> 14.053408 | H20: =IF(A20="","",H9-G20) -> 629.51244 | I20: =IF(A20="","",IF(A20=E8,0,I19-H20)) -> 33098.666
A21: =IF(A20="","",IF(A20<E8,A20+1,"")) -> 9 | B21: =IF(OR(A21="",B7=""),"",EDATE(B7,A21-1)) -> 46492 | C21: =IF(A21="","",E21-D21) -> 536.75101 | D21: =IF(A21="","",F20*E7/12) -> 254.52669 | E21: =IF(A21="","",E9) -> 791.2777 | F21: =IF(A21="","",IF(A21=E8,0,F20-C21)) -> 33437.891 | G21: =IF(A21="","",I20*Loans!C7/12) -> 13.791111 | H21: =IF(A21="","",H9-G21) -> 629.77474 | I21: =IF(A21="","",IF(A21=E8,0,I20-H21)) -> 32468.891
A22: =IF(A21="","",IF(A21<E8,A21+1,"")) -> 10 | B22: =IF(OR(A22="",B7=""),"",EDATE(B7,A22-1)) -> 46522 | C22: =IF(A22="","",E22-D22) -> 540.77217 | D22: =IF(A22="","",F21*E7/12) -> 250.50553 | E22: =IF(A22="","",E9) -> 791.2777 | F22: =IF(A22="","",IF(A22=E8,0,F21-C22)) -> 32897.119 | G22: =IF(A22="","",I21*Loans!C7/12) -> 13.528705 | H22: =IF(A22="","",H9-G22) -> 630.03714 | I22: =IF(A22="","",IF(A22=E8,0,I21-H22)) -> 31838.854
A23: =IF(A22="","",IF(A22<E8,A22+1,"")) -> 11 | B23: =IF(OR(A23="",B7=""),"",EDATE(B7,A23-1)) -> 46553 | C23: =IF(A23="","",E23-D23) -> 544.82346 | D23: =IF(A23="","",F22*E7/12) -> 246.45425 | E23: =IF(A23="","",E9) -> 791.2777 | F23: =IF(A23="","",IF(A23=E8,0,F22-C23)) -> 32352.295 | G23: =IF(A23="","",I22*Loans!C7/12) -> 13.266189 | H23: =IF(A23="","",H9-G23) -> 630.29966 | I23: =IF(A23="","",IF(A23=E8,0,I22-H23)) -> 31208.554
A24: =IF(A23="","",IF(A23<E8,A23+1,"")) -> 12 | B24: =IF(OR(A24="",B7=""),"",EDATE(B7,A24-1)) -> 46583 | C24: =IF(A24="","",E24-D24) -> 548.90509 | D24: =IF(A24="","",F23*E7/12) -> 242.37261 | E24: =IF(A24="","",E9) -> 791.2777 | F24: =IF(A24="","",IF(A24=E8,0,F23-C24)) -> 31803.39 | G24: =IF(A24="","",I23*Loans!C7/12) -> 13.003564 | H24: =IF(A24="","",H9-G24) -> 630.56228 | I24: =IF(A24="","",IF(A24=E8,0,I23-H24)) -> 30577.992
A25: =IF(A24="","",IF(A24<E8,A24+1,"")) -> 13 | B25: =IF(OR(A25="",B7=""),"",EDATE(B7,A25-1)) -> 46614 | C25: =IF(A25="","",E25-D25) -> 553.01731 | D25: =IF(A25="","",F24*E7/12) -> 238.2604 | E25: =IF(A25="","",E9) -> 791.2777 | F25: =IF(A25="","",IF(A25=E8,0,F24-C25)) -> 31250.373 | G25: =IF(A25="","",I24*Loans!C7/12) -> 12.74083 | H25: =IF(A25="","",H9-G25) -> 630.82502 | I25: =IF(A25="","",IF(A25=E8,0,I24-H25)) -> 29947.167
A26: =IF(A25="","",IF(A25<E8,A25+1,"")) -> 14 | B26: =IF(OR(A26="",B7=""),"",EDATE(B7,A26-1)) -> 46645 | C26: =IF(A26="","",E26-D26) -> 557.16033 | D26: =IF(A26="","",F25*E7/12) -> 234.11738 | E26: =IF(A26="","",E9) -> 791.2777 | F26: =IF(A26="","",IF(A26=E8,0,F25-C26)) -> 30693.212 | G26: =IF(A26="","",I25*Loans!C7/12) -> 12.477986 | H26: =IF(A26="","",H9-G26) -> 631.08786 | I26: =IF(A26="","",IF(A26=E8,0,I25-H26)) -> 29316.079
A27: =IF(A26="","",IF(A26<E8,A26+1,"")) -> 15 | B27: =IF(OR(A27="",B7=""),"",EDATE(B7,A27-1)) -> 46675 | C27: =IF(A27="","",E27-D27) -> 561.33439 | D27: =IF(A27="","",F26*E7/12) -> 229.94332 | E27: =IF(A27="","",E9) -> 791.2777 | F27: =IF(A27="","",IF(A27=E8,0,F26-C27)) -> 30131.878 | G27: =IF(A27="","",I26*Loans!C7/12) -> 12.215033 | H27: =IF(A27="","",H9-G27) -> 631.35082 | I27: =IF(A27="","",IF(A27=E8,0,I26-H27)) -> 28684.728
A28: =IF(A27="","",IF(A27<E8,A27+1,"")) -> 16 | B28: =IF(OR(A28="",B7=""),"",EDATE(B7,A28-1)) -> 46706 | C28: =IF(A28="","",E28-D28) -> 565.53972 | D28: =IF(A28="","",F27*E7/12) -> 225.73799 | E28: =IF(A28="","",E9) -> 791.2777 | F28: =IF(A28="","",IF(A28=E8,0,F27-C28)) -> 29566.338 | G28: =IF(A28="","",I27*Loans!C7/12) -> 11.95197 | H28: =IF(A28="","",H9-G28) -> 631.61388 | I28: =IF(A28="","",IF(A28=E8,0,I27-H28)) -> 28053.114
A29: =IF(A28="","",IF(A28<E8,A28+1,"")) -> 17 | B29: =IF(OR(A29="",B7=""),"",EDATE(B7,A29-1)) -> 46736 | C29: =IF(A29="","",E29-D29) -> 569.77655 | D29: =IF(A29="","",F28*E7/12) -> 221.50115 | E29: =IF(A29="","",E9) -> 791.2777 | F29: =IF(A29="","",IF(A29=E8,0,F28-C29)) -> 28996.562 | G29: =IF(A29="","",I28*Loans!C7/12) -> 11.688798 | H29: =IF(A29="","",H9-G29) -> 631.87705 | I29: =IF(A29="","",IF(A29=E8,0,I28-H29)) -> 27421.237
A30: =IF(A29="","",IF(A29<E8,A29+1,"")) -> 18 | B30: =IF(OR(A30="",B7=""),"",EDATE(B7,A30-1)) -> 46767 | C30: =IF(A30="","",E30-D30) -> 574.04513 | D30: =IF(A30="","",F29*E7/12) -> 217.23258 | E30: =IF(A30="","",E9) -> 791.2777 | F30: =IF(A30="","",IF(A30=E8,0,F29-C30)) -> 28422.517 | G30: =IF(A30="","",I29*Loans!C7/12) -> 11.425515 | H30: =IF(A30="","",H9-G30) -> 632.14033 | I30: =IF(A30="","",IF(A30=E8,0,I29-H30)) -> 26789.097
A31: =IF(A30="","",IF(A30<E8,A30+1,"")) -> 19 | B31: =IF(OR(A31="",B7=""),"",EDATE(B7,A31-1)) -> 46798 | C31: =IF(A31="","",E31-D31) -> 578.34568 | D31: =IF(A31="","",F30*E7/12) -> 212.93202 | E31: =IF(A31="","",E9) -> 791.2777 | F31: =IF(A31="","",IF(A31=E8,0,F30-C31)) -> 27844.171 | G31: =IF(A31="","",I30*Loans!C7/12) -> 11.162124 | H31: =IF(A31="","",H9-G31) -> 632.40372 | I31: =IF(A31="","",IF(A31=E8,0,I30-H31)) -> 26156.693
A32: =IF(A31="","",IF(A31<E8,A31+1,"")) -> 20 | B32: =IF(OR(A32="",B7=""),"",EDATE(B7,A32-1)) -> 46827 | C32: =IF(A32="","",E32-D32) -> 582.67846 | D32: =IF(A32="","",F31*E7/12) -> 208.59925 | E32: =IF(A32="","",E9) -> 791.2777 | F32: =IF(A32="","",IF(A32=E8,0,F31-C32)) -> 27261.492 | G32: =IF(A32="","",I31*Loans!C7/12) -> 10.898622 | H32: =IF(A32="","",H9-G32) -> 632.66723 | I32: =IF(A32="","",IF(A32=E8,0,I31-H32)) -> 25524.026
A33: =IF(A32="","",IF(A32<E8,A32+1,"")) -> 21 | B33: =IF(OR(A33="",B7=""),"",EDATE(B7,A33-1)) -> 46858 | C33: =IF(A33="","",E33-D33) -> 587.04369 | D33: =IF(A33="","",F32*E7/12) -> 204.23401 | E33: =IF(A33="","",E9) -> 791.2777 | F33: =IF(A33="","",IF(A33=E8,0,F32-C33)) -> 26674.449 | G33: =IF(A33="","",I32*Loans!C7/12) -> 10.635011 | H33: =IF(A33="","",H9-G33) -> 632.93084 | I33: =IF(A33="","",IF(A33=E8,0,I32-H33)) -> 24891.095
A34: =IF(A33="","",IF(A33<E8,A33+1,"")) -> 22 | B34: =IF(OR(A34="",B7=""),"",EDATE(B7,A34-1)) -> 46888 | C34: =IF(A34="","",E34-D34) -> 591.44163 | D34: =IF(A34="","",F33*E7/12) -> 199.83608 | E34: =IF(A34="","",E9) -> 791.2777 | F34: =IF(A34="","",IF(A34=E8,0,F33-C34)) -> 26083.007 | G34: =IF(A34="","",I33*Loans!C7/12) -> 10.37129 | H34: =IF(A34="","",H9-G34) -> 633.19456 | I34: =IF(A34="","",IF(A34=E8,0,I33-H34)) -> 24257.9
A35: =IF(A34="","",IF(A34<E8,A34+1,"")) -> 23 | B35: =IF(OR(A35="",B7=""),"",EDATE(B7,A35-1)) -> 46919 | C35: =IF(A35="","",E35-D35) -> 595.87251 | D35: =IF(A35="","",F34*E7/12) -> 195.4052 | E35: =IF(A35="","",E9) -> 791.2777 | F35: =IF(A35="","",IF(A35=E8,0,F34-C35)) -> 25487.135 | G35: =IF(A35="","",I34*Loans!C7/12) -> 10.107459 | H35: =IF(A35="","",H9-G35) -> 633.45839 | I35: =IF(A35="","",IF(A35=E8,0,I34-H35)) -> 23624.442
A36: =IF(A35="","",IF(A35<E8,A35+1,"")) -> 24 | B36: =IF(OR(A36="",B7=""),"",EDATE(B7,A36-1)) -> 46949 | C36: =IF(A36="","",E36-D36) -> 600.33659 | D36: =IF(A36="","",F35*E7/12) -> 190.94112 | E36: =IF(A36="","",E9) -> 791.2777 | F36: =IF(A36="","",IF(A36=E8,0,F35-C36)) -> 24886.798 | G36: =IF(A36="","",I35*Loans!C7/12) -> 9.8435175 | H36: =IF(A36="","",H9-G36) -> 633.72233 | I36: =IF(A36="","",IF(A36=E8,0,I35-H36)) -> 22990.72
A37: =IF(A36="","",IF(A36<E8,A36+1,"")) -> 25 | B37: =IF(OR(A37="",B7=""),"",EDATE(B7,A37-1)) -> 46980 | C37: =IF(A37="","",E37-D37) -> 604.83411 | D37: =IF(A37="","",F36*E7/12) -> 186.4436 | E37: =IF(A37="","",E9) -> 791.2777 | F37: =IF(A37="","",IF(A37=E8,0,F36-C37)) -> 24281.964 | G37: =IF(A37="","",I36*Loans!C7/12) -> 9.5794666 | H37: =IF(A37="","",H9-G37) -> 633.98638 | I37: =IF(A37="","",IF(A37=E8,0,I36-H37)) -> 22356.733
A38: =IF(A37="","",IF(A37<E8,A37+1,"")) -> 26 | B38: =IF(OR(A38="",B7=""),"",EDATE(B7,A38-1)) -> 47011 | C38: =IF(A38="","",E38-D38) -> 609.36532 | D38: =IF(A38="","",F37*E7/12) -> 181.91238 | E38: =IF(A38="","",E9) -> 791.2777 | F38: =IF(A38="","",IF(A38=E8,0,F37-C38)) -> 23672.599 | G38: =IF(A38="","",I37*Loans!C7/12) -> 9.3153056 | H38: =IF(A38="","",H9-G38) -> 634.25054 | I38: =IF(A38="","",IF(A38=E8,0,I37-H38)) -> 21722.483
A39: =IF(A38="","",IF(A38<E8,A38+1,"")) -> 27 | B39: =IF(OR(A39="",B7=""),"",EDATE(B7,A39-1)) -> 47041 | C39: =IF(A39="","",E39-D39) -> 613.93049 | D39: =IF(A39="","",F38*E7/12) -> 177.34722 | E39: =IF(A39="","",E9) -> 791.2777 | F39: =IF(A39="","",IF(A39=E8,0,F38-C39)) -> 23058.668 | G39: =IF(A39="","",I38*Loans!C7/12) -> 9.0510345 | H39: =IF(A39="","",H9-G39) -> 634.51481 | I39: =IF(A39="","",IF(A39=E8,0,I38-H39)) -> 21087.968
A40: =IF(A39="","",IF(A39<E8,A39+1,"")) -> 28 | B40: =IF(OR(A40="",B7=""),"",EDATE(B7,A40-1)) -> 47072 | C40: =IF(A40="","",E40-D40) -> 618.52985 | D40: =IF(A40="","",F39*E7/12) -> 172.74786 | E40: =IF(A40="","",E9) -> 791.2777 | F40: =IF(A40="","",IF(A40=E8,0,F39-C40)) -> 22440.138 | G40: =IF(A40="","",I39*Loans!C7/12) -> 8.7866533 | H40: =IF(A40="","",H9-G40) -> 634.7792 | I40: =IF(A40="","",IF(A40=E8,0,I39-H40)) -> 20453.189
A41: =IF(A40="","",IF(A40<E8,A40+1,"")) -> 29 | B41: =IF(OR(A41="",B7=""),"",EDATE(B7,A41-1)) -> 47102 | C41: =IF(A41="","",E41-D41) -> 623.16367 | D41: =IF(A41="","",F40*E7/12) -> 168.11404 | E41: =IF(A41="","",E9) -> 791.2777 | F41: =IF(A41="","",IF(A41=E8,0,F40-C41)) -> 21816.975 | G41: =IF(A41="","",I40*Loans!C7/12) -> 8.522162 | H41: =IF(A41="","",H9-G41) -> 635.04369 | I41: =IF(A41="","",IF(A41=E8,0,I40-H41)) -> 19818.145
A42: =IF(A41="","",IF(A41<E8,A41+1,"")) -> 30 | B42: =IF(OR(A42="",B7=""),"",EDATE(B7,A42-1)) -> 47133 | C42: =IF(A42="","",E42-D42) -> 627.8322 | D42: =IF(A42="","",F41*E7/12) -> 163.4455 | E42: =IF(A42="","",E9) -> 791.2777 | F42: =IF(A42="","",IF(A42=E8,0,F41-C42)) -> 21189.142 | G42: =IF(A42="","",I41*Loans!C7/12) -> 8.2575605 | H42: =IF(A42="","",H9-G42) -> 635.30829 | I42: =IF(A42="","",IF(A42=E8,0,I41-H42)) -> 19182.837
A43: =IF(A42="","",IF(A42<E8,A42+1,"")) -> 31 | B43: =IF(OR(A43="",B7=""),"",EDATE(B7,A43-1)) -> 47164 | C43: =IF(A43="","",E43-D43) -> 632.53571 | D43: =IF(A43="","",F42*E7/12) -> 158.74199 | E43: =IF(A43="","",E9) -> 791.2777 | F43: =IF(A43="","",IF(A43=E8,0,F42-C43)) -> 20556.607 | G43: =IF(A43="","",I42*Loans!C7/12) -> 7.9928487 | H43: =IF(A43="","",H9-G43) -> 635.573 | I43: =IF(A43="","",IF(A43=E8,0,I42-H43)) -> 18547.264
A44: =IF(A43="","",IF(A43<E8,A43+1,"")) -> 32 | B44: =IF(OR(A44="",B7=""),"",EDATE(B7,A44-1)) -> 47192 | C44: =IF(A44="","",E44-D44) -> 637.27446 | D44: =IF(A44="","",F43*E7/12) -> 154.00325 | E44: =IF(A44="","",E9) -> 791.2777 | F44: =IF(A44="","",IF(A44=E8,0,F43-C44)) -> 19919.332 | G44: =IF(A44="","",I43*Loans!C7/12) -> 7.7280266 | H44: =IF(A44="","",H9-G44) -> 635.83782 | I44: =IF(A44="","",IF(A44=E8,0,I43-H44)) -> 17911.426
A45: =IF(A44="","",IF(A44<E8,A44+1,"")) -> 33 | B45: =IF(OR(A45="",B7=""),"",EDATE(B7,A45-1)) -> 47223 | C45: =IF(A45="","",E45-D45) -> 642.04871 | D45: =IF(A45="","",F44*E7/12) -> 149.229 | E45: =IF(A45="","",E9) -> 791.2777 | F45: =IF(A45="","",IF(A45=E8,0,F44-C45)) -> 19277.284 | G45: =IF(A45="","",I44*Loans!C7/12) -> 7.4630942 | H45: =IF(A45="","",H9-G45) -> 636.10275 | I45: =IF(A45="","",IF(A45=E8,0,I44-H45)) -> 17275.323
A46: =IF(A45="","",IF(A45<E8,A45+1,"")) -> 34 | B46: =IF(OR(A46="",B7=""),"",EDATE(B7,A46-1)) -> 47253 | C46: =IF(A46="","",E46-D46) -> 646.85872 | D46: =IF(A46="","",F45*E7/12) -> 144.41898 | E46: =IF(A46="","",E9) -> 791.2777 | F46: =IF(A46="","",IF(A46=E8,0,F45-C46)) -> 18630.425 | G46: =IF(A46="","",I45*Loans!C7/12) -> 7.1980514 | H46: =IF(A46="","",H9-G46) -> 636.3678 | I46: =IF(A46="","",IF(A46=E8,0,I45-H46)) -> 16638.955
A47: =IF(A46="","",IF(A46<E8,A46+1,"")) -> 35 | B47: =IF(OR(A47="",B7=""),"",EDATE(B7,A47-1)) -> 47284 | C47: =IF(A47="","",E47-D47) -> 651.70477 | D47: =IF(A47="","",F46*E7/12) -> 139.57293 | E47: =IF(A47="","",E9) -> 791.2777 | F47: =IF(A47="","",IF(A47=E8,0,F46-C47)) -> 17978.72 | G47: =IF(A47="","",I46*Loans!C7/12) -> 6.9328981 | H47: =IF(A47="","",H9-G47) -> 636.63295 | I47: =IF(A47="","",IF(A47=E8,0,I46-H47)) -> 16002.323
A48: =IF(A47="","",IF(A47<E8,A47+1,"")) -> 36 | B48: =IF(OR(A48="",B7=""),"",EDATE(B7,A48-1)) -> 47314 | C48: =IF(A48="","",E48-D48) -> 656.58713 | D48: =IF(A48="","",F47*E7/12) -> 134.69058 | E48: =IF(A48="","",E9) -> 791.2777 | F48: =IF(A48="","",IF(A48=E8,0,F47-C48)) -> 17322.133 | G48: =IF(A48="","",I47*Loans!C7/12) -> 6.6676344 | H48: =IF(A48="","",H9-G48) -> 636.89821 | I48: =IF(A48="","",IF(A48=E8,0,I47-H48)) -> 15365.424
A49: =IF(A48="","",IF(A48<E8,A48+1,"")) -> 37 | B49: =IF(OR(A49="",B7=""),"",EDATE(B7,A49-1)) -> 47345 | C49: =IF(A49="","",E49-D49) -> 661.50606 | D49: =IF(A49="","",F48*E7/12) -> 129.77165 | E49: =IF(A49="","",E9) -> 791.2777 | F49: =IF(A49="","",IF(A49=E8,0,F48-C49)) -> 16660.627 | G49: =IF(A49="","",I48*Loans!C7/12) -> 6.4022601 | H49: =IF(A49="","",H9-G49) -> 637.16359 | I49: =IF(A49="","",IF(A49=E8,0,I48-H49)) -> 14728.261
A50: =IF(A49="","",IF(A49<E8,A49+1,"")) -> 38 | B50: =IF(OR(A50="",B7=""),"",EDATE(B7,A50-1)) -> 47376 | C50: =IF(A50="","",E50-D50) -> 666.46184 | D50: =IF(A50="","",F49*E7/12) -> 124.81586 | E50: =IF(A50="","",E9) -> 791.2777 | F50: =IF(A50="","",IF(A50=E8,0,F49-C50)) -> 15994.165 | G50: =IF(A50="","",I49*Loans!C7/12) -> 6.1367753 | H50: =IF(A50="","",H9-G50) -> 637.42907 | I50: =IF(A50="","",IF(A50=E8,0,I49-H50)) -> 14090.832
A51: =IF(A50="","",IF(A50<E8,A50+1,"")) -> 39 | B51: =IF(OR(A51="",B7=""),"",EDATE(B7,A51-1)) -> 47406 | C51: =IF(A51="","",E51-D51) -> 671.45475 | D51: =IF(A51="","",F50*E7/12) -> 119.82295 | E51: =IF(A51="","",E9) -> 791.2777 | F51: =IF(A51="","",IF(A51=E8,0,F50-C51)) -> 15322.71 | G51: =IF(A51="","",I50*Loans!C7/12) -> 5.8711799 | H51: =IF(A51="","",H9-G51) -> 637.69467 | I51: =IF(A51="","",IF(A51=E8,0,I50-H51)) -> 13453.137
A52: =IF(A51="","",IF(A51<E8,A51+1,"")) -> 40 | B52: =IF(OR(A52="",B7=""),"",EDATE(B7,A52-1)) -> 47437 | C52: =IF(A52="","",E52-D52) -> 676.48507 | D52: =IF(A52="","",F51*E7/12) -> 114.79264 | E52: =IF(A52="","",E9) -> 791.2777 | F52: =IF(A52="","",IF(A52=E8,0,F51-C52)) -> 14646.225 | G52: =IF(A52="","",I51*Loans!C7/12) -> 5.6054737 | H52: =IF(A52="","",H9-G52) -> 637.96037 | I52: =IF(A52="","",IF(A52=E8,0,I51-H52)) -> 12815.177
A53: =IF(A52="","",IF(A52<E8,A52+1,"")) -> 41 | B53: =IF(OR(A53="",B7=""),"",EDATE(B7,A53-1)) -> 47467 | C53: =IF(A53="","",E53-D53) -> 681.55307 | D53: =IF(A53="","",F52*E7/12) -> 109.72464 | E53: =IF(A53="","",E9) -> 791.2777 | F53: =IF(A53="","",IF(A53=E8,0,F52-C53)) -> 13964.672 | G53: =IF(A53="","",I52*Loans!C7/12) -> 5.3396569 | H53: =IF(A53="","",H9-G53) -> 638.22619 | I53: =IF(A53="","",IF(A53=E8,0,I52-H53)) -> 12176.95
A54: =IF(A53="","",IF(A53<E8,A53+1,"")) -> 42 | B54: =IF(OR(A54="",B7=""),"",EDATE(B7,A54-1)) -> 47498 | C54: =IF(A54="","",E54-D54) -> 686.65904 | D54: =IF(A54="","",F53*E7/12) -> 104.61867 | E54: =IF(A54="","",E9) -> 791.2777 | F54: =IF(A54="","",IF(A54=E8,0,F53-C54)) -> 13278.013 | G54: =IF(A54="","",I53*Loans!C7/12) -> 5.0737293 | H54: =IF(A54="","",H9-G54) -> 638.49212 | I54: =IF(A54="","",IF(A54=E8,0,I53-H54)) -> 11538.458
A55: =IF(A54="","",IF(A54<E8,A54+1,"")) -> 43 | B55: =IF(OR(A55="",B7=""),"",EDATE(B7,A55-1)) -> 47529 | C55: =IF(A55="","",E55-D55) -> 691.80326 | D55: =IF(A55="","",F54*E7/12) -> 99.474448 | E55: =IF(A55="","",E9) -> 791.2777 | F55: =IF(A55="","",IF(A55=E8,0,F54-C55)) -> 12586.21 | G55: =IF(A55="","",I54*Loans!C7/12) -> 4.807691 | H55: =IF(A55="","",H9-G55) -> 638.75816 | I55: =IF(A55="","",IF(A55=E8,0,I54-H55)) -> 10899.7
A56: =IF(A55="","",IF(A55<E8,A55+1,"")) -> 44 | B56: =IF(OR(A56="",B7=""),"",EDATE(B7,A56-1)) -> 47557 | C56: =IF(A56="","",E56-D56) -> 696.98602 | D56: =IF(A56="","",F55*E7/12) -> 94.291689 | E56: =IF(A56="","",E9) -> 791.2777 | F56: =IF(A56="","",IF(A56=E8,0,F55-C56)) -> 11889.224 | G56: =IF(A56="","",I55*Loans!C7/12) -> 4.5415417 | H56: =IF(A56="","",H9-G56) -> 639.02431 | I56: =IF(A56="","",IF(A56=E8,0,I55-H56)) -> 10260.676
A57: =IF(A56="","",IF(A56<E8,A56+1,"")) -> 45 | B57: =IF(OR(A57="",B7=""),"",EDATE(B7,A57-1)) -> 47588 | C57: =IF(A57="","",E57-D57) -> 702.2076 | D57: =IF(A57="","",F56*E7/12) -> 89.070102 | E57: =IF(A57="","",E9) -> 791.2777 | F57: =IF(A57="","",IF(A57=E8,0,F56-C57)) -> 11187.016 | G57: =IF(A57="","",I56*Loans!C7/12) -> 4.2752816 | H57: =IF(A57="","",H9-G57) -> 639.29057 | I57: =IF(A57="","",IF(A57=E8,0,I56-H57)) -> 9621.3853
A58: =IF(A57="","",IF(A57<E8,A57+1,"")) -> 46 | B58: =IF(OR(A58="",B7=""),"",EDATE(B7,A58-1)) -> 47618 | C58: =IF(A58="","",E58-D58) -> 707.46831 | D58: =IF(A58="","",F57*E7/12) -> 83.809397 | E58: =IF(A58="","",E9) -> 791.2777 | F58: =IF(A58="","",IF(A58=E8,0,F57-C58)) -> 10479.548 | G58: =IF(A58="","",I57*Loans!C7/12) -> 4.0089105 | H58: =IF(A58="","",H9-G58) -> 639.55694 | I58: =IF(A58="","",IF(A58=E8,0,I57-H58)) -> 8981.8283
A59: =IF(A58="","",IF(A58<E8,A58+1,"")) -> 47 | B59: =IF(OR(A59="",B7=""),"",EDATE(B7,A59-1)) -> 47649 | C59: =IF(A59="","",E59-D59) -> 712.76842 | D59: =IF(A59="","",F58*E7/12) -> 78.50928 | E59: =IF(A59="","",E9) -> 791.2777 | F59: =IF(A59="","",IF(A59=E8,0,F58-C59)) -> 9766.7795 | G59: =IF(A59="","",I58*Loans!C7/12) -> 3.7424285 | H59: =IF(A59="","",H9-G59) -> 639.82342 | I59: =IF(A59="","",IF(A59=E8,0,I58-H59)) -> 8342.0049
A60: =IF(A59="","",IF(A59<E8,A59+1,"")) -> 48 | B60: =IF(OR(A60="",B7=""),"",EDATE(B7,A60-1)) -> 47679 | C60: =IF(A60="","",E60-D60) -> 718.10825 | D60: =IF(A60="","",F59*E7/12) -> 73.169457 | E60: =IF(A60="","",E9) -> 791.2777 | F60: =IF(A60="","",IF(A60=E8,0,F59-C60)) -> 9048.6713 | G60: =IF(A60="","",I59*Loans!C7/12) -> 3.4758354 | H60: =IF(A60="","",H9-G60) -> 640.09001 | I60: =IF(A60="","",IF(A60=E8,0,I59-H60)) -> 7701.9149
A61: =IF(A60="","",IF(A60<E8,A60+1,"")) -> 49 | B61: =IF(OR(A61="",B7=""),"",EDATE(B7,A61-1)) -> 47710 | C61: =IF(A61="","",E61-D61) -> 723.48808 | D61: =IF(A61="","",F60*E7/12) -> 67.789629 | E61: =IF(A61="","",E9) -> 791.2777 | F61: =IF(A61="","",IF(A61=E8,0,F60-C61)) -> 8325.1832 | G61: =IF(A61="","",I60*Loans!C7/12) -> 3.2091312 | H61: =IF(A61="","",H9-G61) -> 640.35672 | I61: =IF(A61="","",IF(A61=E8,0,I60-H61)) -> 7061.5582
A62: =IF(A61="","",IF(A61<E8,A61+1,"")) -> 50 | B62: =IF(OR(A62="",B7=""),"",EDATE(B7,A62-1)) -> 47741 | C62: =IF(A62="","",E62-D62) -> 728.90821 | D62: =IF(A62="","",F61*E7/12) -> 62.369497 | E62: =IF(A62="","",E9) -> 791.2777 | F62: =IF(A62="","",IF(A62=E8,0,F61-C62)) -> 7596.275 | G62: =IF(A62="","",I61*Loans!C7/12) -> 2.9423159 | H62: =IF(A62="","",H9-G62) -> 640.62353 | I62: =IF(A62="","",IF(A62=E8,0,I61-H62)) -> 6420.9346
A63: =IF(A62="","",IF(A62<E8,A62+1,"")) -> 51 | B63: =IF(OR(A63="",B7=""),"",EDATE(B7,A63-1)) -> 47771 | C63: =IF(A63="","",E63-D63) -> 734.36894 | D63: =IF(A63="","",F62*E7/12) -> 56.90876 | E63: =IF(A63="","",E9) -> 791.2777 | F63: =IF(A63="","",IF(A63=E8,0,F62-C63)) -> 6861.906 | G63: =IF(A63="","",I62*Loans!C7/12) -> 2.6753894 | H63: =IF(A63="","",H9-G63) -> 640.89046 | I63: =IF(A63="","",IF(A63=E8,0,I62-H63)) -> 5780.0442
A64: =IF(A63="","",IF(A63<E8,A63+1,"")) -> 52 | B64: =IF(OR(A64="",B7=""),"",EDATE(B7,A64-1)) -> 47802 | C64: =IF(A64="","",E64-D64) -> 739.87059 | D64: =IF(A64="","",F63*E7/12) -> 51.407113 | E64: =IF(A64="","",E9) -> 791.2777 | F64: =IF(A64="","",IF(A64=E8,0,F63-C64)) -> 6122.0354 | G64: =IF(A64="","",I63*Loans!C7/12) -> 2.4083517 | H64: =IF(A64="","",H9-G64) -> 641.1575 | I64: =IF(A64="","",IF(A64=E8,0,I63-H64)) -> 5138.8867
A65: =IF(A64="","",IF(A64<E8,A64+1,"")) -> 53 | B65: =IF(OR(A65="",B7=""),"",EDATE(B7,A65-1)) -> 47832 | C65: =IF(A65="","",E65-D65) -> 745.41346 | D65: =IF(A65="","",F64*E7/12) -> 45.864249 | E65: =IF(A65="","",E9) -> 791.2777 | F65: =IF(A65="","",IF(A65=E8,0,F64-C65)) -> 5376.622 | G65: =IF(A65="","",I64*Loans!C7/12) -> 2.1412028 | H65: =IF(A65="","",H9-G65) -> 641.42465 | I65: =IF(A65="","",IF(A65=E8,0,I64-H65)) -> 4497.462
A66: =IF(A65="","",IF(A65<E8,A65+1,"")) -> 54 | B66: =IF(OR(A66="",B7=""),"",EDATE(B7,A66-1)) -> 47863 | C66: =IF(A66="","",E66-D66) -> 750.99784 | D66: =IF(A66="","",F65*E7/12) -> 40.27986 | E66: =IF(A66="","",E9) -> 791.2777 | F66: =IF(A66="","",IF(A66=E8,0,F65-C66)) -> 4625.6241 | G66: =IF(A66="","",I65*Loans!C7/12) -> 1.8739425 | H66: =IF(A66="","",H9-G66) -> 641.69191 | I66: =IF(A66="","",IF(A66=E8,0,I65-H66)) -> 3855.7701
A67: =IF(A66="","",IF(A66<E8,A66+1,"")) -> 55 | B67: =IF(OR(A67="",B7=""),"",EDATE(B7,A67-1)) -> 47894 | C67: =IF(A67="","",E67-D67) -> 756.62407 | D67: =IF(A67="","",F66*E7/12) -> 34.653634 | E67: =IF(A67="","",E9) -> 791.2777 | F67: =IF(A67="","",IF(A67=E8,0,F66-C67)) -> 3869.0001 | G67: =IF(A67="","",I66*Loans!C7/12) -> 1.6065709 | H67: =IF(A67="","",H9-G67) -> 641.95928 | I67: =IF(A67="","",IF(A67=E8,0,I66-H67)) -> 3213.8109
A68: =IF(A67="","",IF(A67<E8,A67+1,"")) -> 56 | B68: =IF(OR(A68="",B7=""),"",EDATE(B7,A68-1)) -> 47922 | C68: =IF(A68="","",E68-D68) -> 762.29245 | D68: =IF(A68="","",F67*E7/12) -> 28.985259 | E68: =IF(A68="","",E9) -> 791.2777 | F68: =IF(A68="","",IF(A68=E8,0,F67-C68)) -> 3106.7076 | G68: =IF(A68="","",I67*Loans!C7/12) -> 1.3390879 | H68: =IF(A68="","",H9-G68) -> 642.22676 | I68: =IF(A68="","",IF(A68=E8,0,I67-H68)) -> 2571.5841
A69: =IF(A68="","",IF(A68<E8,A68+1,"")) -> 57 | B69: =IF(OR(A69="",B7=""),"",EDATE(B7,A69-1)) -> 47953 | C69: =IF(A69="","",E69-D69) -> 768.00329 | D69: =IF(A69="","",F68*E7/12) -> 23.274418 | E69: =IF(A69="","",E9) -> 791.2777 | F69: =IF(A69="","",IF(A69=E8,0,F68-C69)) -> 2338.7043 | G69: =IF(A69="","",I68*Loans!C7/12) -> 1.0714934 | H69: =IF(A69="","",H9-G69) -> 642.49436 | I69: =IF(A69="","",IF(A69=E8,0,I68-H69)) -> 1929.0897
A70: =IF(A69="","",IF(A69<E8,A69+1,"")) -> 58 | B70: =IF(OR(A70="",B7=""),"",EDATE(B7,A70-1)) -> 47983 | C70: =IF(A70="","",E70-D70) -> 773.75691 | D70: =IF(A70="","",F69*E7/12) -> 17.520793 | E70: =IF(A70="","",E9) -> 791.2777 | F70: =IF(A70="","",IF(A70=E8,0,F69-C70)) -> 1564.9474 | G70: =IF(A70="","",I69*Loans!C7/12) -> 0.80378739 | H70: =IF(A70="","",H9-G70) -> 642.76206 | I70: =IF(A70="","",IF(A70=E8,0,I69-H70)) -> 1286.3277
A71: =IF(A70="","",IF(A70<E8,A70+1,"")) -> 59 | B71: =IF(OR(A71="",B7=""),"",EDATE(B7,A71-1)) -> 48014 | C71: =IF(A71="","",E71-D71) -> 779.55364 | D71: =IF(A71="","",F70*E7/12) -> 11.724065 | E71: =IF(A71="","",E9) -> 791.2777 | F71: =IF(A71="","",IF(A71=E8,0,F70-C71)) -> 785.3938 | G71: =IF(A71="","",I70*Loans!C7/12) -> 0.53596987 | H71: =IF(A71="","",H9-G71) -> 643.02988 | I71: =IF(A71="","",IF(A71=E8,0,I70-H71)) -> 643.29781
A72: =IF(A71="","",IF(A71<E8,A71+1,"")) -> 60 | B72: =IF(OR(A72="",B7=""),"",EDATE(B7,A72-1)) -> 48044 | C72: =IF(A72="","",E72-D72) -> 785.3938 | D72: =IF(A72="","",F71*E7/12) -> 5.8839085 | E72: =IF(A72="","",E9) -> 791.2777 | F72: =IF(A72="","",IF(A72=E8,0,F71-C72)) -> 0 | G72: =IF(A72="","",I71*Loans!C7/12) -> 0.26804075 | H72: =IF(A72="","",H9-G72) -> 643.29781 | I72: =IF(A72="","",IF(A72=E8,0,I71-H72)) -> 0

Sheet Referral Fees
A1: Referral Fees (engine, nothing to type)
A2: Block 1: referral fee for each payment number, Closed loans only. Fee = balance x yearly rate / 12 on a separate loan for the same Costo de Equipo and term (rate in Loans!C7). Block 2 holds that separate loan's balance.
A3: Blocks 3 and 4 (further down) turn the same fees into calendar months for the Dashboard.
A10: BLOCK 1: Referral Fee by payment number
A11: Loan # | B11: Client | C11: Status | D11: Termino (mo.) | E11: First Payment Date | F11: Costo de Equipo | G11: Referral loan monthly payment | H11: Total Referral Fee | I11: 1 | J11: 2 | K11: 3 | L11: 4 | M11: 5 | N11: 6 | O11: 7 | P11: 8 | Q11: 9 | R11: 10 | S11: 11 | T11: 12 | U11: 13 | V11: 14 | W11: 15 | X11: 16 | Y11: 17 | Z11: 18 | AA11: 19 | AB11: 20 | AC11: 21 | AD11: 22 | AE11: 23 | AF11: 24 | AG11: 25 | AH11: 26 | AI11: 27 | AJ11: 28 | AK11: 29 | AL11: 30 | AM11: 31 | AN11: 32 | AO11: 33 | AP11: 34 | AQ11: 35 | AR11: 36 | AS11: 37 | AT11: 38 | AU11: 39 | AV11: 40 | AW11: 41 | AX11: 42 | AY11: 43 | AZ11: 44 | BA11: 45 | BB11: 46 | BC11: 47 | BD11: 48 | BE11: 49 | BF11: 50 | BG11: 51 | BH11: 52 | BI11: 53 | BJ11: 54 | BK11: 55 | BL11: 56 | BM11: 57 | BN11: 58 | BO11: 59 | BP11: 60
A12: =IF(Loans!A12="","",Loans!A12) -> 1 | B12: =IF(Loans!B12="","",Loans!B12) -> SAMPLE Client A (replace) | C12: =IF(Loans!C12="","",Loans!C12) -> Closed | D12: =IF(Loans!I12="","",Loans!I12) -> 60 | E12: =IF(Loans!E12="","",Loans!E12) -> 46249 | F12: =IF(Loans!F12="","",Loans!F12) -> 38127.43 | G12: =IF(OR(C12<>"Closed",D12="",F12=""),"",PMT(Loans!C7/12,D12,-F12)) -> 643.56585 | H12: =IF(C12<>"Closed","",SUM(I12:BP12)) -> 486.52091 | I12: =IF(OR(C12<>"Closed",D12="",F12=""),"",IF(I11>D12,"",F12*Loans!C7/12)) -> 15.886429 | J12: =IF(OR(C12<>"Closed",D12="",F12=""),"",IF(J11>D12,"",I72*Loans!C7/12)) -> 15.624896 | K12: =IF(OR(C12<>"Closed",D12="",F12=""),"",IF(K11>D12,"",J72*Loans!C7/12)) -> 15.363254 | L12: =IF(OR(C12<>"Closed",D12="",F12=""),"",IF(L11>D12,"",K72*Loans!C7/12)) -> 15.101503 | M12: =IF(OR(C12<>"Closed",D12="",F12=""),"",IF(M11>D12,"",L72*Loans!C7/12)) -> 14.839643 | N12: =IF(OR(C12<>"Closed",D12="",F12=""),"",IF(N11>D12,"",M72*Loans!C7/12)) -> 14.577674 | O12: =IF(OR(C12<>"Closed",D12="",F12=""),"",IF(O11>D12,"",N72*Loans!C7/12)) -> 14.315595 | P12: =IF(OR(C12<>"Closed",D12="",F12=""),"",IF(P11>D12,"",O72*Loans!C7/12)) -> 14.053408 | Q12: =IF(OR(C12<>"Closed",D12="",F12=""),"",IF(Q11>D12,"",P72*Loans!C7/12)) -> 13.791111 | R12: =IF(OR(C12<>"Closed",D12="",F12=""),"",IF(R11>D12,"",Q72*Loans!C7/12)) -> 13.528705 | S12: =IF(OR(C12<>"Closed",D12="",F12=""),"",IF(S11>D12,"",R72*Loans!C7/12)) -> 13.266189 | T12: =IF(OR(C12<>"Closed",D12="",F12=""),"",IF(T11>D12,"",S72*Loans!C7/12)) -> 13.003564 | U12: =IF(OR(C12<>"Closed",D12="",F12=""),"",IF(U11>D12,"",T72*Loans!C7/12)) -> 12.74083 | V12: =IF(OR(C12<>"Closed",D12="",F12=""),"",IF(V11>D12,"",U72*Loans!C7/12)) -> 12.477986 | W12: =IF(OR(C12<>"Closed",D12="",F12=""),"",IF(W11>D12,"",V72*Loans!C7/12)) -> 12.215033 | X12: =IF(OR(C12<>"Closed",D12="",F12=""),"",IF(X11>D12,"",W72*Loans!C7/12)) -> 11.95197 | Y12: =IF(OR(C12<>"Closed",D12="",F12=""),"",IF(Y11>D12,"",X72*Loans!C7/12)) -> 11.688798 | Z12: =IF(OR(C12<>"Closed",D12="",F12=""),"",IF(Z11>D12,"",Y72*Loans!C7/12)) -> 11.425515 | AA12: =IF(OR(C12<>"Closed",D12="",F12=""),"",IF(AA11>D12,"",Z72*Loans!C7/12)) -> 11.162124 | AB12: =IF(OR(C12<>"Closed",D12="",F12=""),"",IF(AB11>D12,"",AA72*Loans!C7/12)) -> 10.898622 | AC12: =IF(OR(C12<>"Closed",D12="",F12=""),"",IF(AC11>D12,"",AB72*Loans!C7/12)) -> 10.635011 | AD12: =IF(OR(C12<>"Closed",D12="",F12=""),"",IF(AD11>D12,"",AC72*Loans!C7/12)) -> 10.37129 | AE12: =IF(OR(C12<>"Closed",D12="",F12=""),"",IF(AE11>D12,"",AD72*Loans!C7/12)) -> 10.107459 | AF12: =IF(OR(C12<>"Closed",D12="",F12=""),"",IF(AF11>D12,"",AE72*Loans!C7/12)) -> 9.8435175 | AG12: =IF(OR(C12<>"Closed",D12="",F12=""),"",IF(AG11>D12,"",AF72*Loans!C7/12)) -> 9.5794666 | AH12: =IF(OR(C12<>"Closed",D12="",F12=""),"",IF(AH11>D12,"",AG72*Loans!C7/12)) -> 9.3153056 | AI12: =IF(OR(C12<>"Closed",D12="",F12=""),"",IF(AI11>D12,"",AH72*Loans!C7/12)) -> 9.0510345 | AJ12: =IF(OR(C12<>"Closed",D12="",F12=""),"",IF(AJ11>D12,"",AI72*Loans!C7/12)) -> 8.7866533 | AK12: =IF(OR(C12<>"Closed",D12="",F12=""),"",IF(AK11>D12,"",AJ72*Loans!C7/12)) -> 8.522162 | AL12: =IF(OR(C12<>"Closed",D12="",F12=""),"",IF(AL11>D12,"",AK72*Loans!C7/12)) -> 8.2575605 | AM12: =IF(OR(C12<>"Closed",D12="",F12=""),"",IF(AM11>D12,"",AL72*Loans!C7/12)) -> 7.9928487 | AN12: =IF(OR(C12<>"Closed",D12="",F12=""),"",IF(AN11>D12,"",AM72*Loans!C7/12)) -> 7.7280266 | AO12: =IF(OR(C12<>"Closed",D12="",F12=""),"",IF(AO11>D12,"",AN72*Loans!C7/12)) -> 7.4630942 | AP12: =IF(OR(C12<>"Closed",D12="",F12=""),"",IF(AP11>D12,"",AO72*Loans!C7/12)) -> 7.1980514 | AQ12: =IF(OR(C12<>"Closed",D12="",F12=""),"",IF(AQ11>D12,"",AP72*Loans!C7/12)) -> 6.9328981 | AR12: =IF(OR(C12<>"Closed",D12="",F12=""),"",IF(AR11>D12,"",AQ72*Loans!C7/12)) -> 6.6676344 | AS12: =IF(OR(C12<>"Closed",D12="",F12=""),"",IF(AS11>D12,"",AR72*Loans!C7/12)) -> 6.4022601 | AT12: =IF(OR(C12<>"Closed",D12="",F12=""),"",IF(AT11>D12,"",AS72*Loans!C7/12)) -> 6.1367753 | AU12: =IF(OR(C12<>"Closed",D12="",F12=""),"",IF(AU11>D12,"",AT72*Loans!C7/12)) -> 5.8711799 | AV12: =IF(OR(C12<>"Closed",D12="",F12=""),"",IF(AV11>D12,"",AU72*Loans!C7/12)) -> 5.6054737 | AW12: =IF(OR(C12<>"Closed",D12="",F12=""),"",IF(AW11>D12,"",AV72*Loans!C7/12)) -> 5.3396569 | AX12: =IF(OR(C12<>"Closed",D12="",F12=""),"",IF(AX11>D12,"",AW72*Loans!C7/12)) -> 5.0737293 | AY12: =IF(OR(C12<>"Closed",D12="",F12=""),"",IF(AY11>D12,"",AX72*Loans!C7/12)) -> 4.807691 | AZ12: =IF(OR(C12<>"Closed",D12="",F12=""),"",IF(AZ11>D12,"",AY72*Loans!C7/12)) -> 4.5415417 | BA12: =IF(OR(C12<>"Closed",D12="",F12=""),"",IF(BA11>D12,"",AZ72*Loans!C7/12)) -> 4.2752816 | BB12: =IF(OR(C12<>"Closed",D12="",F12=""),"",IF(BB11>D12,"",BA72*Loans!C7/12)) -> 4.0089105 | BC12: =IF(OR(C12<>"Closed",D12="",F12=""),"",IF(BC11>D12,"",BB72*Loans!C7/12)) -> 3.7424285 | BD12: =IF(OR(C12<>"Closed",D12="",F12=""),"",IF(BD11>D12,"",BC72*Loans!C7/12)) -> 3.4758354 | BE12: =IF(OR(C12<>"Closed",D12="",F12=""),"",IF(BE11>D12,"",BD72*Loans!C7/12)) -> 3.2091312 | BF12: =IF(OR(C12<>"Closed",D12="",F12=""),"",IF(BF11>D12,"",BE72*Loans!C7/12)) -> 2.9423159 | BG12: =IF(OR(C12<>"Closed",D12="",F12=""),"",IF(BG11>D12,"",BF72*Loans!C7/12)) -> 2.6753894 | BH12: =IF(OR(C12<>"Closed",D12="",F12=""),"",IF(BH11>D12,"",BG72*Loans!C7/12)) -> 2.4083517 | BI12: =IF(OR(C12<>"Closed",D12="",F12=""),"",IF(BI11>D12,"",BH72*Loans!C7/12)) -> 2.1412028 | BJ12: =IF(OR(C12<>"Closed",D12="",F12=""),"",IF(BJ11>D12,"",BI72*Loans!C7/12)) -> 1.8739425 | BK12: =IF(OR(C12<>"Closed",D12="",F12=""),"",IF(BK11>D12,"",BJ72*Loans!C7/12)) -> 1.6065709 | BL12: =IF(OR(C12<>"Closed",D12="",F12=""),"",IF(BL11>D12,"",BK72*Loans!C7/12)) -> 1.3390879 | BM12: =IF(OR(C12<>"Closed",D12="",F12=""),"",IF(BM11>D12,"",BL72*Loans!C7/12)) -> 1.0714934 | BN12: =IF(OR(C12<>"Closed",D12="",F12=""),"",IF(BN11>D12,"",BM72*Loans!C7/12)) -> 0.80378739 | BO12: =IF(OR(C12<>"Closed",D12="",F12=""),"",IF(BO11>D12,"",BN72*Loans!C7/12)) -> 0.53596987 | BP12: =IF(OR(C12<>"Closed",D12="",F12=""),"",IF(BP11>D12,"",BO72*Loans!C7/12)) -> 0.26804075
A13: =IF(Loans!A13="","",Loans!A13) -> 2 | B13: =IF(Loans!B13="","",Loans!B13) -> SAMPLE Client B (replace) | C13: =IF(Loans!C13="","",Loans!C13) -> Pipeline | D13: =IF(Loans!I13="","",Loans!I13) -> 60 | E13: =IF(Loans!E13="","",Loans!E13) -> 46371 | F13: =IF(Loans!F13="","",Loans!F13) -> 58000 | G13: =IF(OR(C13<>"Closed",D13="",F13=""),"",PMT(Loans!C7/12,D13,-F13)) | H13: =IF(C13<>"Closed","",SUM(I13:BP13)) | I13: =IF(OR(C13<>"Closed",D13="",F13=""),"",IF(I11>D13,"",F13*Loans!C7/12)) | J13: =IF(OR(C13<>"Closed",D13="",F13=""),"",IF(J11>D13,"",I73*Loans!C7/12)) | K13: =IF(OR(C13<>"Closed",D13="",F13=""),"",IF(K11>D13,"",J73*Loans!C7/12)) | L13: =IF(OR(C13<>"Closed",D13="",F13=""),"",IF(L11>D13,"",K73*Loans!C7/12)) | M13: =IF(OR(C13<>"Closed",D13="",F13=""),"",IF(M11>D13,"",L73*Loans!C7/12)) | N13: =IF(OR(C13<>"Closed",D13="",F13=""),"",IF(N11>D13,"",M73*Loans!C7/12)) | O13: =IF(OR(C13<>"Closed",D13="",F13=""),"",IF(O11>D13,"",N73*Loans!C7/12)) | P13: =IF(OR(C13<>"Closed",D13="",F13=""),"",IF(P11>D13,"",O73*Loans!C7/12)) | Q13: =IF(OR(C13<>"Closed",D13="",F13=""),"",IF(Q11>D13,"",P73*Loans!C7/12)) | R13: =IF(OR(C13<>"Closed",D13="",F13=""),"",IF(R11>D13,"",Q73*Loans!C7/12)) | S13: =IF(OR(C13<>"Closed",D13="",F13=""),"",IF(S11>D13,"",R73*Loans!C7/12)) | T13: =IF(OR(C13<>"Closed",D13="",F13=""),"",IF(T11>D13,"",S73*Loans!C7/12)) | U13: =IF(OR(C13<>"Closed",D13="",F13=""),"",IF(U11>D13,"",T73*Loans!C7/12)) | V13: =IF(OR(C13<>"Closed",D13="",F13=""),"",IF(V11>D13,"",U73*Loans!C7/12)) | W13: =IF(OR(C13<>"Closed",D13="",F13=""),"",IF(W11>D13,"",V73*Loans!C7/12)) | X13: =IF(OR(C13<>"Closed",D13="",F13=""),"",IF(X11>D13,"",W73*Loans!C7/12)) | Y13: =IF(OR(C13<>"Closed",D13="",F13=""),"",IF(Y11>D13,"",X73*Loans!C7/12)) | Z13: =IF(OR(C13<>"Closed",D13="",F13=""),"",IF(Z11>D13,"",Y73*Loans!C7/12)) | AA13: =IF(OR(C13<>"Closed",D13="",F13=""),"",IF(AA11>D13,"",Z73*Loans!C7/12)) | AB13: =IF(OR(C13<>"Closed",D13="",F13=""),"",IF(AB11>D13,"",AA73*Loans!C7/12)) | AC13: =IF(OR(C13<>"Closed",D13="",F13=""),"",IF(AC11>D13,"",AB73*Loans!C7/12)) | AD13: =IF(OR(C13<>"Closed",D13="",F13=""),"",IF(AD11>D13,"",AC73*Loans!C7/12)) | AE13: =IF(OR(C13<>"Closed",D13="",F13=""),"",IF(AE11>D13,"",AD73*Loans!C7/12)) | AF13: =IF(OR(C13<>"Closed",D13="",F13=""),"",IF(AF11>D13,"",AE73*Loans!C7/12)) | AG13: =IF(OR(C13<>"Closed",D13="",F13=""),"",IF(AG11>D13,"",AF73*Loans!C7/12)) | AH13: =IF(OR(C13<>"Closed",D13="",F13=""),"",IF(AH11>D13,"",AG73*Loans!C7/12)) | AI13: =IF(OR(C13<>"Closed",D13="",F13=""),"",IF(AI11>D13,"",AH73*Loans!C7/12)) | AJ13: =IF(OR(C13<>"Closed",D13="",F13=""),"",IF(AJ11>D13,"",AI73*Loans!C7/12)) | AK13: =IF(OR(C13<>"Closed",D13="",F13=""),"",IF(AK11>D13,"",AJ73*Loans!C7/12)) | AL13: =IF(OR(C13<>"Closed",D13="",F13=""),"",IF(AL11>D13,"",AK73*Loans!C7/12)) | AM13: =IF(OR(C13<>"Closed",D13="",F13=""),"",IF(AM11>D13,"",AL73*Loans!C7/12)) | AN13: =IF(OR(C13<>"Closed",D13="",F13=""),"",IF(AN11>D13,"",AM73*Loans!C7/12)) | AO13: =IF(OR(C13<>"Closed",D13="",F13=""),"",IF(AO11>D13,"",AN73*Loans!C7/12)) | AP13: =IF(OR(C13<>"Closed",D13="",F13=""),"",IF(AP11>D13,"",AO73*Loans!C7/12)) | AQ13: =IF(OR(C13<>"Closed",D13="",F13=""),"",IF(AQ11>D13,"",AP73*Loans!C7/12)) | AR13: =IF(OR(C13<>"Closed",D13="",F13=""),"",IF(AR11>D13,"",AQ73*Loans!C7/12)) | AS13: =IF(OR(C13<>"Closed",D13="",F13=""),"",IF(AS11>D13,"",AR73*Loans!C7/12)) | AT13: =IF(OR(C13<>"Closed",D13="",F13=""),"",IF(AT11>D13,"",AS73*Loans!C7/12)) | AU13: =IF(OR(C13<>"Closed",D13="",F13=""),"",IF(AU11>D13,"",AT73*Loans!C7/12)) | AV13: =IF(OR(C13<>"Closed",D13="",F13=""),"",IF(AV11>D13,"",AU73*Loans!C7/12)) | AW13: =IF(OR(C13<>"Closed",D13="",F13=""),"",IF(AW11>D13,"",AV73*Loans!C7/12)) | AX13: =IF(OR(C13<>"Closed",D13="",F13=""),"",IF(AX11>D13,"",AW73*Loans!C7/12)) | AY13: =IF(OR(C13<>"Closed",D13="",F13=""),"",IF(AY11>D13,"",AX73*Loans!C7/12)) | AZ13: =IF(OR(C13<>"Closed",D13="",F13=""),"",IF(AZ11>D13,"",AY73*Loans!C7/12)) | BA13: =IF(OR(C13<>"Closed",D13="",F13=""),"",IF(BA11>D13,"",AZ73*Loans!C7/12)) | BB13: =IF(OR(C13<>"Closed",D13="",F13=""),"",IF(BB11>D13,"",BA73*Loans!C7/12)) | BC13: =IF(OR(C13<>"Closed",D13="",F13=""),"",IF(BC11>D13,"",BB73*Loans!C7/12)) | BD13: =IF(OR(C13<>"Closed",D13="",F13=""),"",IF(BD11>D13,"",BC73*Loans!C7/12)) | BE13: =IF(OR(C13<>"Closed",D13="",F13=""),"",IF(BE11>D13,"",BD73*Loans!C7/12)) | BF13: =IF(OR(C13<>"Closed",D13="",F13=""),"",IF(BF11>D13,"",BE73*Loans!C7/12)) | BG13: =IF(OR(C13<>"Closed",D13="",F13=""),"",IF(BG11>D13,"",BF73*Loans!C7/12)) | BH13: =IF(OR(C13<>"Closed",D13="",F13=""),"",IF(BH11>D13,"",BG73*Loans!C7/12)) | BI13: =IF(OR(C13<>"Closed",D13="",F13=""),"",IF(BI11>D13,"",BH73*Loans!C7/12)) | BJ13: =IF(OR(C13<>"Closed",D13="",F13=""),"",IF(BJ11>D13,"",BI73*Loans!C7/12)) | BK13: =IF(OR(C13<>"Closed",D13="",F13=""),"",IF(BK11>D13,"",BJ73*Loans!C7/12)) | BL13: =IF(OR(C13<>"Closed",D13="",F13=""),"",IF(BL11>D13,"",BK73*Loans!C7/12)) | BM13: =IF(OR(C13<>"Closed",D13="",F13=""),"",IF(BM11>D13,"",BL73*Loans!C7/12)) | BN13: =IF(OR(C13<>"Closed",D13="",F13=""),"",IF(BN11>D13,"",BM73*Loans!C7/12)) | BO13: =IF(OR(C13<>"Closed",D13="",F13=""),"",IF(BO11>D13,"",BN73*Loans!C7/12)) | BP13: =IF(OR(C13<>"Closed",D13="",F13=""),"",IF(BP11>D13,"",BO73*Loans!C7/12))
A14: =IF(Loans!A14="","",Loans!A14) -> 3 | B14: =IF(Loans!B14="","",Loans!B14) -> SAMPLE Client C (replace) | C14: =IF(Loans!C14="","",Loans!C14) -> Pipeline | D14: =IF(Loans!I14="","",Loans!I14) -> 60 | E14: =IF(Loans!E14="","",Loans!E14) -> 46397 | F14: =IF(Loans!F14="","",Loans!F14) -> 17500 | G14: =IF(OR(C14<>"Closed",D14="",F14=""),"",PMT(Loans!C7/12,D14,-F14)) | H14: =IF(C14<>"Closed","",SUM(I14:BP14)) | I14: =IF(OR(C14<>"Closed",D14="",F14=""),"",IF(I11>D14,"",F14*Loans!C7/12)) | J14: =IF(OR(C14<>"Closed",D14="",F14=""),"",IF(J11>D14,"",I74*Loans!C7/12)) | K14: =IF(OR(C14<>"Closed",D14="",F14=""),"",IF(K11>D14,"",J74*Loans!C7/12)) | L14: =IF(OR(C14<>"Closed",D14="",F14=""),"",IF(L11>D14,"",K74*Loans!C7/12)) | M14: =IF(OR(C14<>"Closed",D14="",F14=""),"",IF(M11>D14,"",L74*Loans!C7/12)) | N14: =IF(OR(C14<>"Closed",D14="",F14=""),"",IF(N11>D14,"",M74*Loans!C7/12)) | O14: =IF(OR(C14<>"Closed",D14="",F14=""),"",IF(O11>D14,"",N74*Loans!C7/12)) | P14: =IF(OR(C14<>"Closed",D14="",F14=""),"",IF(P11>D14,"",O74*Loans!C7/12)) | Q14: =IF(OR(C14<>"Closed",D14="",F14=""),"",IF(Q11>D14,"",P74*Loans!C7/12)) | R14: =IF(OR(C14<>"Closed",D14="",F14=""),"",IF(R11>D14,"",Q74*Loans!C7/12)) | S14: =IF(OR(C14<>"Closed",D14="",F14=""),"",IF(S11>D14,"",R74*Loans!C7/12)) | T14: =IF(OR(C14<>"Closed",D14="",F14=""),"",IF(T11>D14,"",S74*Loans!C7/12)) | U14: =IF(OR(C14<>"Closed",D14="",F14=""),"",IF(U11>D14,"",T74*Loans!C7/12)) | V14: =IF(OR(C14<>"Closed",D14="",F14=""),"",IF(V11>D14,"",U74*Loans!C7/12)) | W14: =IF(OR(C14<>"Closed",D14="",F14=""),"",IF(W11>D14,"",V74*Loans!C7/12)) | X14: =IF(OR(C14<>"Closed",D14="",F14=""),"",IF(X11>D14,"",W74*Loans!C7/12)) | Y14: =IF(OR(C14<>"Closed",D14="",F14=""),"",IF(Y11>D14,"",X74*Loans!C7/12)) | Z14: =IF(OR(C14<>"Closed",D14="",F14=""),"",IF(Z11>D14,"",Y74*Loans!C7/12)) | AA14: =IF(OR(C14<>"Closed",D14="",F14=""),"",IF(AA11>D14,"",Z74*Loans!C7/12)) | AB14: =IF(OR(C14<>"Closed",D14="",F14=""),"",IF(AB11>D14,"",AA74*Loans!C7/12)) | AC14: =IF(OR(C14<>"Closed",D14="",F14=""),"",IF(AC11>D14,"",AB74*Loans!C7/12)) | AD14: =IF(OR(C14<>"Closed",D14="",F14=""),"",IF(AD11>D14,"",AC74*Loans!C7/12)) | AE14: =IF(OR(C14<>"Closed",D14="",F14=""),"",IF(AE11>D14,"",AD74*Loans!C7/12)) | AF14: =IF(OR(C14<>"Closed",D14="",F14=""),"",IF(AF11>D14,"",AE74*Loans!C7/12)) | AG14: =IF(OR(C14<>"Closed",D14="",F14=""),"",IF(AG11>D14,"",AF74*Loans!C7/12)) | AH14: =IF(OR(C14<>"Closed",D14="",F14=""),"",IF(AH11>D14,"",AG74*Loans!C7/12)) | AI14: =IF(OR(C14<>"Closed",D14="",F14=""),"",IF(AI11>D14,"",AH74*Loans!C7/12)) | AJ14: =IF(OR(C14<>"Closed",D14="",F14=""),"",IF(AJ11>D14,"",AI74*Loans!C7/12)) | AK14: =IF(OR(C14<>"Closed",D14="",F14=""),"",IF(AK11>D14,"",AJ74*Loans!C7/12)) | AL14: =IF(OR(C14<>"Closed",D14="",F14=""),"",IF(AL11>D14,"",AK74*Loans!C7/12)) | AM14: =IF(OR(C14<>"Closed",D14="",F14=""),"",IF(AM11>D14,"",AL74*Loans!C7/12)) | AN14: =IF(OR(C14<>"Closed",D14="",F14=""),"",IF(AN11>D14,"",AM74*Loans!C7/12)) | AO14: =IF(OR(C14<>"Closed",D14="",F14=""),"",IF(AO11>D14,"",AN74*Loans!C7/12)) | AP14: =IF(OR(C14<>"Closed",D14="",F14=""),"",IF(AP11>D14,"",AO74*Loans!C7/12)) | AQ14: =IF(OR(C14<>"Closed",D14="",F14=""),"",IF(AQ11>D14,"",AP74*Loans!C7/12)) | AR14: =IF(OR(C14<>"Closed",D14="",F14=""),"",IF(AR11>D14,"",AQ74*Loans!C7/12)) | AS14: =IF(OR(C14<>"Closed",D14="",F14=""),"",IF(AS11>D14,"",AR74*Loans!C7/12)) | AT14: =IF(OR(C14<>"Closed",D14="",F14=""),"",IF(AT11>D14,"",AS74*Loans!C7/12)) | AU14: =IF(OR(C14<>"Closed",D14="",F14=""),"",IF(AU11>D14,"",AT74*Loans!C7/12)) | AV14: =IF(OR(C14<>"Closed",D14="",F14=""),"",IF(AV11>D14,"",AU74*Loans!C7/12)) | AW14: =IF(OR(C14<>"Closed",D14="",F14=""),"",IF(AW11>D14,"",AV74*Loans!C7/12)) | AX14: =IF(OR(C14<>"Closed",D14="",F14=""),"",IF(AX11>D14,"",AW74*Loans!C7/12)) | AY14: =IF(OR(C14<>"Closed",D14="",F14=""),"",IF(AY11>D14,"",AX74*Loans!C7/12)) | AZ14: =IF(OR(C14<>"Closed",D14="",F14=""),"",IF(AZ11>D14,"",AY74*Loans!C7/12)) | BA14: =IF(OR(C14<>"Closed",D14="",F14=""),"",IF(BA11>D14,"",AZ74*Loans!C7/12)) | BB14: =IF(OR(C14<>"Closed",D14="",F14=""),"",IF(BB11>D14,"",BA74*Loans!C7/12)) | BC14: =IF(OR(C14<>"Closed",D14="",F14=""),"",IF(BC11>D14,"",BB74*Loans!C7/12)) | BD14: =IF(OR(C14<>"Closed",D14="",F14=""),"",IF(BD11>D14,"",BC74*Loans!C7/12)) | BE14: =IF(OR(C14<>"Closed",D14="",F14=""),"",IF(BE11>D14,"",BD74*Loans!C7/12)) | BF14: =IF(OR(C14<>"Closed",D14="",F14=""),"",IF(BF11>D14,"",BE74*Loans!C7/12)) | BG14: =IF(OR(C14<>"Closed",D14="",F14=""),"",IF(BG11>D14,"",BF74*Loans!C7/12)) | BH14: =IF(OR(C14<>"Closed",D14="",F14=""),"",IF(BH11>D14,"",BG74*Loans!C7/12)) | BI14: =IF(OR(C14<>"Closed",D14="",F14=""),"",IF(BI11>D14,"",BH74*Loans!C7/12)) | BJ14: =IF(OR(C14<>"Closed",D14="",F14=""),"",IF(BJ11>D14,"",BI74*Loans!C7/12)) | BK14: =IF(OR(C14<>"Closed",D14="",F14=""),"",IF(BK11>D14,"",BJ74*Loans!C7/12)) | BL14: =IF(OR(C14<>"Closed",D14="",F14=""),"",IF(BL11>D14,"",BK74*Loans!C7/12)) | BM14: =IF(OR(C14<>"Closed",D14="",F14=""),"",IF(BM11>D14,"",BL74*Loans!C7/12)) | BN14: =IF(OR(C14<>"Closed",D14="",F14=""),"",IF(BN11>D14,"",BM74*Loans!C7/12)) | BO14: =IF(OR(C14<>"Closed",D14="",F14=""),"",IF(BO11>D14,"",BN74*Loans!C7/12)) | BP14: =IF(OR(C14<>"Closed",D14="",F14=""),"",IF(BP11>D14,"",BO74*Loans!C7/12))
A15: =IF(Loans!A15="","",Loans!A15) | B15: =IF(Loans!B15="","",Loans!B15) | C15: =IF(Loans!C15="","",Loans!C15) | D15: =IF(Loans!I15="","",Loans!I15) | E15: =IF(Loans!E15="","",Loans!E15) | F15: =IF(Loans!F15="","",Loans!F15) | G15: =IF(OR(C15<>"Closed",D15="",F15=""),"",PMT(Loans!C7/12,D15,-F15)) | H15: =IF(C15<>"Closed","",SUM(I15:BP15)) | I15: =IF(OR(C15<>"Closed",D15="",F15=""),"",IF(I11>D15,"",F15*Loans!C7/12)) | J15: =IF(OR(C15<>"Closed",D15="",F15=""),"",IF(J11>D15,"",I75*Loans!C7/12)) | K15: =IF(OR(C15<>"Closed",D15="",F15=""),"",IF(K11>D15,"",J75*Loans!C7/12)) | L15: =IF(OR(C15<>"Closed",D15="",F15=""),"",IF(L11>D15,"",K75*Loans!C7/12)) | M15: =IF(OR(C15<>"Closed",D15="",F15=""),"",IF(M11>D15,"",L75*Loans!C7/12)) | N15: =IF(OR(C15<>"Closed",D15="",F15=""),"",IF(N11>D15,"",M75*Loans!C7/12)) | O15: =IF(OR(C15<>"Closed",D15="",F15=""),"",IF(O11>D15,"",N75*Loans!C7/12)) | P15: =IF(OR(C15<>"Closed",D15="",F15=""),"",IF(P11>D15,"",O75*Loans!C7/12)) | Q15: =IF(OR(C15<>"Closed",D15="",F15=""),"",IF(Q11>D15,"",P75*Loans!C7/12)) | R15: =IF(OR(C15<>"Closed",D15="",F15=""),"",IF(R11>D15,"",Q75*Loans!C7/12)) | S15: =IF(OR(C15<>"Closed",D15="",F15=""),"",IF(S11>D15,"",R75*Loans!C7/12)) | T15: =IF(OR(C15<>"Closed",D15="",F15=""),"",IF(T11>D15,"",S75*Loans!C7/12)) | U15: =IF(OR(C15<>"Closed",D15="",F15=""),"",IF(U11>D15,"",T75*Loans!C7/12)) | V15: =IF(OR(C15<>"Closed",D15="",F15=""),"",IF(V11>D15,"",U75*Loans!C7/12)) | W15: =IF(OR(C15<>"Closed",D15="",F15=""),"",IF(W11>D15,"",V75*Loans!C7/12)) | X15: =IF(OR(C15<>"Closed",D15="",F15=""),"",IF(X11>D15,"",W75*Loans!C7/12)) | Y15: =IF(OR(C15<>"Closed",D15="",F15=""),"",IF(Y11>D15,"",X75*Loans!C7/12)) | Z15: =IF(OR(C15<>"Closed",D15="",F15=""),"",IF(Z11>D15,"",Y75*Loans!C7/12)) | AA15: =IF(OR(C15<>"Closed",D15="",F15=""),"",IF(AA11>D15,"",Z75*Loans!C7/12)) | AB15: =IF(OR(C15<>"Closed",D15="",F15=""),"",IF(AB11>D15,"",AA75*Loans!C7/12)) | AC15: =IF(OR(C15<>"Closed",D15="",F15=""),"",IF(AC11>D15,"",AB75*Loans!C7/12)) | AD15: =IF(OR(C15<>"Closed",D15="",F15=""),"",IF(AD11>D15,"",AC75*Loans!C7/12)) | AE15: =IF(OR(C15<>"Closed",D15="",F15=""),"",IF(AE11>D15,"",AD75*Loans!C7/12)) | AF15: =IF(OR(C15<>"Closed",D15="",F15=""),"",IF(AF11>D15,"",AE75*Loans!C7/12)) | AG15: =IF(OR(C15<>"Closed",D15="",F15=""),"",IF(AG11>D15,"",AF75*Loans!C7/12)) | AH15: =IF(OR(C15<>"Closed",D15="",F15=""),"",IF(AH11>D15,"",AG75*Loans!C7/12)) | AI15: =IF(OR(C15<>"Closed",D15="",F15=""),"",IF(AI11>D15,"",AH75*Loans!C7/12)) | AJ15: =IF(OR(C15<>"Closed",D15="",F15=""),"",IF(AJ11>D15,"",AI75*Loans!C7/12)) | AK15: =IF(OR(C15<>"Closed",D15="",F15=""),"",IF(AK11>D15,"",AJ75*Loans!C7/12)) | AL15: =IF(OR(C15<>"Closed",D15="",F15=""),"",IF(AL11>D15,"",AK75*Loans!C7/12)) | AM15: =IF(OR(C15<>"Closed",D15="",F15=""),"",IF(AM11>D15,"",AL75*Loans!C7/12)) | AN15: =IF(OR(C15<>"Closed",D15="",F15=""),"",IF(AN11>D15,"",AM75*Loans!C7/12)) | AO15: =IF(OR(C15<>"Closed",D15="",F15=""),"",IF(AO11>D15,"",AN75*Loans!C7/12)) | AP15: =IF(OR(C15<>"Closed",D15="",F15=""),"",IF(AP11>D15,"",AO75*Loans!C7/12)) | AQ15: =IF(OR(C15<>"Closed",D15="",F15=""),"",IF(AQ11>D15,"",AP75*Loans!C7/12)) | AR15: =IF(OR(C15<>"Closed",D15="",F15=""),"",IF(AR11>D15,"",AQ75*Loans!C7/12)) | AS15: =IF(OR(C15<>"Closed",D15="",F15=""),"",IF(AS11>D15,"",AR75*Loans!C7/12)) | AT15: =IF(OR(C15<>"Closed",D15="",F15=""),"",IF(AT11>D15,"",AS75*Loans!C7/12)) | AU15: =IF(OR(C15<>"Closed",D15="",F15=""),"",IF(AU11>D15,"",AT75*Loans!C7/12)) | AV15: =IF(OR(C15<>"Closed",D15="",F15=""),"",IF(AV11>D15,"",AU75*Loans!C7/12)) | AW15: =IF(OR(C15<>"Closed",D15="",F15=""),"",IF(AW11>D15,"",AV75*Loans!C7/12)) | AX15: =IF(OR(C15<>"Closed",D15="",F15=""),"",IF(AX11>D15,"",AW75*Loans!C7/12)) | AY15: =IF(OR(C15<>"Closed",D15="",F15=""),"",IF(AY11>D15,"",AX75*Loans!C7/12)) | AZ15: =IF(OR(C15<>"Closed",D15="",F15=""),"",IF(AZ11>D15,"",AY75*Loans!C7/12)) | BA15: =IF(OR(C15<>"Closed",D15="",F15=""),"",IF(BA11>D15,"",AZ75*Loans!C7/12)) | BB15: =IF(OR(C15<>"Closed",D15="",F15=""),"",IF(BB11>D15,"",BA75*Loans!C7/12)) | BC15: =IF(OR(C15<>"Closed",D15="",F15=""),"",IF(BC11>D15,"",BB75*Loans!C7/12)) | BD15: =IF(OR(C15<>"Closed",D15="",F15=""),"",IF(BD11>D15,"",BC75*Loans!C7/12)) | BE15: =IF(OR(C15<>"Closed",D15="",F15=""),"",IF(BE11>D15,"",BD75*Loans!C7/12)) | BF15: =IF(OR(C15<>"Closed",D15="",F15=""),"",IF(BF11>D15,"",BE75*Loans!C7/12)) | BG15: =IF(OR(C15<>"Closed",D15="",F15=""),"",IF(BG11>D15,"",BF75*Loans!C7/12)) | BH15: =IF(OR(C15<>"Closed",D15="",F15=""),"",IF(BH11>D15,"",BG75*Loans!C7/12)) | BI15: =IF(OR(C15<>"Closed",D15="",F15=""),"",IF(BI11>D15,"",BH75*Loans!C7/12)) | BJ15: =IF(OR(C15<>"Closed",D15="",F15=""),"",IF(BJ11>D15,"",BI75*Loans!C7/12)) | BK15: =IF(OR(C15<>"Closed",D15="",F15=""),"",IF(BK11>D15,"",BJ75*Loans!C7/12)) | BL15: =IF(OR(C15<>"Closed",D15="",F15=""),"",IF(BL11>D15,"",BK75*Loans!C7/12)) | BM15: =IF(OR(C15<>"Closed",D15="",F15=""),"",IF(BM11>D15,"",BL75*Loans!C7/12)) | BN15: =IF(OR(C15<>"Closed",D15="",F15=""),"",IF(BN11>D15,"",BM75*Loans!C7/12)) | BO15: =IF(OR(C15<>"Closed",D15="",F15=""),"",IF(BO11>D15,"",BN75*Loans!C7/12)) | BP15: =IF(OR(C15<>"Closed",D15="",F15=""),"",IF(BP11>D15,"",BO75*Loans!C7/12))
A16: =IF(Loans!A16="","",Loans!A16) | B16: =IF(Loans!B16="","",Loans!B16) | C16: =IF(Loans!C16="","",Loans!C16) | D16: =IF(Loans!I16="","",Loans!I16) | E16: =IF(Loans!E16="","",Loans!E16) | F16: =IF(Loans!F16="","",Loans!F16) | G16: =IF(OR(C16<>"Closed",D16="",F16=""),"",PMT(Loans!C7/12,D16,-F16)) | H16: =IF(C16<>"Closed","",SUM(I16:BP16)) | I16: =IF(OR(C16<>"Closed",D16="",F16=""),"",IF(I11>D16,"",F16*Loans!C7/12)) | J16: =IF(OR(C16<>"Closed",D16="",F16=""),"",IF(J11>D16,"",I76*Loans!C7/12)) | K16: =IF(OR(C16<>"Closed",D16="",F16=""),"",IF(K11>D16,"",J76*Loans!C7/12)) | L16: =IF(OR(C16<>"Closed",D16="",F16=""),"",IF(L11>D16,"",K76*Loans!C7/12)) | M16: =IF(OR(C16<>"Closed",D16="",F16=""),"",IF(M11>D16,"",L76*Loans!C7/12)) | N16: =IF(OR(C16<>"Closed",D16="",F16=""),"",IF(N11>D16,"",M76*Loans!C7/12)) | O16: =IF(OR(C16<>"Closed",D16="",F16=""),"",IF(O11>D16,"",N76*Loans!C7/12)) | P16: =IF(OR(C16<>"Closed",D16="",F16=""),"",IF(P11>D16,"",O76*Loans!C7/12)) | Q16: =IF(OR(C16<>"Closed",D16="",F16=""),"",IF(Q11>D16,"",P76*Loans!C7/12)) | R16: =IF(OR(C16<>"Closed",D16="",F16=""),"",IF(R11>D16,"",Q76*Loans!C7/12)) | S16: =IF(OR(C16<>"Closed",D16="",F16=""),"",IF(S11>D16,"",R76*Loans!C7/12)) | T16: =IF(OR(C16<>"Closed",D16="",F16=""),"",IF(T11>D16,"",S76*Loans!C7/12)) | U16: =IF(OR(C16<>"Closed",D16="",F16=""),"",IF(U11>D16,"",T76*Loans!C7/12)) | V16: =IF(OR(C16<>"Closed",D16="",F16=""),"",IF(V11>D16,"",U76*Loans!C7/12)) | W16: =IF(OR(C16<>"Closed",D16="",F16=""),"",IF(W11>D16,"",V76*Loans!C7/12)) | X16: =IF(OR(C16<>"Closed",D16="",F16=""),"",IF(X11>D16,"",W76*Loans!C7/12)) | Y16: =IF(OR(C16<>"Closed",D16="",F16=""),"",IF(Y11>D16,"",X76*Loans!C7/12)) | Z16: =IF(OR(C16<>"Closed",D16="",F16=""),"",IF(Z11>D16,"",Y76*Loans!C7/12)) | AA16: =IF(OR(C16<>"Closed",D16="",F16=""),"",IF(AA11>D16,"",Z76*Loans!C7/12)) | AB16: =IF(OR(C16<>"Closed",D16="",F16=""),"",IF(AB11>D16,"",AA76*Loans!C7/12)) | AC16: =IF(OR(C16<>"Closed",D16="",F16=""),"",IF(AC11>D16,"",AB76*Loans!C7/12)) | AD16: =IF(OR(C16<>"Closed",D16="",F16=""),"",IF(AD11>D16,"",AC76*Loans!C7/12)) | AE16: =IF(OR(C16<>"Closed",D16="",F16=""),"",IF(AE11>D16,"",AD76*Loans!C7/12)) | AF16: =IF(OR(C16<>"Closed",D16="",F16=""),"",IF(AF11>D16,"",AE76*Loans!C7/12)) | AG16: =IF(OR(C16<>"Closed",D16="",F16=""),"",IF(AG11>D16,"",AF76*Loans!C7/12)) | AH16: =IF(OR(C16<>"Closed",D16="",F16=""),"",IF(AH11>D16,"",AG76*Loans!C7/12)) | AI16: =IF(OR(C16<>"Closed",D16="",F16=""),"",IF(AI11>D16,"",AH76*Loans!C7/12)) | AJ16: =IF(OR(C16<>"Closed",D16="",F16=""),"",IF(AJ11>D16,"",AI76*Loans!C7/12)) | AK16: =IF(OR(C16<>"Closed",D16="",F16=""),"",IF(AK11>D16,"",AJ76*Loans!C7/12)) | AL16: =IF(OR(C16<>"Closed",D16="",F16=""),"",IF(AL11>D16,"",AK76*Loans!C7/12)) | AM16: =IF(OR(C16<>"Closed",D16="",F16=""),"",IF(AM11>D16,"",AL76*Loans!C7/12)) | AN16: =IF(OR(C16<>"Closed",D16="",F16=""),"",IF(AN11>D16,"",AM76*Loans!C7/12)) | AO16: =IF(OR(C16<>"Closed",D16="",F16=""),"",IF(AO11>D16,"",AN76*Loans!C7/12)) | AP16: =IF(OR(C16<>"Closed",D16="",F16=""),"",IF(AP11>D16,"",AO76*Loans!C7/12)) | AQ16: =IF(OR(C16<>"Closed",D16="",F16=""),"",IF(AQ11>D16,"",AP76*Loans!C7/12)) | AR16: =IF(OR(C16<>"Closed",D16="",F16=""),"",IF(AR11>D16,"",AQ76*Loans!C7/12)) | AS16: =IF(OR(C16<>"Closed",D16="",F16=""),"",IF(AS11>D16,"",AR76*Loans!C7/12)) | AT16: =IF(OR(C16<>"Closed",D16="",F16=""),"",IF(AT11>D16,"",AS76*Loans!C7/12)) | AU16: =IF(OR(C16<>"Closed",D16="",F16=""),"",IF(AU11>D16,"",AT76*Loans!C7/12)) | AV16: =IF(OR(C16<>"Closed",D16="",F16=""),"",IF(AV11>D16,"",AU76*Loans!C7/12)) | AW16: =IF(OR(C16<>"Closed",D16="",F16=""),"",IF(AW11>D16,"",AV76*Loans!C7/12)) | AX16: =IF(OR(C16<>"Closed",D16="",F16=""),"",IF(AX11>D16,"",AW76*Loans!C7/12)) | AY16: =IF(OR(C16<>"Closed",D16="",F16=""),"",IF(AY11>D16,"",AX76*Loans!C7/12)) | AZ16: =IF(OR(C16<>"Closed",D16="",F16=""),"",IF(AZ11>D16,"",AY76*Loans!C7/12)) | BA16: =IF(OR(C16<>"Closed",D16="",F16=""),"",IF(BA11>D16,"",AZ76*Loans!C7/12)) | BB16: =IF(OR(C16<>"Closed",D16="",F16=""),"",IF(BB11>D16,"",BA76*Loans!C7/12)) | BC16: =IF(OR(C16<>"Closed",D16="",F16=""),"",IF(BC11>D16,"",BB76*Loans!C7/12)) | BD16: =IF(OR(C16<>"Closed",D16="",F16=""),"",IF(BD11>D16,"",BC76*Loans!C7/12)) | BE16: =IF(OR(C16<>"Closed",D16="",F16=""),"",IF(BE11>D16,"",BD76*Loans!C7/12)) | BF16: =IF(OR(C16<>"Closed",D16="",F16=""),"",IF(BF11>D16,"",BE76*Loans!C7/12)) | BG16: =IF(OR(C16<>"Closed",D16="",F16=""),"",IF(BG11>D16,"",BF76*Loans!C7/12)) | BH16: =IF(OR(C16<>"Closed",D16="",F16=""),"",IF(BH11>D16,"",BG76*Loans!C7/12)) | BI16: =IF(OR(C16<>"Closed",D16="",F16=""),"",IF(BI11>D16,"",BH76*Loans!C7/12)) | BJ16: =IF(OR(C16<>"Closed",D16="",F16=""),"",IF(BJ11>D16,"",BI76*Loans!C7/12)) | BK16: =IF(OR(C16<>"Closed",D16="",F16=""),"",IF(BK11>D16,"",BJ76*Loans!C7/12)) | BL16: =IF(OR(C16<>"Closed",D16="",F16=""),"",IF(BL11>D16,"",BK76*Loans!C7/12)) | BM16: =IF(OR(C16<>"Closed",D16="",F16=""),"",IF(BM11>D16,"",BL76*Loans!C7/12)) | BN16: =IF(OR(C16<>"Closed",D16="",F16=""),"",IF(BN11>D16,"",BM76*Loans!C7/12)) | BO16: =IF(OR(C16<>"Closed",D16="",F16=""),"",IF(BO11>D16,"",BN76*Loans!C7/12)) | BP16: =IF(OR(C16<>"Closed",D16="",F16=""),"",IF(BP11>D16,"",BO76*Loans!C7/12))
A17: =IF(Loans!A17="","",Loans!A17) | B17: =IF(Loans!B17="","",Loans!B17) | C17: =IF(Loans!C17="","",Loans!C17) | D17: =IF(Loans!I17="","",Loans!I17) | E17: =IF(Loans!E17="","",Loans!E17) | F17: =IF(Loans!F17="","",Loans!F17) | G17: =IF(OR(C17<>"Closed",D17="",F17=""),"",PMT(Loans!C7/12,D17,-F17)) | H17: =IF(C17<>"Closed","",SUM(I17:BP17)) | I17: =IF(OR(C17<>"Closed",D17="",F17=""),"",IF(I11>D17,"",F17*Loans!C7/12)) | J17: =IF(OR(C17<>"Closed",D17="",F17=""),"",IF(J11>D17,"",I77*Loans!C7/12)) | K17: =IF(OR(C17<>"Closed",D17="",F17=""),"",IF(K11>D17,"",J77*Loans!C7/12)) | L17: =IF(OR(C17<>"Closed",D17="",F17=""),"",IF(L11>D17,"",K77*Loans!C7/12)) | M17: =IF(OR(C17<>"Closed",D17="",F17=""),"",IF(M11>D17,"",L77*Loans!C7/12)) | N17: =IF(OR(C17<>"Closed",D17="",F17=""),"",IF(N11>D17,"",M77*Loans!C7/12)) | O17: =IF(OR(C17<>"Closed",D17="",F17=""),"",IF(O11>D17,"",N77*Loans!C7/12)) | P17: =IF(OR(C17<>"Closed",D17="",F17=""),"",IF(P11>D17,"",O77*Loans!C7/12)) | Q17: =IF(OR(C17<>"Closed",D17="",F17=""),"",IF(Q11>D17,"",P77*Loans!C7/12)) | R17: =IF(OR(C17<>"Closed",D17="",F17=""),"",IF(R11>D17,"",Q77*Loans!C7/12)) | S17: =IF(OR(C17<>"Closed",D17="",F17=""),"",IF(S11>D17,"",R77*Loans!C7/12)) | T17: =IF(OR(C17<>"Closed",D17="",F17=""),"",IF(T11>D17,"",S77*Loans!C7/12)) | U17: =IF(OR(C17<>"Closed",D17="",F17=""),"",IF(U11>D17,"",T77*Loans!C7/12)) | V17: =IF(OR(C17<>"Closed",D17="",F17=""),"",IF(V11>D17,"",U77*Loans!C7/12)) | W17: =IF(OR(C17<>"Closed",D17="",F17=""),"",IF(W11>D17,"",V77*Loans!C7/12)) | X17: =IF(OR(C17<>"Closed",D17="",F17=""),"",IF(X11>D17,"",W77*Loans!C7/12)) | Y17: =IF(OR(C17<>"Closed",D17="",F17=""),"",IF(Y11>D17,"",X77*Loans!C7/12)) | Z17: =IF(OR(C17<>"Closed",D17="",F17=""),"",IF(Z11>D17,"",Y77*Loans!C7/12)) | AA17: =IF(OR(C17<>"Closed",D17="",F17=""),"",IF(AA11>D17,"",Z77*Loans!C7/12)) | AB17: =IF(OR(C17<>"Closed",D17="",F17=""),"",IF(AB11>D17,"",AA77*Loans!C7/12)) | AC17: =IF(OR(C17<>"Closed",D17="",F17=""),"",IF(AC11>D17,"",AB77*Loans!C7/12)) | AD17: =IF(OR(C17<>"Closed",D17="",F17=""),"",IF(AD11>D17,"",AC77*Loans!C7/12)) | AE17: =IF(OR(C17<>"Closed",D17="",F17=""),"",IF(AE11>D17,"",AD77*Loans!C7/12)) | AF17: =IF(OR(C17<>"Closed",D17="",F17=""),"",IF(AF11>D17,"",AE77*Loans!C7/12)) | AG17: =IF(OR(C17<>"Closed",D17="",F17=""),"",IF(AG11>D17,"",AF77*Loans!C7/12)) | AH17: =IF(OR(C17<>"Closed",D17="",F17=""),"",IF(AH11>D17,"",AG77*Loans!C7/12)) | AI17: =IF(OR(C17<>"Closed",D17="",F17=""),"",IF(AI11>D17,"",AH77*Loans!C7/12)) | AJ17: =IF(OR(C17<>"Closed",D17="",F17=""),"",IF(AJ11>D17,"",AI77*Loans!C7/12)) | AK17: =IF(OR(C17<>"Closed",D17="",F17=""),"",IF(AK11>D17,"",AJ77*Loans!C7/12)) | AL17: =IF(OR(C17<>"Closed",D17="",F17=""),"",IF(AL11>D17,"",AK77*Loans!C7/12)) | AM17: =IF(OR(C17<>"Closed",D17="",F17=""),"",IF(AM11>D17,"",AL77*Loans!C7/12)) | AN17: =IF(OR(C17<>"Closed",D17="",F17=""),"",IF(AN11>D17,"",AM77*Loans!C7/12)) | AO17: =IF(OR(C17<>"Closed",D17="",F17=""),"",IF(AO11>D17,"",AN77*Loans!C7/12)) | AP17: =IF(OR(C17<>"Closed",D17="",F17=""),"",IF(AP11>D17,"",AO77*Loans!C7/12)) | AQ17: =IF(OR(C17<>"Closed",D17="",F17=""),"",IF(AQ11>D17,"",AP77*Loans!C7/12)) | AR17: =IF(OR(C17<>"Closed",D17="",F17=""),"",IF(AR11>D17,"",AQ77*Loans!C7/12)) | AS17: =IF(OR(C17<>"Closed",D17="",F17=""),"",IF(AS11>D17,"",AR77*Loans!C7/12)) | AT17: =IF(OR(C17<>"Closed",D17="",F17=""),"",IF(AT11>D17,"",AS77*Loans!C7/12)) | AU17: =IF(OR(C17<>"Closed",D17="",F17=""),"",IF(AU11>D17,"",AT77*Loans!C7/12)) | AV17: =IF(OR(C17<>"Closed",D17="",F17=""),"",IF(AV11>D17,"",AU77*Loans!C7/12)) | AW17: =IF(OR(C17<>"Closed",D17="",F17=""),"",IF(AW11>D17,"",AV77*Loans!C7/12)) | AX17: =IF(OR(C17<>"Closed",D17="",F17=""),"",IF(AX11>D17,"",AW77*Loans!C7/12)) | AY17: =IF(OR(C17<>"Closed",D17="",F17=""),"",IF(AY11>D17,"",AX77*Loans!C7/12)) | AZ17: =IF(OR(C17<>"Closed",D17="",F17=""),"",IF(AZ11>D17,"",AY77*Loans!C7/12)) | BA17: =IF(OR(C17<>"Closed",D17="",F17=""),"",IF(BA11>D17,"",AZ77*Loans!C7/12)) | BB17: =IF(OR(C17<>"Closed",D17="",F17=""),"",IF(BB11>D17,"",BA77*Loans!C7/12)) | BC17: =IF(OR(C17<>"Closed",D17="",F17=""),"",IF(BC11>D17,"",BB77*Loans!C7/12)) | BD17: =IF(OR(C17<>"Closed",D17="",F17=""),"",IF(BD11>D17,"",BC77*Loans!C7/12)) | BE17: =IF(OR(C17<>"Closed",D17="",F17=""),"",IF(BE11>D17,"",BD77*Loans!C7/12)) | BF17: =IF(OR(C17<>"Closed",D17="",F17=""),"",IF(BF11>D17,"",BE77*Loans!C7/12)) | BG17: =IF(OR(C17<>"Closed",D17="",F17=""),"",IF(BG11>D17,"",BF77*Loans!C7/12)) | BH17: =IF(OR(C17<>"Closed",D17="",F17=""),"",IF(BH11>D17,"",BG77*Loans!C7/12)) | BI17: =IF(OR(C17<>"Closed",D17="",F17=""),"",IF(BI11>D17,"",BH77*Loans!C7/12)) | BJ17: =IF(OR(C17<>"Closed",D17="",F17=""),"",IF(BJ11>D17,"",BI77*Loans!C7/12)) | BK17: =IF(OR(C17<>"Closed",D17="",F17=""),"",IF(BK11>D17,"",BJ77*Loans!C7/12)) | BL17: =IF(OR(C17<>"Closed",D17="",F17=""),"",IF(BL11>D17,"",BK77*Loans!C7/12)) | BM17: =IF(OR(C17<>"Closed",D17="",F17=""),"",IF(BM11>D17,"",BL77*Loans!C7/12)) | BN17: =IF(OR(C17<>"Closed",D17="",F17=""),"",IF(BN11>D17,"",BM77*Loans!C7/12)) | BO17: =IF(OR(C17<>"Closed",D17="",F17=""),"",IF(BO11>D17,"",BN77*Loans!C7/12)) | BP17: =IF(OR(C17<>"Closed",D17="",F17=""),"",IF(BP11>D17,"",BO77*Loans!C7/12))
A18: =IF(Loans!A18="","",Loans!A18) | B18: =IF(Loans!B18="","",Loans!B18) | C18: =IF(Loans!C18="","",Loans!C18) | D18: =IF(Loans!I18="","",Loans!I18) | E18: =IF(Loans!E18="","",Loans!E18) | F18: =IF(Loans!F18="","",Loans!F18) | G18: =IF(OR(C18<>"Closed",D18="",F18=""),"",PMT(Loans!C7/12,D18,-F18)) | H18: =IF(C18<>"Closed","",SUM(I18:BP18)) | I18: =IF(OR(C18<>"Closed",D18="",F18=""),"",IF(I11>D18,"",F18*Loans!C7/12)) | J18: =IF(OR(C18<>"Closed",D18="",F18=""),"",IF(J11>D18,"",I78*Loans!C7/12)) | K18: =IF(OR(C18<>"Closed",D18="",F18=""),"",IF(K11>D18,"",J78*Loans!C7/12)) | L18: =IF(OR(C18<>"Closed",D18="",F18=""),"",IF(L11>D18,"",K78*Loans!C7/12)) | M18: =IF(OR(C18<>"Closed",D18="",F18=""),"",IF(M11>D18,"",L78*Loans!C7/12)) | N18: =IF(OR(C18<>"Closed",D18="",F18=""),"",IF(N11>D18,"",M78*Loans!C7/12)) | O18: =IF(OR(C18<>"Closed",D18="",F18=""),"",IF(O11>D18,"",N78*Loans!C7/12)) | P18: =IF(OR(C18<>"Closed",D18="",F18=""),"",IF(P11>D18,"",O78*Loans!C7/12)) | Q18: =IF(OR(C18<>"Closed",D18="",F18=""),"",IF(Q11>D18,"",P78*Loans!C7/12)) | R18: =IF(OR(C18<>"Closed",D18="",F18=""),"",IF(R11>D18,"",Q78*Loans!C7/12)) | S18: =IF(OR(C18<>"Closed",D18="",F18=""),"",IF(S11>D18,"",R78*Loans!C7/12)) | T18: =IF(OR(C18<>"Closed",D18="",F18=""),"",IF(T11>D18,"",S78*Loans!C7/12)) | U18: =IF(OR(C18<>"Closed",D18="",F18=""),"",IF(U11>D18,"",T78*Loans!C7/12)) | V18: =IF(OR(C18<>"Closed",D18="",F18=""),"",IF(V11>D18,"",U78*Loans!C7/12)) | W18: =IF(OR(C18<>"Closed",D18="",F18=""),"",IF(W11>D18,"",V78*Loans!C7/12)) | X18: =IF(OR(C18<>"Closed",D18="",F18=""),"",IF(X11>D18,"",W78*Loans!C7/12)) | Y18: =IF(OR(C18<>"Closed",D18="",F18=""),"",IF(Y11>D18,"",X78*Loans!C7/12)) | Z18: =IF(OR(C18<>"Closed",D18="",F18=""),"",IF(Z11>D18,"",Y78*Loans!C7/12)) | AA18: =IF(OR(C18<>"Closed",D18="",F18=""),"",IF(AA11>D18,"",Z78*Loans!C7/12)) | AB18: =IF(OR(C18<>"Closed",D18="",F18=""),"",IF(AB11>D18,"",AA78*Loans!C7/12)) | AC18: =IF(OR(C18<>"Closed",D18="",F18=""),"",IF(AC11>D18,"",AB78*Loans!C7/12)) | AD18: =IF(OR(C18<>"Closed",D18="",F18=""),"",IF(AD11>D18,"",AC78*Loans!C7/12)) | AE18: =IF(OR(C18<>"Closed",D18="",F18=""),"",IF(AE11>D18,"",AD78*Loans!C7/12)) | AF18: =IF(OR(C18<>"Closed",D18="",F18=""),"",IF(AF11>D18,"",AE78*Loans!C7/12)) | AG18: =IF(OR(C18<>"Closed",D18="",F18=""),"",IF(AG11>D18,"",AF78*Loans!C7/12)) | AH18: =IF(OR(C18<>"Closed",D18="",F18=""),"",IF(AH11>D18,"",AG78*Loans!C7/12)) | AI18: =IF(OR(C18<>"Closed",D18="",F18=""),"",IF(AI11>D18,"",AH78*Loans!C7/12)) | AJ18: =IF(OR(C18<>"Closed",D18="",F18=""),"",IF(AJ11>D18,"",AI78*Loans!C7/12)) | AK18: =IF(OR(C18<>"Closed",D18="",F18=""),"",IF(AK11>D18,"",AJ78*Loans!C7/12)) | AL18: =IF(OR(C18<>"Closed",D18="",F18=""),"",IF(AL11>D18,"",AK78*Loans!C7/12)) | AM18: =IF(OR(C18<>"Closed",D18="",F18=""),"",IF(AM11>D18,"",AL78*Loans!C7/12)) | AN18: =IF(OR(C18<>"Closed",D18="",F18=""),"",IF(AN11>D18,"",AM78*Loans!C7/12)) | AO18: =IF(OR(C18<>"Closed",D18="",F18=""),"",IF(AO11>D18,"",AN78*Loans!C7/12)) | AP18: =IF(OR(C18<>"Closed",D18="",F18=""),"",IF(AP11>D18,"",AO78*Loans!C7/12)) | AQ18: =IF(OR(C18<>"Closed",D18="",F18=""),"",IF(AQ11>D18,"",AP78*Loans!C7/12)) | AR18: =IF(OR(C18<>"Closed",D18="",F18=""),"",IF(AR11>D18,"",AQ78*Loans!C7/12)) | AS18: =IF(OR(C18<>"Closed",D18="",F18=""),"",IF(AS11>D18,"",AR78*Loans!C7/12)) | AT18: =IF(OR(C18<>"Closed",D18="",F18=""),"",IF(AT11>D18,"",AS78*Loans!C7/12)) | AU18: =IF(OR(C18<>"Closed",D18="",F18=""),"",IF(AU11>D18,"",AT78*Loans!C7/12)) | AV18: =IF(OR(C18<>"Closed",D18="",F18=""),"",IF(AV11>D18,"",AU78*Loans!C7/12)) | AW18: =IF(OR(C18<>"Closed",D18="",F18=""),"",IF(AW11>D18,"",AV78*Loans!C7/12)) | AX18: =IF(OR(C18<>"Closed",D18="",F18=""),"",IF(AX11>D18,"",AW78*Loans!C7/12)) | AY18: =IF(OR(C18<>"Closed",D18="",F18=""),"",IF(AY11>D18,"",AX78*Loans!C7/12)) | AZ18: =IF(OR(C18<>"Closed",D18="",F18=""),"",IF(AZ11>D18,"",AY78*Loans!C7/12)) | BA18: =IF(OR(C18<>"Closed",D18="",F18=""),"",IF(BA11>D18,"",AZ78*Loans!C7/12)) | BB18: =IF(OR(C18<>"Closed",D18="",F18=""),"",IF(BB11>D18,"",BA78*Loans!C7/12)) | BC18: =IF(OR(C18<>"Closed",D18="",F18=""),"",IF(BC11>D18,"",BB78*Loans!C7/12)) | BD18: =IF(OR(C18<>"Closed",D18="",F18=""),"",IF(BD11>D18,"",BC78*Loans!C7/12)) | BE18: =IF(OR(C18<>"Closed",D18="",F18=""),"",IF(BE11>D18,"",BD78*Loans!C7/12)) | BF18: =IF(OR(C18<>"Closed",D18="",F18=""),"",IF(BF11>D18,"",BE78*Loans!C7/12)) | BG18: =IF(OR(C18<>"Closed",D18="",F18=""),"",IF(BG11>D18,"",BF78*Loans!C7/12)) | BH18: =IF(OR(C18<>"Closed",D18="",F18=""),"",IF(BH11>D18,"",BG78*Loans!C7/12)) | BI18: =IF(OR(C18<>"Closed",D18="",F18=""),"",IF(BI11>D18,"",BH78*Loans!C7/12)) | BJ18: =IF(OR(C18<>"Closed",D18="",F18=""),"",IF(BJ11>D18,"",BI78*Loans!C7/12)) | BK18: =IF(OR(C18<>"Closed",D18="",F18=""),"",IF(BK11>D18,"",BJ78*Loans!C7/12)) | BL18: =IF(OR(C18<>"Closed",D18="",F18=""),"",IF(BL11>D18,"",BK78*Loans!C7/12)) | BM18: =IF(OR(C18<>"Closed",D18="",F18=""),"",IF(BM11>D18,"",BL78*Loans!C7/12)) | BN18: =IF(OR(C18<>"Closed",D18="",F18=""),"",IF(BN11>D18,"",BM78*Loans!C7/12)) | BO18: =IF(OR(C18<>"Closed",D18="",F18=""),"",IF(BO11>D18,"",BN78*Loans!C7/12)) | BP18: =IF(OR(C18<>"Closed",D18="",F18=""),"",IF(BP11>D18,"",BO78*Loans!C7/12))
A19: =IF(Loans!A19="","",Loans!A19) | B19: =IF(Loans!B19="","",Loans!B19) | C19: =IF(Loans!C19="","",Loans!C19) | D19: =IF(Loans!I19="","",Loans!I19) | E19: =IF(Loans!E19="","",Loans!E19) | F19: =IF(Loans!F19="","",Loans!F19) | G19: =IF(OR(C19<>"Closed",D19="",F19=""),"",PMT(Loans!C7/12,D19,-F19)) | H19: =IF(C19<>"Closed","",SUM(I19:BP19)) | I19: =IF(OR(C19<>"Closed",D19="",F19=""),"",IF(I11>D19,"",F19*Loans!C7/12)) | J19: =IF(OR(C19<>"Closed",D19="",F19=""),"",IF(J11>D19,"",I79*Loans!C7/12)) | K19: =IF(OR(C19<>"Closed",D19="",F19=""),"",IF(K11>D19,"",J79*Loans!C7/12)) | L19: =IF(OR(C19<>"Closed",D19="",F19=""),"",IF(L11>D19,"",K79*Loans!C7/12)) | M19: =IF(OR(C19<>"Closed",D19="",F19=""),"",IF(M11>D19,"",L79*Loans!C7/12)) | N19: =IF(OR(C19<>"Closed",D19="",F19=""),"",IF(N11>D19,"",M79*Loans!C7/12)) | O19: =IF(OR(C19<>"Closed",D19="",F19=""),"",IF(O11>D19,"",N79*Loans!C7/12)) | P19: =IF(OR(C19<>"Closed",D19="",F19=""),"",IF(P11>D19,"",O79*Loans!C7/12)) | Q19: =IF(OR(C19<>"Closed",D19="",F19=""),"",IF(Q11>D19,"",P79*Loans!C7/12)) | R19: =IF(OR(C19<>"Closed",D19="",F19=""),"",IF(R11>D19,"",Q79*Loans!C7/12)) | S19: =IF(OR(C19<>"Closed",D19="",F19=""),"",IF(S11>D19,"",R79*Loans!C7/12)) | T19: =IF(OR(C19<>"Closed",D19="",F19=""),"",IF(T11>D19,"",S79*Loans!C7/12)) | U19: =IF(OR(C19<>"Closed",D19="",F19=""),"",IF(U11>D19,"",T79*Loans!C7/12)) | V19: =IF(OR(C19<>"Closed",D19="",F19=""),"",IF(V11>D19,"",U79*Loans!C7/12)) | W19: =IF(OR(C19<>"Closed",D19="",F19=""),"",IF(W11>D19,"",V79*Loans!C7/12)) | X19: =IF(OR(C19<>"Closed",D19="",F19=""),"",IF(X11>D19,"",W79*Loans!C7/12)) | Y19: =IF(OR(C19<>"Closed",D19="",F19=""),"",IF(Y11>D19,"",X79*Loans!C7/12)) | Z19: =IF(OR(C19<>"Closed",D19="",F19=""),"",IF(Z11>D19,"",Y79*Loans!C7/12)) | AA19: =IF(OR(C19<>"Closed",D19="",F19=""),"",IF(AA11>D19,"",Z79*Loans!C7/12)) | AB19: =IF(OR(C19<>"Closed",D19="",F19=""),"",IF(AB11>D19,"",AA79*Loans!C7/12)) | AC19: =IF(OR(C19<>"Closed",D19="",F19=""),"",IF(AC11>D19,"",AB79*Loans!C7/12)) | AD19: =IF(OR(C19<>"Closed",D19="",F19=""),"",IF(AD11>D19,"",AC79*Loans!C7/12)) | AE19: =IF(OR(C19<>"Closed",D19="",F19=""),"",IF(AE11>D19,"",AD79*Loans!C7/12)) | AF19: =IF(OR(C19<>"Closed",D19="",F19=""),"",IF(AF11>D19,"",AE79*Loans!C7/12)) | AG19: =IF(OR(C19<>"Closed",D19="",F19=""),"",IF(AG11>D19,"",AF79*Loans!C7/12)) | AH19: =IF(OR(C19<>"Closed",D19="",F19=""),"",IF(AH11>D19,"",AG79*Loans!C7/12)) | AI19: =IF(OR(C19<>"Closed",D19="",F19=""),"",IF(AI11>D19,"",AH79*Loans!C7/12)) | AJ19: =IF(OR(C19<>"Closed",D19="",F19=""),"",IF(AJ11>D19,"",AI79*Loans!C7/12)) | AK19: =IF(OR(C19<>"Closed",D19="",F19=""),"",IF(AK11>D19,"",AJ79*Loans!C7/12)) | AL19: =IF(OR(C19<>"Closed",D19="",F19=""),"",IF(AL11>D19,"",AK79*Loans!C7/12)) | AM19: =IF(OR(C19<>"Closed",D19="",F19=""),"",IF(AM11>D19,"",AL79*Loans!C7/12)) | AN19: =IF(OR(C19<>"Closed",D19="",F19=""),"",IF(AN11>D19,"",AM79*Loans!C7/12)) | AO19: =IF(OR(C19<>"Closed",D19="",F19=""),"",IF(AO11>D19,"",AN79*Loans!C7/12)) | AP19: =IF(OR(C19<>"Closed",D19="",F19=""),"",IF(AP11>D19,"",AO79*Loans!C7/12)) | AQ19: =IF(OR(C19<>"Closed",D19="",F19=""),"",IF(AQ11>D19,"",AP79*Loans!C7/12)) | AR19: =IF(OR(C19<>"Closed",D19="",F19=""),"",IF(AR11>D19,"",AQ79*Loans!C7/12)) | AS19: =IF(OR(C19<>"Closed",D19="",F19=""),"",IF(AS11>D19,"",AR79*Loans!C7/12)) | AT19: =IF(OR(C19<>"Closed",D19="",F19=""),"",IF(AT11>D19,"",AS79*Loans!C7/12)) | AU19: =IF(OR(C19<>"Closed",D19="",F19=""),"",IF(AU11>D19,"",AT79*Loans!C7/12)) | AV19: =IF(OR(C19<>"Closed",D19="",F19=""),"",IF(AV11>D19,"",AU79*Loans!C7/12)) | AW19: =IF(OR(C19<>"Closed",D19="",F19=""),"",IF(AW11>D19,"",AV79*Loans!C7/12)) | AX19: =IF(OR(C19<>"Closed",D19="",F19=""),"",IF(AX11>D19,"",AW79*Loans!C7/12)) | AY19: =IF(OR(C19<>"Closed",D19="",F19=""),"",IF(AY11>D19,"",AX79*Loans!C7/12)) | AZ19: =IF(OR(C19<>"Closed",D19="",F19=""),"",IF(AZ11>D19,"",AY79*Loans!C7/12)) | BA19: =IF(OR(C19<>"Closed",D19="",F19=""),"",IF(BA11>D19,"",AZ79*Loans!C7/12)) | BB19: =IF(OR(C19<>"Closed",D19="",F19=""),"",IF(BB11>D19,"",BA79*Loans!C7/12)) | BC19: =IF(OR(C19<>"Closed",D19="",F19=""),"",IF(BC11>D19,"",BB79*Loans!C7/12)) | BD19: =IF(OR(C19<>"Closed",D19="",F19=""),"",IF(BD11>D19,"",BC79*Loans!C7/12)) | BE19: =IF(OR(C19<>"Closed",D19="",F19=""),"",IF(BE11>D19,"",BD79*Loans!C7/12)) | BF19: =IF(OR(C19<>"Closed",D19="",F19=""),"",IF(BF11>D19,"",BE79*Loans!C7/12)) | BG19: =IF(OR(C19<>"Closed",D19="",F19=""),"",IF(BG11>D19,"",BF79*Loans!C7/12)) | BH19: =IF(OR(C19<>"Closed",D19="",F19=""),"",IF(BH11>D19,"",BG79*Loans!C7/12)) | BI19: =IF(OR(C19<>"Closed",D19="",F19=""),"",IF(BI11>D19,"",BH79*Loans!C7/12)) | BJ19: =IF(OR(C19<>"Closed",D19="",F19=""),"",IF(BJ11>D19,"",BI79*Loans!C7/12)) | BK19: =IF(OR(C19<>"Closed",D19="",F19=""),"",IF(BK11>D19,"",BJ79*Loans!C7/12)) | BL19: =IF(OR(C19<>"Closed",D19="",F19=""),"",IF(BL11>D19,"",BK79*Loans!C7/12)) | BM19: =IF(OR(C19<>"Closed",D19="",F19=""),"",IF(BM11>D19,"",BL79*Loans!C7/12)) | BN19: =IF(OR(C19<>"Closed",D19="",F19=""),"",IF(BN11>D19,"",BM79*Loans!C7/12)) | BO19: =IF(OR(C19<>"Closed",D19="",F19=""),"",IF(BO11>D19,"",BN79*Loans!C7/12)) | BP19: =IF(OR(C19<>"Closed",D19="",F19=""),"",IF(BP11>D19,"",BO79*Loans!C7/12))
A20: =IF(Loans!A20="","",Loans!A20) | B20: =IF(Loans!B20="","",Loans!B20) | C20: =IF(Loans!C20="","",Loans!C20) | D20: =IF(Loans!I20="","",Loans!I20) | E20: =IF(Loans!E20="","",Loans!E20) | F20: =IF(Loans!F20="","",Loans!F20) | G20: =IF(OR(C20<>"Closed",D20="",F20=""),"",PMT(Loans!C7/12,D20,-F20)) | H20: =IF(C20<>"Closed","",SUM(I20:BP20)) | I20: =IF(OR(C20<>"Closed",D20="",F20=""),"",IF(I11>D20,"",F20*Loans!C7/12)) | J20: =IF(OR(C20<>"Closed",D20="",F20=""),"",IF(J11>D20,"",I80*Loans!C7/12)) | K20: =IF(OR(C20<>"Closed",D20="",F20=""),"",IF(K11>D20,"",J80*Loans!C7/12)) | L20: =IF(OR(C20<>"Closed",D20="",F20=""),"",IF(L11>D20,"",K80*Loans!C7/12)) | M20: =IF(OR(C20<>"Closed",D20="",F20=""),"",IF(M11>D20,"",L80*Loans!C7/12)) | N20: =IF(OR(C20<>"Closed",D20="",F20=""),"",IF(N11>D20,"",M80*Loans!C7/12)) | O20: =IF(OR(C20<>"Closed",D20="",F20=""),"",IF(O11>D20,"",N80*Loans!C7/12)) | P20: =IF(OR(C20<>"Closed",D20="",F20=""),"",IF(P11>D20,"",O80*Loans!C7/12)) | Q20: =IF(OR(C20<>"Closed",D20="",F20=""),"",IF(Q11>D20,"",P80*Loans!C7/12)) | R20: =IF(OR(C20<>"Closed",D20="",F20=""),"",IF(R11>D20,"",Q80*Loans!C7/12)) | S20: =IF(OR(C20<>"Closed",D20="",F20=""),"",IF(S11>D20,"",R80*Loans!C7/12)) | T20: =IF(OR(C20<>"Closed",D20="",F20=""),"",IF(T11>D20,"",S80*Loans!C7/12)) | U20: =IF(OR(C20<>"Closed",D20="",F20=""),"",IF(U11>D20,"",T80*Loans!C7/12)) | V20: =IF(OR(C20<>"Closed",D20="",F20=""),"",IF(V11>D20,"",U80*Loans!C7/12)) | W20: =IF(OR(C20<>"Closed",D20="",F20=""),"",IF(W11>D20,"",V80*Loans!C7/12)) | X20: =IF(OR(C20<>"Closed",D20="",F20=""),"",IF(X11>D20,"",W80*Loans!C7/12)) | Y20: =IF(OR(C20<>"Closed",D20="",F20=""),"",IF(Y11>D20,"",X80*Loans!C7/12)) | Z20: =IF(OR(C20<>"Closed",D20="",F20=""),"",IF(Z11>D20,"",Y80*Loans!C7/12)) | AA20: =IF(OR(C20<>"Closed",D20="",F20=""),"",IF(AA11>D20,"",Z80*Loans!C7/12)) | AB20: =IF(OR(C20<>"Closed",D20="",F20=""),"",IF(AB11>D20,"",AA80*Loans!C7/12)) | AC20: =IF(OR(C20<>"Closed",D20="",F20=""),"",IF(AC11>D20,"",AB80*Loans!C7/12)) | AD20: =IF(OR(C20<>"Closed",D20="",F20=""),"",IF(AD11>D20,"",AC80*Loans!C7/12)) | AE20: =IF(OR(C20<>"Closed",D20="",F20=""),"",IF(AE11>D20,"",AD80*Loans!C7/12)) | AF20: =IF(OR(C20<>"Closed",D20="",F20=""),"",IF(AF11>D20,"",AE80*Loans!C7/12)) | AG20: =IF(OR(C20<>"Closed",D20="",F20=""),"",IF(AG11>D20,"",AF80*Loans!C7/12)) | AH20: =IF(OR(C20<>"Closed",D20="",F20=""),"",IF(AH11>D20,"",AG80*Loans!C7/12)) | AI20: =IF(OR(C20<>"Closed",D20="",F20=""),"",IF(AI11>D20,"",AH80*Loans!C7/12)) | AJ20: =IF(OR(C20<>"Closed",D20="",F20=""),"",IF(AJ11>D20,"",AI80*Loans!C7/12)) | AK20: =IF(OR(C20<>"Closed",D20="",F20=""),"",IF(AK11>D20,"",AJ80*Loans!C7/12)) | AL20: =IF(OR(C20<>"Closed",D20="",F20=""),"",IF(AL11>D20,"",AK80*Loans!C7/12)) | AM20: =IF(OR(C20<>"Closed",D20="",F20=""),"",IF(AM11>D20,"",AL80*Loans!C7/12)) | AN20: =IF(OR(C20<>"Closed",D20="",F20=""),"",IF(AN11>D20,"",AM80*Loans!C7/12)) | AO20: =IF(OR(C20<>"Closed",D20="",F20=""),"",IF(AO11>D20,"",AN80*Loans!C7/12)) | AP20: =IF(OR(C20<>"Closed",D20="",F20=""),"",IF(AP11>D20,"",AO80*Loans!C7/12)) | AQ20: =IF(OR(C20<>"Closed",D20="",F20=""),"",IF(AQ11>D20,"",AP80*Loans!C7/12)) | AR20: =IF(OR(C20<>"Closed",D20="",F20=""),"",IF(AR11>D20,"",AQ80*Loans!C7/12)) | AS20: =IF(OR(C20<>"Closed",D20="",F20=""),"",IF(AS11>D20,"",AR80*Loans!C7/12)) | AT20: =IF(OR(C20<>"Closed",D20="",F20=""),"",IF(AT11>D20,"",AS80*Loans!C7/12)) | AU20: =IF(OR(C20<>"Closed",D20="",F20=""),"",IF(AU11>D20,"",AT80*Loans!C7/12)) | AV20: =IF(OR(C20<>"Closed",D20="",F20=""),"",IF(AV11>D20,"",AU80*Loans!C7/12)) | AW20: =IF(OR(C20<>"Closed",D20="",F20=""),"",IF(AW11>D20,"",AV80*Loans!C7/12)) | AX20: =IF(OR(C20<>"Closed",D20="",F20=""),"",IF(AX11>D20,"",AW80*Loans!C7/12)) | AY20: =IF(OR(C20<>"Closed",D20="",F20=""),"",IF(AY11>D20,"",AX80*Loans!C7/12)) | AZ20: =IF(OR(C20<>"Closed",D20="",F20=""),"",IF(AZ11>D20,"",AY80*Loans!C7/12)) | BA20: =IF(OR(C20<>"Closed",D20="",F20=""),"",IF(BA11>D20,"",AZ80*Loans!C7/12)) | BB20: =IF(OR(C20<>"Closed",D20="",F20=""),"",IF(BB11>D20,"",BA80*Loans!C7/12)) | BC20: =IF(OR(C20<>"Closed",D20="",F20=""),"",IF(BC11>D20,"",BB80*Loans!C7/12)) | BD20: =IF(OR(C20<>"Closed",D20="",F20=""),"",IF(BD11>D20,"",BC80*Loans!C7/12)) | BE20: =IF(OR(C20<>"Closed",D20="",F20=""),"",IF(BE11>D20,"",BD80*Loans!C7/12)) | BF20: =IF(OR(C20<>"Closed",D20="",F20=""),"",IF(BF11>D20,"",BE80*Loans!C7/12)) | BG20: =IF(OR(C20<>"Closed",D20="",F20=""),"",IF(BG11>D20,"",BF80*Loans!C7/12)) | BH20: =IF(OR(C20<>"Closed",D20="",F20=""),"",IF(BH11>D20,"",BG80*Loans!C7/12)) | BI20: =IF(OR(C20<>"Closed",D20="",F20=""),"",IF(BI11>D20,"",BH80*Loans!C7/12)) | BJ20: =IF(OR(C20<>"Closed",D20="",F20=""),"",IF(BJ11>D20,"",BI80*Loans!C7/12)) | BK20: =IF(OR(C20<>"Closed",D20="",F20=""),"",IF(BK11>D20,"",BJ80*Loans!C7/12)) | BL20: =IF(OR(C20<>"Closed",D20="",F20=""),"",IF(BL11>D20,"",BK80*Loans!C7/12)) | BM20: =IF(OR(C20<>"Closed",D20="",F20=""),"",IF(BM11>D20,"",BL80*Loans!C7/12)) | BN20: =IF(OR(C20<>"Closed",D20="",F20=""),"",IF(BN11>D20,"",BM80*Loans!C7/12)) | BO20: =IF(OR(C20<>"Closed",D20="",F20=""),"",IF(BO11>D20,"",BN80*Loans!C7/12)) | BP20: =IF(OR(C20<>"Closed",D20="",F20=""),"",IF(BP11>D20,"",BO80*Loans!C7/12))
A21: =IF(Loans!A21="","",Loans!A21) | B21: =IF(Loans!B21="","",Loans!B21) | C21: =IF(Loans!C21="","",Loans!C21) | D21: =IF(Loans!I21="","",Loans!I21) | E21: =IF(Loans!E21="","",Loans!E21) | F21: =IF(Loans!F21="","",Loans!F21) | G21: =IF(OR(C21<>"Closed",D21="",F21=""),"",PMT(Loans!C7/12,D21,-F21)) | H21: =IF(C21<>"Closed","",SUM(I21:BP21)) | I21: =IF(OR(C21<>"Closed",D21="",F21=""),"",IF(I11>D21,"",F21*Loans!C7/12)) | J21: =IF(OR(C21<>"Closed",D21="",F21=""),"",IF(J11>D21,"",I81*Loans!C7/12)) | K21: =IF(OR(C21<>"Closed",D21="",F21=""),"",IF(K11>D21,"",J81*Loans!C7/12)) | L21: =IF(OR(C21<>"Closed",D21="",F21=""),"",IF(L11>D21,"",K81*Loans!C7/12)) | M21: =IF(OR(C21<>"Closed",D21="",F21=""),"",IF(M11>D21,"",L81*Loans!C7/12)) | N21: =IF(OR(C21<>"Closed",D21="",F21=""),"",IF(N11>D21,"",M81*Loans!C7/12)) | O21: =IF(OR(C21<>"Closed",D21="",F21=""),"",IF(O11>D21,"",N81*Loans!C7/12)) | P21: =IF(OR(C21<>"Closed",D21="",F21=""),"",IF(P11>D21,"",O81*Loans!C7/12)) | Q21: =IF(OR(C21<>"Closed",D21="",F21=""),"",IF(Q11>D21,"",P81*Loans!C7/12)) | R21: =IF(OR(C21<>"Closed",D21="",F21=""),"",IF(R11>D21,"",Q81*Loans!C7/12)) | S21: =IF(OR(C21<>"Closed",D21="",F21=""),"",IF(S11>D21,"",R81*Loans!C7/12)) | T21: =IF(OR(C21<>"Closed",D21="",F21=""),"",IF(T11>D21,"",S81*Loans!C7/12)) | U21: =IF(OR(C21<>"Closed",D21="",F21=""),"",IF(U11>D21,"",T81*Loans!C7/12)) | V21: =IF(OR(C21<>"Closed",D21="",F21=""),"",IF(V11>D21,"",U81*Loans!C7/12)) | W21: =IF(OR(C21<>"Closed",D21="",F21=""),"",IF(W11>D21,"",V81*Loans!C7/12)) | X21: =IF(OR(C21<>"Closed",D21="",F21=""),"",IF(X11>D21,"",W81*Loans!C7/12)) | Y21: =IF(OR(C21<>"Closed",D21="",F21=""),"",IF(Y11>D21,"",X81*Loans!C7/12)) | Z21: =IF(OR(C21<>"Closed",D21="",F21=""),"",IF(Z11>D21,"",Y81*Loans!C7/12)) | AA21: =IF(OR(C21<>"Closed",D21="",F21=""),"",IF(AA11>D21,"",Z81*Loans!C7/12)) | AB21: =IF(OR(C21<>"Closed",D21="",F21=""),"",IF(AB11>D21,"",AA81*Loans!C7/12)) | AC21: =IF(OR(C21<>"Closed",D21="",F21=""),"",IF(AC11>D21,"",AB81*Loans!C7/12)) | AD21: =IF(OR(C21<>"Closed",D21="",F21=""),"",IF(AD11>D21,"",AC81*Loans!C7/12)) | AE21: =IF(OR(C21<>"Closed",D21="",F21=""),"",IF(AE11>D21,"",AD81*Loans!C7/12)) | AF21: =IF(OR(C21<>"Closed",D21="",F21=""),"",IF(AF11>D21,"",AE81*Loans!C7/12)) | AG21: =IF(OR(C21<>"Closed",D21="",F21=""),"",IF(AG11>D21,"",AF81*Loans!C7/12)) | AH21: =IF(OR(C21<>"Closed",D21="",F21=""),"",IF(AH11>D21,"",AG81*Loans!C7/12)) | AI21: =IF(OR(C21<>"Closed",D21="",F21=""),"",IF(AI11>D21,"",AH81*Loans!C7/12)) | AJ21: =IF(OR(C21<>"Closed",D21="",F21=""),"",IF(AJ11>D21,"",AI81*Loans!C7/12)) | AK21: =IF(OR(C21<>"Closed",D21="",F21=""),"",IF(AK11>D21,"",AJ81*Loans!C7/12)) | AL21: =IF(OR(C21<>"Closed",D21="",F21=""),"",IF(AL11>D21,"",AK81*Loans!C7/12)) | AM21: =IF(OR(C21<>"Closed",D21="",F21=""),"",IF(AM11>D21,"",AL81*Loans!C7/12)) | AN21: =IF(OR(C21<>"Closed",D21="",F21=""),"",IF(AN11>D21,"",AM81*Loans!C7/12)) | AO21: =IF(OR(C21<>"Closed",D21="",F21=""),"",IF(AO11>D21,"",AN81*Loans!C7/12)) | AP21: =IF(OR(C21<>"Closed",D21="",F21=""),"",IF(AP11>D21,"",AO81*Loans!C7/12)) | AQ21: =IF(OR(C21<>"Closed",D21="",F21=""),"",IF(AQ11>D21,"",AP81*Loans!C7/12)) | AR21: =IF(OR(C21<>"Closed",D21="",F21=""),"",IF(AR11>D21,"",AQ81*Loans!C7/12)) | AS21: =IF(OR(C21<>"Closed",D21="",F21=""),"",IF(AS11>D21,"",AR81*Loans!C7/12)) | AT21: =IF(OR(C21<>"Closed",D21="",F21=""),"",IF(AT11>D21,"",AS81*Loans!C7/12)) | AU21: =IF(OR(C21<>"Closed",D21="",F21=""),"",IF(AU11>D21,"",AT81*Loans!C7/12)) | AV21: =IF(OR(C21<>"Closed",D21="",F21=""),"",IF(AV11>D21,"",AU81*Loans!C7/12)) | AW21: =IF(OR(C21<>"Closed",D21="",F21=""),"",IF(AW11>D21,"",AV81*Loans!C7/12)) | AX21: =IF(OR(C21<>"Closed",D21="",F21=""),"",IF(AX11>D21,"",AW81*Loans!C7/12)) | AY21: =IF(OR(C21<>"Closed",D21="",F21=""),"",IF(AY11>D21,"",AX81*Loans!C7/12)) | AZ21: =IF(OR(C21<>"Closed",D21="",F21=""),"",IF(AZ11>D21,"",AY81*Loans!C7/12)) | BA21: =IF(OR(C21<>"Closed",D21="",F21=""),"",IF(BA11>D21,"",AZ81*Loans!C7/12)) | BB21: =IF(OR(C21<>"Closed",D21="",F21=""),"",IF(BB11>D21,"",BA81*Loans!C7/12)) | BC21: =IF(OR(C21<>"Closed",D21="",F21=""),"",IF(BC11>D21,"",BB81*Loans!C7/12)) | BD21: =IF(OR(C21<>"Closed",D21="",F21=""),"",IF(BD11>D21,"",BC81*Loans!C7/12)) | BE21: =IF(OR(C21<>"Closed",D21="",F21=""),"",IF(BE11>D21,"",BD81*Loans!C7/12)) | BF21: =IF(OR(C21<>"Closed",D21="",F21=""),"",IF(BF11>D21,"",BE81*Loans!C7/12)) | BG21: =IF(OR(C21<>"Closed",D21="",F21=""),"",IF(BG11>D21,"",BF81*Loans!C7/12)) | BH21: =IF(OR(C21<>"Closed",D21="",F21=""),"",IF(BH11>D21,"",BG81*Loans!C7/12)) | BI21: =IF(OR(C21<>"Closed",D21="",F21=""),"",IF(BI11>D21,"",BH81*Loans!C7/12)) | BJ21: =IF(OR(C21<>"Closed",D21="",F21=""),"",IF(BJ11>D21,"",BI81*Loans!C7/12)) | BK21: =IF(OR(C21<>"Closed",D21="",F21=""),"",IF(BK11>D21,"",BJ81*Loans!C7/12)) | BL21: =IF(OR(C21<>"Closed",D21="",F21=""),"",IF(BL11>D21,"",BK81*Loans!C7/12)) | BM21: =IF(OR(C21<>"Closed",D21="",F21=""),"",IF(BM11>D21,"",BL81*Loans!C7/12)) | BN21: =IF(OR(C21<>"Closed",D21="",F21=""),"",IF(BN11>D21,"",BM81*Loans!C7/12)) | BO21: =IF(OR(C21<>"Closed",D21="",F21=""),"",IF(BO11>D21,"",BN81*Loans!C7/12)) | BP21: =IF(OR(C21<>"Closed",D21="",F21=""),"",IF(BP11>D21,"",BO81*Loans!C7/12))
A22: =IF(Loans!A22="","",Loans!A22) | B22: =IF(Loans!B22="","",Loans!B22) | C22: =IF(Loans!C22="","",Loans!C22) | D22: =IF(Loans!I22="","",Loans!I22) | E22: =IF(Loans!E22="","",Loans!E22) | F22: =IF(Loans!F22="","",Loans!F22) | G22: =IF(OR(C22<>"Closed",D22="",F22=""),"",PMT(Loans!C7/12,D22,-F22)) | H22: =IF(C22<>"Closed","",SUM(I22:BP22)) | I22: =IF(OR(C22<>"Closed",D22="",F22=""),"",IF(I11>D22,"",F22*Loans!C7/12)) | J22: =IF(OR(C22<>"Closed",D22="",F22=""),"",IF(J11>D22,"",I82*Loans!C7/12)) | K22: =IF(OR(C22<>"Closed",D22="",F22=""),"",IF(K11>D22,"",J82*Loans!C7/12)) | L22: =IF(OR(C22<>"Closed",D22="",F22=""),"",IF(L11>D22,"",K82*Loans!C7/12)) | M22: =IF(OR(C22<>"Closed",D22="",F22=""),"",IF(M11>D22,"",L82*Loans!C7/12)) | N22: =IF(OR(C22<>"Closed",D22="",F22=""),"",IF(N11>D22,"",M82*Loans!C7/12)) | O22: =IF(OR(C22<>"Closed",D22="",F22=""),"",IF(O11>D22,"",N82*Loans!C7/12)) | P22: =IF(OR(C22<>"Closed",D22="",F22=""),"",IF(P11>D22,"",O82*Loans!C7/12)) | Q22: =IF(OR(C22<>"Closed",D22="",F22=""),"",IF(Q11>D22,"",P82*Loans!C7/12)) | R22: =IF(OR(C22<>"Closed",D22="",F22=""),"",IF(R11>D22,"",Q82*Loans!C7/12)) | S22: =IF(OR(C22<>"Closed",D22="",F22=""),"",IF(S11>D22,"",R82*Loans!C7/12)) | T22: =IF(OR(C22<>"Closed",D22="",F22=""),"",IF(T11>D22,"",S82*Loans!C7/12)) | U22: =IF(OR(C22<>"Closed",D22="",F22=""),"",IF(U11>D22,"",T82*Loans!C7/12)) | V22: =IF(OR(C22<>"Closed",D22="",F22=""),"",IF(V11>D22,"",U82*Loans!C7/12)) | W22: =IF(OR(C22<>"Closed",D22="",F22=""),"",IF(W11>D22,"",V82*Loans!C7/12)) | X22: =IF(OR(C22<>"Closed",D22="",F22=""),"",IF(X11>D22,"",W82*Loans!C7/12)) | Y22: =IF(OR(C22<>"Closed",D22="",F22=""),"",IF(Y11>D22,"",X82*Loans!C7/12)) | Z22: =IF(OR(C22<>"Closed",D22="",F22=""),"",IF(Z11>D22,"",Y82*Loans!C7/12)) | AA22: =IF(OR(C22<>"Closed",D22="",F22=""),"",IF(AA11>D22,"",Z82*Loans!C7/12)) | AB22: =IF(OR(C22<>"Closed",D22="",F22=""),"",IF(AB11>D22,"",AA82*Loans!C7/12)) | AC22: =IF(OR(C22<>"Closed",D22="",F22=""),"",IF(AC11>D22,"",AB82*Loans!C7/12)) | AD22: =IF(OR(C22<>"Closed",D22="",F22=""),"",IF(AD11>D22,"",AC82*Loans!C7/12)) | AE22: =IF(OR(C22<>"Closed",D22="",F22=""),"",IF(AE11>D22,"",AD82*Loans!C7/12)) | AF22: =IF(OR(C22<>"Closed",D22="",F22=""),"",IF(AF11>D22,"",AE82*Loans!C7/12)) | AG22: =IF(OR(C22<>"Closed",D22="",F22=""),"",IF(AG11>D22,"",AF82*Loans!C7/12)) | AH22: =IF(OR(C22<>"Closed",D22="",F22=""),"",IF(AH11>D22,"",AG82*Loans!C7/12)) | AI22: =IF(OR(C22<>"Closed",D22="",F22=""),"",IF(AI11>D22,"",AH82*Loans!C7/12)) | AJ22: =IF(OR(C22<>"Closed",D22="",F22=""),"",IF(AJ11>D22,"",AI82*Loans!C7/12)) | AK22: =IF(OR(C22<>"Closed",D22="",F22=""),"",IF(AK11>D22,"",AJ82*Loans!C7/12)) | AL22: =IF(OR(C22<>"Closed",D22="",F22=""),"",IF(AL11>D22,"",AK82*Loans!C7/12)) | AM22: =IF(OR(C22<>"Closed",D22="",F22=""),"",IF(AM11>D22,"",AL82*Loans!C7/12)) | AN22: =IF(OR(C22<>"Closed",D22="",F22=""),"",IF(AN11>D22,"",AM82*Loans!C7/12)) | AO22: =IF(OR(C22<>"Closed",D22="",F22=""),"",IF(AO11>D22,"",AN82*Loans!C7/12)) | AP22: =IF(OR(C22<>"Closed",D22="",F22=""),"",IF(AP11>D22,"",AO82*Loans!C7/12)) | AQ22: =IF(OR(C22<>"Closed",D22="",F22=""),"",IF(AQ11>D22,"",AP82*Loans!C7/12)) | AR22: =IF(OR(C22<>"Closed",D22="",F22=""),"",IF(AR11>D22,"",AQ82*Loans!C7/12)) | AS22: =IF(OR(C22<>"Closed",D22="",F22=""),"",IF(AS11>D22,"",AR82*Loans!C7/12)) | AT22: =IF(OR(C22<>"Closed",D22="",F22=""),"",IF(AT11>D22,"",AS82*Loans!C7/12)) | AU22: =IF(OR(C22<>"Closed",D22="",F22=""),"",IF(AU11>D22,"",AT82*Loans!C7/12)) | AV22: =IF(OR(C22<>"Closed",D22="",F22=""),"",IF(AV11>D22,"",AU82*Loans!C7/12)) | AW22: =IF(OR(C22<>"Closed",D22="",F22=""),"",IF(AW11>D22,"",AV82*Loans!C7/12)) | AX22: =IF(OR(C22<>"Closed",D22="",F22=""),"",IF(AX11>D22,"",AW82*Loans!C7/12)) | AY22: =IF(OR(C22<>"Closed",D22="",F22=""),"",IF(AY11>D22,"",AX82*Loans!C7/12)) | AZ22: =IF(OR(C22<>"Closed",D22="",F22=""),"",IF(AZ11>D22,"",AY82*Loans!C7/12)) | BA22: =IF(OR(C22<>"Closed",D22="",F22=""),"",IF(BA11>D22,"",AZ82*Loans!C7/12)) | BB22: =IF(OR(C22<>"Closed",D22="",F22=""),"",IF(BB11>D22,"",BA82*Loans!C7/12)) | BC22: =IF(OR(C22<>"Closed",D22="",F22=""),"",IF(BC11>D22,"",BB82*Loans!C7/12)) | BD22: =IF(OR(C22<>"Closed",D22="",F22=""),"",IF(BD11>D22,"",BC82*Loans!C7/12)) | BE22: =IF(OR(C22<>"Closed",D22="",F22=""),"",IF(BE11>D22,"",BD82*Loans!C7/12)) | BF22: =IF(OR(C22<>"Closed",D22="",F22=""),"",IF(BF11>D22,"",BE82*Loans!C7/12)) | BG22: =IF(OR(C22<>"Closed",D22="",F22=""),"",IF(BG11>D22,"",BF82*Loans!C7/12)) | BH22: =IF(OR(C22<>"Closed",D22="",F22=""),"",IF(BH11>D22,"",BG82*Loans!C7/12)) | BI22: =IF(OR(C22<>"Closed",D22="",F22=""),"",IF(BI11>D22,"",BH82*Loans!C7/12)) | BJ22: =IF(OR(C22<>"Closed",D22="",F22=""),"",IF(BJ11>D22,"",BI82*Loans!C7/12)) | BK22: =IF(OR(C22<>"Closed",D22="",F22=""),"",IF(BK11>D22,"",BJ82*Loans!C7/12)) | BL22: =IF(OR(C22<>"Closed",D22="",F22=""),"",IF(BL11>D22,"",BK82*Loans!C7/12)) | BM22: =IF(OR(C22<>"Closed",D22="",F22=""),"",IF(BM11>D22,"",BL82*Loans!C7/12)) | BN22: =IF(OR(C22<>"Closed",D22="",F22=""),"",IF(BN11>D22,"",BM82*Loans!C7/12)) | BO22: =IF(OR(C22<>"Closed",D22="",F22=""),"",IF(BO11>D22,"",BN82*Loans!C7/12)) | BP22: =IF(OR(C22<>"Closed",D22="",F22=""),"",IF(BP11>D22,"",BO82*Loans!C7/12))
A23: =IF(Loans!A23="","",Loans!A23) | B23: =IF(Loans!B23="","",Loans!B23) | C23: =IF(Loans!C23="","",Loans!C23) | D23: =IF(Loans!I23="","",Loans!I23) | E23: =IF(Loans!E23="","",Loans!E23) | F23: =IF(Loans!F23="","",Loans!F23) | G23: =IF(OR(C23<>"Closed",D23="",F23=""),"",PMT(Loans!C7/12,D23,-F23)) | H23: =IF(C23<>"Closed","",SUM(I23:BP23)) | I23: =IF(OR(C23<>"Closed",D23="",F23=""),"",IF(I11>D23,"",F23*Loans!C7/12)) | J23: =IF(OR(C23<>"Closed",D23="",F23=""),"",IF(J11>D23,"",I83*Loans!C7/12)) | K23: =IF(OR(C23<>"Closed",D23="",F23=""),"",IF(K11>D23,"",J83*Loans!C7/12)) | L23: =IF(OR(C23<>"Closed",D23="",F23=""),"",IF(L11>D23,"",K83*Loans!C7/12)) | M23: =IF(OR(C23<>"Closed",D23="",F23=""),"",IF(M11>D23,"",L83*Loans!C7/12)) | N23: =IF(OR(C23<>"Closed",D23="",F23=""),"",IF(N11>D23,"",M83*Loans!C7/12)) | O23: =IF(OR(C23<>"Closed",D23="",F23=""),"",IF(O11>D23,"",N83*Loans!C7/12)) | P23: =IF(OR(C23<>"Closed",D23="",F23=""),"",IF(P11>D23,"",O83*Loans!C7/12)) | Q23: =IF(OR(C23<>"Closed",D23="",F23=""),"",IF(Q11>D23,"",P83*Loans!C7/12)) | R23: =IF(OR(C23<>"Closed",D23="",F23=""),"",IF(R11>D23,"",Q83*Loans!C7/12)) | S23: =IF(OR(C23<>"Closed",D23="",F23=""),"",IF(S11>D23,"",R83*Loans!C7/12)) | T23: =IF(OR(C23<>"Closed",D23="",F23=""),"",IF(T11>D23,"",S83*Loans!C7/12)) | U23: =IF(OR(C23<>"Closed",D23="",F23=""),"",IF(U11>D23,"",T83*Loans!C7/12)) | V23: =IF(OR(C23<>"Closed",D23="",F23=""),"",IF(V11>D23,"",U83*Loans!C7/12)) | W23: =IF(OR(C23<>"Closed",D23="",F23=""),"",IF(W11>D23,"",V83*Loans!C7/12)) | X23: =IF(OR(C23<>"Closed",D23="",F23=""),"",IF(X11>D23,"",W83*Loans!C7/12)) | Y23: =IF(OR(C23<>"Closed",D23="",F23=""),"",IF(Y11>D23,"",X83*Loans!C7/12)) | Z23: =IF(OR(C23<>"Closed",D23="",F23=""),"",IF(Z11>D23,"",Y83*Loans!C7/12)) | AA23: =IF(OR(C23<>"Closed",D23="",F23=""),"",IF(AA11>D23,"",Z83*Loans!C7/12)) | AB23: =IF(OR(C23<>"Closed",D23="",F23=""),"",IF(AB11>D23,"",AA83*Loans!C7/12)) | AC23: =IF(OR(C23<>"Closed",D23="",F23=""),"",IF(AC11>D23,"",AB83*Loans!C7/12)) | AD23: =IF(OR(C23<>"Closed",D23="",F23=""),"",IF(AD11>D23,"",AC83*Loans!C7/12)) | AE23: =IF(OR(C23<>"Closed",D23="",F23=""),"",IF(AE11>D23,"",AD83*Loans!C7/12)) | AF23: =IF(OR(C23<>"Closed",D23="",F23=""),"",IF(AF11>D23,"",AE83*Loans!C7/12)) | AG23: =IF(OR(C23<>"Closed",D23="",F23=""),"",IF(AG11>D23,"",AF83*Loans!C7/12)) | AH23: =IF(OR(C23<>"Closed",D23="",F23=""),"",IF(AH11>D23,"",AG83*Loans!C7/12)) | AI23: =IF(OR(C23<>"Closed",D23="",F23=""),"",IF(AI11>D23,"",AH83*Loans!C7/12)) | AJ23: =IF(OR(C23<>"Closed",D23="",F23=""),"",IF(AJ11>D23,"",AI83*Loans!C7/12)) | AK23: =IF(OR(C23<>"Closed",D23="",F23=""),"",IF(AK11>D23,"",AJ83*Loans!C7/12)) | AL23: =IF(OR(C23<>"Closed",D23="",F23=""),"",IF(AL11>D23,"",AK83*Loans!C7/12)) | AM23: =IF(OR(C23<>"Closed",D23="",F23=""),"",IF(AM11>D23,"",AL83*Loans!C7/12)) | AN23: =IF(OR(C23<>"Closed",D23="",F23=""),"",IF(AN11>D23,"",AM83*Loans!C7/12)) | AO23: =IF(OR(C23<>"Closed",D23="",F23=""),"",IF(AO11>D23,"",AN83*Loans!C7/12)) | AP23: =IF(OR(C23<>"Closed",D23="",F23=""),"",IF(AP11>D23,"",AO83*Loans!C7/12)) | AQ23: =IF(OR(C23<>"Closed",D23="",F23=""),"",IF(AQ11>D23,"",AP83*Loans!C7/12)) | AR23: =IF(OR(C23<>"Closed",D23="",F23=""),"",IF(AR11>D23,"",AQ83*Loans!C7/12)) | AS23: =IF(OR(C23<>"Closed",D23="",F23=""),"",IF(AS11>D23,"",AR83*Loans!C7/12)) | AT23: =IF(OR(C23<>"Closed",D23="",F23=""),"",IF(AT11>D23,"",AS83*Loans!C7/12)) | AU23: =IF(OR(C23<>"Closed",D23="",F23=""),"",IF(AU11>D23,"",AT83*Loans!C7/12)) | AV23: =IF(OR(C23<>"Closed",D23="",F23=""),"",IF(AV11>D23,"",AU83*Loans!C7/12)) | AW23: =IF(OR(C23<>"Closed",D23="",F23=""),"",IF(AW11>D23,"",AV83*Loans!C7/12)) | AX23: =IF(OR(C23<>"Closed",D23="",F23=""),"",IF(AX11>D23,"",AW83*Loans!C7/12)) | AY23: =IF(OR(C23<>"Closed",D23="",F23=""),"",IF(AY11>D23,"",AX83*Loans!C7/12)) | AZ23: =IF(OR(C23<>"Closed",D23="",F23=""),"",IF(AZ11>D23,"",AY83*Loans!C7/12)) | BA23: =IF(OR(C23<>"Closed",D23="",F23=""),"",IF(BA11>D23,"",AZ83*Loans!C7/12)) | BB23: =IF(OR(C23<>"Closed",D23="",F23=""),"",IF(BB11>D23,"",BA83*Loans!C7/12)) | BC23: =IF(OR(C23<>"Closed",D23="",F23=""),"",IF(BC11>D23,"",BB83*Loans!C7/12)) | BD23: =IF(OR(C23<>"Closed",D23="",F23=""),"",IF(BD11>D23,"",BC83*Loans!C7/12)) | BE23: =IF(OR(C23<>"Closed",D23="",F23=""),"",IF(BE11>D23,"",BD83*Loans!C7/12)) | BF23: =IF(OR(C23<>"Closed",D23="",F23=""),"",IF(BF11>D23,"",BE83*Loans!C7/12)) | BG23: =IF(OR(C23<>"Closed",D23="",F23=""),"",IF(BG11>D23,"",BF83*Loans!C7/12)) | BH23: =IF(OR(C23<>"Closed",D23="",F23=""),"",IF(BH11>D23,"",BG83*Loans!C7/12)) | BI23: =IF(OR(C23<>"Closed",D23="",F23=""),"",IF(BI11>D23,"",BH83*Loans!C7/12)) | BJ23: =IF(OR(C23<>"Closed",D23="",F23=""),"",IF(BJ11>D23,"",BI83*Loans!C7/12)) | BK23: =IF(OR(C23<>"Closed",D23="",F23=""),"",IF(BK11>D23,"",BJ83*Loans!C7/12)) | BL23: =IF(OR(C23<>"Closed",D23="",F23=""),"",IF(BL11>D23,"",BK83*Loans!C7/12)) | BM23: =IF(OR(C23<>"Closed",D23="",F23=""),"",IF(BM11>D23,"",BL83*Loans!C7/12)) | BN23: =IF(OR(C23<>"Closed",D23="",F23=""),"",IF(BN11>D23,"",BM83*Loans!C7/12)) | BO23: =IF(OR(C23<>"Closed",D23="",F23=""),"",IF(BO11>D23,"",BN83*Loans!C7/12)) | BP23: =IF(OR(C23<>"Closed",D23="",F23=""),"",IF(BP11>D23,"",BO83*Loans!C7/12))
A24: =IF(Loans!A24="","",Loans!A24) | B24: =IF(Loans!B24="","",Loans!B24) | C24: =IF(Loans!C24="","",Loans!C24) | D24: =IF(Loans!I24="","",Loans!I24) | E24: =IF(Loans!E24="","",Loans!E24) | F24: =IF(Loans!F24="","",Loans!F24) | G24: =IF(OR(C24<>"Closed",D24="",F24=""),"",PMT(Loans!C7/12,D24,-F24)) | H24: =IF(C24<>"Closed","",SUM(I24:BP24)) | I24: =IF(OR(C24<>"Closed",D24="",F24=""),"",IF(I11>D24,"",F24*Loans!C7/12)) | J24: =IF(OR(C24<>"Closed",D24="",F24=""),"",IF(J11>D24,"",I84*Loans!C7/12)) | K24: =IF(OR(C24<>"Closed",D24="",F24=""),"",IF(K11>D24,"",J84*Loans!C7/12)) | L24: =IF(OR(C24<>"Closed",D24="",F24=""),"",IF(L11>D24,"",K84*Loans!C7/12)) | M24: =IF(OR(C24<>"Closed",D24="",F24=""),"",IF(M11>D24,"",L84*Loans!C7/12)) | N24: =IF(OR(C24<>"Closed",D24="",F24=""),"",IF(N11>D24,"",M84*Loans!C7/12)) | O24: =IF(OR(C24<>"Closed",D24="",F24=""),"",IF(O11>D24,"",N84*Loans!C7/12)) | P24: =IF(OR(C24<>"Closed",D24="",F24=""),"",IF(P11>D24,"",O84*Loans!C7/12)) | Q24: =IF(OR(C24<>"Closed",D24="",F24=""),"",IF(Q11>D24,"",P84*Loans!C7/12)) | R24: =IF(OR(C24<>"Closed",D24="",F24=""),"",IF(R11>D24,"",Q84*Loans!C7/12)) | S24: =IF(OR(C24<>"Closed",D24="",F24=""),"",IF(S11>D24,"",R84*Loans!C7/12)) | T24: =IF(OR(C24<>"Closed",D24="",F24=""),"",IF(T11>D24,"",S84*Loans!C7/12)) | U24: =IF(OR(C24<>"Closed",D24="",F24=""),"",IF(U11>D24,"",T84*Loans!C7/12)) | V24: =IF(OR(C24<>"Closed",D24="",F24=""),"",IF(V11>D24,"",U84*Loans!C7/12)) | W24: =IF(OR(C24<>"Closed",D24="",F24=""),"",IF(W11>D24,"",V84*Loans!C7/12)) | X24: =IF(OR(C24<>"Closed",D24="",F24=""),"",IF(X11>D24,"",W84*Loans!C7/12)) | Y24: =IF(OR(C24<>"Closed",D24="",F24=""),"",IF(Y11>D24,"",X84*Loans!C7/12)) | Z24: =IF(OR(C24<>"Closed",D24="",F24=""),"",IF(Z11>D24,"",Y84*Loans!C7/12)) | AA24: =IF(OR(C24<>"Closed",D24="",F24=""),"",IF(AA11>D24,"",Z84*Loans!C7/12)) | AB24: =IF(OR(C24<>"Closed",D24="",F24=""),"",IF(AB11>D24,"",AA84*Loans!C7/12)) | AC24: =IF(OR(C24<>"Closed",D24="",F24=""),"",IF(AC11>D24,"",AB84*Loans!C7/12)) | AD24: =IF(OR(C24<>"Closed",D24="",F24=""),"",IF(AD11>D24,"",AC84*Loans!C7/12)) | AE24: =IF(OR(C24<>"Closed",D24="",F24=""),"",IF(AE11>D24,"",AD84*Loans!C7/12)) | AF24: =IF(OR(C24<>"Closed",D24="",F24=""),"",IF(AF11>D24,"",AE84*Loans!C7/12)) | AG24: =IF(OR(C24<>"Closed",D24="",F24=""),"",IF(AG11>D24,"",AF84*Loans!C7/12)) | AH24: =IF(OR(C24<>"Closed",D24="",F24=""),"",IF(AH11>D24,"",AG84*Loans!C7/12)) | AI24: =IF(OR(C24<>"Closed",D24="",F24=""),"",IF(AI11>D24,"",AH84*Loans!C7/12)) | AJ24: =IF(OR(C24<>"Closed",D24="",F24=""),"",IF(AJ11>D24,"",AI84*Loans!C7/12)) | AK24: =IF(OR(C24<>"Closed",D24="",F24=""),"",IF(AK11>D24,"",AJ84*Loans!C7/12)) | AL24: =IF(OR(C24<>"Closed",D24="",F24=""),"",IF(AL11>D24,"",AK84*Loans!C7/12)) | AM24: =IF(OR(C24<>"Closed",D24="",F24=""),"",IF(AM11>D24,"",AL84*Loans!C7/12)) | AN24: =IF(OR(C24<>"Closed",D24="",F24=""),"",IF(AN11>D24,"",AM84*Loans!C7/12)) | AO24: =IF(OR(C24<>"Closed",D24="",F24=""),"",IF(AO11>D24,"",AN84*Loans!C7/12)) | AP24: =IF(OR(C24<>"Closed",D24="",F24=""),"",IF(AP11>D24,"",AO84*Loans!C7/12)) | AQ24: =IF(OR(C24<>"Closed",D24="",F24=""),"",IF(AQ11>D24,"",AP84*Loans!C7/12)) | AR24: =IF(OR(C24<>"Closed",D24="",F24=""),"",IF(AR11>D24,"",AQ84*Loans!C7/12)) | AS24: =IF(OR(C24<>"Closed",D24="",F24=""),"",IF(AS11>D24,"",AR84*Loans!C7/12)) | AT24: =IF(OR(C24<>"Closed",D24="",F24=""),"",IF(AT11>D24,"",AS84*Loans!C7/12)) | AU24: =IF(OR(C24<>"Closed",D24="",F24=""),"",IF(AU11>D24,"",AT84*Loans!C7/12)) | AV24: =IF(OR(C24<>"Closed",D24="",F24=""),"",IF(AV11>D24,"",AU84*Loans!C7/12)) | AW24: =IF(OR(C24<>"Closed",D24="",F24=""),"",IF(AW11>D24,"",AV84*Loans!C7/12)) | AX24: =IF(OR(C24<>"Closed",D24="",F24=""),"",IF(AX11>D24,"",AW84*Loans!C7/12)) | AY24: =IF(OR(C24<>"Closed",D24="",F24=""),"",IF(AY11>D24,"",AX84*Loans!C7/12)) | AZ24: =IF(OR(C24<>"Closed",D24="",F24=""),"",IF(AZ11>D24,"",AY84*Loans!C7/12)) | BA24: =IF(OR(C24<>"Closed",D24="",F24=""),"",IF(BA11>D24,"",AZ84*Loans!C7/12)) | BB24: =IF(OR(C24<>"Closed",D24="",F24=""),"",IF(BB11>D24,"",BA84*Loans!C7/12)) | BC24: =IF(OR(C24<>"Closed",D24="",F24=""),"",IF(BC11>D24,"",BB84*Loans!C7/12)) | BD24: =IF(OR(C24<>"Closed",D24="",F24=""),"",IF(BD11>D24,"",BC84*Loans!C7/12)) | BE24: =IF(OR(C24<>"Closed",D24="",F24=""),"",IF(BE11>D24,"",BD84*Loans!C7/12)) | BF24: =IF(OR(C24<>"Closed",D24="",F24=""),"",IF(BF11>D24,"",BE84*Loans!C7/12)) | BG24: =IF(OR(C24<>"Closed",D24="",F24=""),"",IF(BG11>D24,"",BF84*Loans!C7/12)) | BH24: =IF(OR(C24<>"Closed",D24="",F24=""),"",IF(BH11>D24,"",BG84*Loans!C7/12)) | BI24: =IF(OR(C24<>"Closed",D24="",F24=""),"",IF(BI11>D24,"",BH84*Loans!C7/12)) | BJ24: =IF(OR(C24<>"Closed",D24="",F24=""),"",IF(BJ11>D24,"",BI84*Loans!C7/12)) | BK24: =IF(OR(C24<>"Closed",D24="",F24=""),"",IF(BK11>D24,"",BJ84*Loans!C7/12)) | BL24: =IF(OR(C24<>"Closed",D24="",F24=""),"",IF(BL11>D24,"",BK84*Loans!C7/12)) | BM24: =IF(OR(C24<>"Closed",D24="",F24=""),"",IF(BM11>D24,"",BL84*Loans!C7/12)) | BN24: =IF(OR(C24<>"Closed",D24="",F24=""),"",IF(BN11>D24,"",BM84*Loans!C7/12)) | BO24: =IF(OR(C24<>"Closed",D24="",F24=""),"",IF(BO11>D24,"",BN84*Loans!C7/12)) | BP24: =IF(OR(C24<>"Closed",D24="",F24=""),"",IF(BP11>D24,"",BO84*Loans!C7/12))
A25: =IF(Loans!A25="","",Loans!A25) | B25: =IF(Loans!B25="","",Loans!B25) | C25: =IF(Loans!C25="","",Loans!C25) | D25: =IF(Loans!I25="","",Loans!I25) | E25: =IF(Loans!E25="","",Loans!E25) | F25: =IF(Loans!F25="","",Loans!F25) | G25: =IF(OR(C25<>"Closed",D25="",F25=""),"",PMT(Loans!C7/12,D25,-F25)) | H25: =IF(C25<>"Closed","",SUM(I25:BP25)) | I25: =IF(OR(C25<>"Closed",D25="",F25=""),"",IF(I11>D25,"",F25*Loans!C7/12)) | J25: =IF(OR(C25<>"Closed",D25="",F25=""),"",IF(J11>D25,"",I85*Loans!C7/12)) | K25: =IF(OR(C25<>"Closed",D25="",F25=""),"",IF(K11>D25,"",J85*Loans!C7/12)) | L25: =IF(OR(C25<>"Closed",D25="",F25=""),"",IF(L11>D25,"",K85*Loans!C7/12)) | M25: =IF(OR(C25<>"Closed",D25="",F25=""),"",IF(M11>D25,"",L85*Loans!C7/12)) | N25: =IF(OR(C25<>"Closed",D25="",F25=""),"",IF(N11>D25,"",M85*Loans!C7/12)) | O25: =IF(OR(C25<>"Closed",D25="",F25=""),"",IF(O11>D25,"",N85*Loans!C7/12)) | P25: =IF(OR(C25<>"Closed",D25="",F25=""),"",IF(P11>D25,"",O85*Loans!C7/12)) | Q25: =IF(OR(C25<>"Closed",D25="",F25=""),"",IF(Q11>D25,"",P85*Loans!C7/12)) | R25: =IF(OR(C25<>"Closed",D25="",F25=""),"",IF(R11>D25,"",Q85*Loans!C7/12)) | S25: =IF(OR(C25<>"Closed",D25="",F25=""),"",IF(S11>D25,"",R85*Loans!C7/12)) | T25: =IF(OR(C25<>"Closed",D25="",F25=""),"",IF(T11>D25,"",S85*Loans!C7/12)) | U25: =IF(OR(C25<>"Closed",D25="",F25=""),"",IF(U11>D25,"",T85*Loans!C7/12)) | V25: =IF(OR(C25<>"Closed",D25="",F25=""),"",IF(V11>D25,"",U85*Loans!C7/12)) | W25: =IF(OR(C25<>"Closed",D25="",F25=""),"",IF(W11>D25,"",V85*Loans!C7/12)) | X25: =IF(OR(C25<>"Closed",D25="",F25=""),"",IF(X11>D25,"",W85*Loans!C7/12)) | Y25: =IF(OR(C25<>"Closed",D25="",F25=""),"",IF(Y11>D25,"",X85*Loans!C7/12)) | Z25: =IF(OR(C25<>"Closed",D25="",F25=""),"",IF(Z11>D25,"",Y85*Loans!C7/12)) | AA25: =IF(OR(C25<>"Closed",D25="",F25=""),"",IF(AA11>D25,"",Z85*Loans!C7/12)) | AB25: =IF(OR(C25<>"Closed",D25="",F25=""),"",IF(AB11>D25,"",AA85*Loans!C7/12)) | AC25: =IF(OR(C25<>"Closed",D25="",F25=""),"",IF(AC11>D25,"",AB85*Loans!C7/12)) | AD25: =IF(OR(C25<>"Closed",D25="",F25=""),"",IF(AD11>D25,"",AC85*Loans!C7/12)) | AE25: =IF(OR(C25<>"Closed",D25="",F25=""),"",IF(AE11>D25,"",AD85*Loans!C7/12)) | AF25: =IF(OR(C25<>"Closed",D25="",F25=""),"",IF(AF11>D25,"",AE85*Loans!C7/12)) | AG25: =IF(OR(C25<>"Closed",D25="",F25=""),"",IF(AG11>D25,"",AF85*Loans!C7/12)) | AH25: =IF(OR(C25<>"Closed",D25="",F25=""),"",IF(AH11>D25,"",AG85*Loans!C7/12)) | AI25: =IF(OR(C25<>"Closed",D25="",F25=""),"",IF(AI11>D25,"",AH85*Loans!C7/12)) | AJ25: =IF(OR(C25<>"Closed",D25="",F25=""),"",IF(AJ11>D25,"",AI85*Loans!C7/12)) | AK25: =IF(OR(C25<>"Closed",D25="",F25=""),"",IF(AK11>D25,"",AJ85*Loans!C7/12)) | AL25: =IF(OR(C25<>"Closed",D25="",F25=""),"",IF(AL11>D25,"",AK85*Loans!C7/12)) | AM25: =IF(OR(C25<>"Closed",D25="",F25=""),"",IF(AM11>D25,"",AL85*Loans!C7/12)) | AN25: =IF(OR(C25<>"Closed",D25="",F25=""),"",IF(AN11>D25,"",AM85*Loans!C7/12)) | AO25: =IF(OR(C25<>"Closed",D25="",F25=""),"",IF(AO11>D25,"",AN85*Loans!C7/12)) | AP25: =IF(OR(C25<>"Closed",D25="",F25=""),"",IF(AP11>D25,"",AO85*Loans!C7/12)) | AQ25: =IF(OR(C25<>"Closed",D25="",F25=""),"",IF(AQ11>D25,"",AP85*Loans!C7/12)) | AR25: =IF(OR(C25<>"Closed",D25="",F25=""),"",IF(AR11>D25,"",AQ85*Loans!C7/12)) | AS25: =IF(OR(C25<>"Closed",D25="",F25=""),"",IF(AS11>D25,"",AR85*Loans!C7/12)) | AT25: =IF(OR(C25<>"Closed",D25="",F25=""),"",IF(AT11>D25,"",AS85*Loans!C7/12)) | AU25: =IF(OR(C25<>"Closed",D25="",F25=""),"",IF(AU11>D25,"",AT85*Loans!C7/12)) | AV25: =IF(OR(C25<>"Closed",D25="",F25=""),"",IF(AV11>D25,"",AU85*Loans!C7/12)) | AW25: =IF(OR(C25<>"Closed",D25="",F25=""),"",IF(AW11>D25,"",AV85*Loans!C7/12)) | AX25: =IF(OR(C25<>"Closed",D25="",F25=""),"",IF(AX11>D25,"",AW85*Loans!C7/12)) | AY25: =IF(OR(C25<>"Closed",D25="",F25=""),"",IF(AY11>D25,"",AX85*Loans!C7/12)) | AZ25: =IF(OR(C25<>"Closed",D25="",F25=""),"",IF(AZ11>D25,"",AY85*Loans!C7/12)) | BA25: =IF(OR(C25<>"Closed",D25="",F25=""),"",IF(BA11>D25,"",AZ85*Loans!C7/12)) | BB25: =IF(OR(C25<>"Closed",D25="",F25=""),"",IF(BB11>D25,"",BA85*Loans!C7/12)) | BC25: =IF(OR(C25<>"Closed",D25="",F25=""),"",IF(BC11>D25,"",BB85*Loans!C7/12)) | BD25: =IF(OR(C25<>"Closed",D25="",F25=""),"",IF(BD11>D25,"",BC85*Loans!C7/12)) | BE25: =IF(OR(C25<>"Closed",D25="",F25=""),"",IF(BE11>D25,"",BD85*Loans!C7/12)) | BF25: =IF(OR(C25<>"Closed",D25="",F25=""),"",IF(BF11>D25,"",BE85*Loans!C7/12)) | BG25: =IF(OR(C25<>"Closed",D25="",F25=""),"",IF(BG11>D25,"",BF85*Loans!C7/12)) | BH25: =IF(OR(C25<>"Closed",D25="",F25=""),"",IF(BH11>D25,"",BG85*Loans!C7/12)) | BI25: =IF(OR(C25<>"Closed",D25="",F25=""),"",IF(BI11>D25,"",BH85*Loans!C7/12)) | BJ25: =IF(OR(C25<>"Closed",D25="",F25=""),"",IF(BJ11>D25,"",BI85*Loans!C7/12)) | BK25: =IF(OR(C25<>"Closed",D25="",F25=""),"",IF(BK11>D25,"",BJ85*Loans!C7/12)) | BL25: =IF(OR(C25<>"Closed",D25="",F25=""),"",IF(BL11>D25,"",BK85*Loans!C7/12)) | BM25: =IF(OR(C25<>"Closed",D25="",F25=""),"",IF(BM11>D25,"",BL85*Loans!C7/12)) | BN25: =IF(OR(C25<>"Closed",D25="",F25=""),"",IF(BN11>D25,"",BM85*Loans!C7/12)) | BO25: =IF(OR(C25<>"Closed",D25="",F25=""),"",IF(BO11>D25,"",BN85*Loans!C7/12)) | BP25: =IF(OR(C25<>"Closed",D25="",F25=""),"",IF(BP11>D25,"",BO85*Loans!C7/12))
A26: =IF(Loans!A26="","",Loans!A26) | B26: =IF(Loans!B26="","",Loans!B26) | C26: =IF(Loans!C26="","",Loans!C26) | D26: =IF(Loans!I26="","",Loans!I26) | E26: =IF(Loans!E26="","",Loans!E26) | F26: =IF(Loans!F26="","",Loans!F26) | G26: =IF(OR(C26<>"Closed",D26="",F26=""),"",PMT(Loans!C7/12,D26,-F26)) | H26: =IF(C26<>"Closed","",SUM(I26:BP26)) | I26: =IF(OR(C26<>"Closed",D26="",F26=""),"",IF(I11>D26,"",F26*Loans!C7/12)) | J26: =IF(OR(C26<>"Closed",D26="",F26=""),"",IF(J11>D26,"",I86*Loans!C7/12)) | K26: =IF(OR(C26<>"Closed",D26="",F26=""),"",IF(K11>D26,"",J86*Loans!C7/12)) | L26: =IF(OR(C26<>"Closed",D26="",F26=""),"",IF(L11>D26,"",K86*Loans!C7/12)) | M26: =IF(OR(C26<>"Closed",D26="",F26=""),"",IF(M11>D26,"",L86*Loans!C7/12)) | N26: =IF(OR(C26<>"Closed",D26="",F26=""),"",IF(N11>D26,"",M86*Loans!C7/12)) | O26: =IF(OR(C26<>"Closed",D26="",F26=""),"",IF(O11>D26,"",N86*Loans!C7/12)) | P26: =IF(OR(C26<>"Closed",D26="",F26=""),"",IF(P11>D26,"",O86*Loans!C7/12)) | Q26: =IF(OR(C26<>"Closed",D26="",F26=""),"",IF(Q11>D26,"",P86*Loans!C7/12)) | R26: =IF(OR(C26<>"Closed",D26="",F26=""),"",IF(R11>D26,"",Q86*Loans!C7/12)) | S26: =IF(OR(C26<>"Closed",D26="",F26=""),"",IF(S11>D26,"",R86*Loans!C7/12)) | T26: =IF(OR(C26<>"Closed",D26="",F26=""),"",IF(T11>D26,"",S86*Loans!C7/12)) | U26: =IF(OR(C26<>"Closed",D26="",F26=""),"",IF(U11>D26,"",T86*Loans!C7/12)) | V26: =IF(OR(C26<>"Closed",D26="",F26=""),"",IF(V11>D26,"",U86*Loans!C7/12)) | W26: =IF(OR(C26<>"Closed",D26="",F26=""),"",IF(W11>D26,"",V86*Loans!C7/12)) | X26: =IF(OR(C26<>"Closed",D26="",F26=""),"",IF(X11>D26,"",W86*Loans!C7/12)) | Y26: =IF(OR(C26<>"Closed",D26="",F26=""),"",IF(Y11>D26,"",X86*Loans!C7/12)) | Z26: =IF(OR(C26<>"Closed",D26="",F26=""),"",IF(Z11>D26,"",Y86*Loans!C7/12)) | AA26: =IF(OR(C26<>"Closed",D26="",F26=""),"",IF(AA11>D26,"",Z86*Loans!C7/12)) | AB26: =IF(OR(C26<>"Closed",D26="",F26=""),"",IF(AB11>D26,"",AA86*Loans!C7/12)) | AC26: =IF(OR(C26<>"Closed",D26="",F26=""),"",IF(AC11>D26,"",AB86*Loans!C7/12)) | AD26: =IF(OR(C26<>"Closed",D26="",F26=""),"",IF(AD11>D26,"",AC86*Loans!C7/12)) | AE26: =IF(OR(C26<>"Closed",D26="",F26=""),"",IF(AE11>D26,"",AD86*Loans!C7/12)) | AF26: =IF(OR(C26<>"Closed",D26="",F26=""),"",IF(AF11>D26,"",AE86*Loans!C7/12)) | AG26: =IF(OR(C26<>"Closed",D26="",F26=""),"",IF(AG11>D26,"",AF86*Loans!C7/12)) | AH26: =IF(OR(C26<>"Closed",D26="",F26=""),"",IF(AH11>D26,"",AG86*Loans!C7/12)) | AI26: =IF(OR(C26<>"Closed",D26="",F26=""),"",IF(AI11>D26,"",AH86*Loans!C7/12)) | AJ26: =IF(OR(C26<>"Closed",D26="",F26=""),"",IF(AJ11>D26,"",AI86*Loans!C7/12)) | AK26: =IF(OR(C26<>"Closed",D26="",F26=""),"",IF(AK11>D26,"",AJ86*Loans!C7/12)) | AL26: =IF(OR(C26<>"Closed",D26="",F26=""),"",IF(AL11>D26,"",AK86*Loans!C7/12)) | AM26: =IF(OR(C26<>"Closed",D26="",F26=""),"",IF(AM11>D26,"",AL86*Loans!C7/12)) | AN26: =IF(OR(C26<>"Closed",D26="",F26=""),"",IF(AN11>D26,"",AM86*Loans!C7/12)) | AO26: =IF(OR(C26<>"Closed",D26="",F26=""),"",IF(AO11>D26,"",AN86*Loans!C7/12)) | AP26: =IF(OR(C26<>"Closed",D26="",F26=""),"",IF(AP11>D26,"",AO86*Loans!C7/12)) | AQ26: =IF(OR(C26<>"Closed",D26="",F26=""),"",IF(AQ11>D26,"",AP86*Loans!C7/12)) | AR26: =IF(OR(C26<>"Closed",D26="",F26=""),"",IF(AR11>D26,"",AQ86*Loans!C7/12)) | AS26: =IF(OR(C26<>"Closed",D26="",F26=""),"",IF(AS11>D26,"",AR86*Loans!C7/12)) | AT26: =IF(OR(C26<>"Closed",D26="",F26=""),"",IF(AT11>D26,"",AS86*Loans!C7/12)) | AU26: =IF(OR(C26<>"Closed",D26="",F26=""),"",IF(AU11>D26,"",AT86*Loans!C7/12)) | AV26: =IF(OR(C26<>"Closed",D26="",F26=""),"",IF(AV11>D26,"",AU86*Loans!C7/12)) | AW26: =IF(OR(C26<>"Closed",D26="",F26=""),"",IF(AW11>D26,"",AV86*Loans!C7/12)) | AX26: =IF(OR(C26<>"Closed",D26="",F26=""),"",IF(AX11>D26,"",AW86*Loans!C7/12)) | AY26: =IF(OR(C26<>"Closed",D26="",F26=""),"",IF(AY11>D26,"",AX86*Loans!C7/12)) | AZ26: =IF(OR(C26<>"Closed",D26="",F26=""),"",IF(AZ11>D26,"",AY86*Loans!C7/12)) | BA26: =IF(OR(C26<>"Closed",D26="",F26=""),"",IF(BA11>D26,"",AZ86*Loans!C7/12)) | BB26: =IF(OR(C26<>"Closed",D26="",F26=""),"",IF(BB11>D26,"",BA86*Loans!C7/12)) | BC26: =IF(OR(C26<>"Closed",D26="",F26=""),"",IF(BC11>D26,"",BB86*Loans!C7/12)) | BD26: =IF(OR(C26<>"Closed",D26="",F26=""),"",IF(BD11>D26,"",BC86*Loans!C7/12)) | BE26: =IF(OR(C26<>"Closed",D26="",F26=""),"",IF(BE11>D26,"",BD86*Loans!C7/12)) | BF26: =IF(OR(C26<>"Closed",D26="",F26=""),"",IF(BF11>D26,"",BE86*Loans!C7/12)) | BG26: =IF(OR(C26<>"Closed",D26="",F26=""),"",IF(BG11>D26,"",BF86*Loans!C7/12)) | BH26: =IF(OR(C26<>"Closed",D26="",F26=""),"",IF(BH11>D26,"",BG86*Loans!C7/12)) | BI26: =IF(OR(C26<>"Closed",D26="",F26=""),"",IF(BI11>D26,"",BH86*Loans!C7/12)) | BJ26: =IF(OR(C26<>"Closed",D26="",F26=""),"",IF(BJ11>D26,"",BI86*Loans!C7/12)) | BK26: =IF(OR(C26<>"Closed",D26="",F26=""),"",IF(BK11>D26,"",BJ86*Loans!C7/12)) | BL26: =IF(OR(C26<>"Closed",D26="",F26=""),"",IF(BL11>D26,"",BK86*Loans!C7/12)) | BM26: =IF(OR(C26<>"Closed",D26="",F26=""),"",IF(BM11>D26,"",BL86*Loans!C7/12)) | BN26: =IF(OR(C26<>"Closed",D26="",F26=""),"",IF(BN11>D26,"",BM86*Loans!C7/12)) | BO26: =IF(OR(C26<>"Closed",D26="",F26=""),"",IF(BO11>D26,"",BN86*Loans!C7/12)) | BP26: =IF(OR(C26<>"Closed",D26="",F26=""),"",IF(BP11>D26,"",BO86*Loans!C7/12))
A27: =IF(Loans!A27="","",Loans!A27) | B27: =IF(Loans!B27="","",Loans!B27) | C27: =IF(Loans!C27="","",Loans!C27) | D27: =IF(Loans!I27="","",Loans!I27) | E27: =IF(Loans!E27="","",Loans!E27) | F27: =IF(Loans!F27="","",Loans!F27) | G27: =IF(OR(C27<>"Closed",D27="",F27=""),"",PMT(Loans!C7/12,D27,-F27)) | H27: =IF(C27<>"Closed","",SUM(I27:BP27)) | I27: =IF(OR(C27<>"Closed",D27="",F27=""),"",IF(I11>D27,"",F27*Loans!C7/12)) | J27: =IF(OR(C27<>"Closed",D27="",F27=""),"",IF(J11>D27,"",I87*Loans!C7/12)) | K27: =IF(OR(C27<>"Closed",D27="",F27=""),"",IF(K11>D27,"",J87*Loans!C7/12)) | L27: =IF(OR(C27<>"Closed",D27="",F27=""),"",IF(L11>D27,"",K87*Loans!C7/12)) | M27: =IF(OR(C27<>"Closed",D27="",F27=""),"",IF(M11>D27,"",L87*Loans!C7/12)) | N27: =IF(OR(C27<>"Closed",D27="",F27=""),"",IF(N11>D27,"",M87*Loans!C7/12)) | O27: =IF(OR(C27<>"Closed",D27="",F27=""),"",IF(O11>D27,"",N87*Loans!C7/12)) | P27: =IF(OR(C27<>"Closed",D27="",F27=""),"",IF(P11>D27,"",O87*Loans!C7/12)) | Q27: =IF(OR(C27<>"Closed",D27="",F27=""),"",IF(Q11>D27,"",P87*Loans!C7/12)) | R27: =IF(OR(C27<>"Closed",D27="",F27=""),"",IF(R11>D27,"",Q87*Loans!C7/12)) | S27: =IF(OR(C27<>"Closed",D27="",F27=""),"",IF(S11>D27,"",R87*Loans!C7/12)) | T27: =IF(OR(C27<>"Closed",D27="",F27=""),"",IF(T11>D27,"",S87*Loans!C7/12)) | U27: =IF(OR(C27<>"Closed",D27="",F27=""),"",IF(U11>D27,"",T87*Loans!C7/12)) | V27: =IF(OR(C27<>"Closed",D27="",F27=""),"",IF(V11>D27,"",U87*Loans!C7/12)) | W27: =IF(OR(C27<>"Closed",D27="",F27=""),"",IF(W11>D27,"",V87*Loans!C7/12)) | X27: =IF(OR(C27<>"Closed",D27="",F27=""),"",IF(X11>D27,"",W87*Loans!C7/12)) | Y27: =IF(OR(C27<>"Closed",D27="",F27=""),"",IF(Y11>D27,"",X87*Loans!C7/12)) | Z27: =IF(OR(C27<>"Closed",D27="",F27=""),"",IF(Z11>D27,"",Y87*Loans!C7/12)) | AA27: =IF(OR(C27<>"Closed",D27="",F27=""),"",IF(AA11>D27,"",Z87*Loans!C7/12)) | AB27: =IF(OR(C27<>"Closed",D27="",F27=""),"",IF(AB11>D27,"",AA87*Loans!C7/12)) | AC27: =IF(OR(C27<>"Closed",D27="",F27=""),"",IF(AC11>D27,"",AB87*Loans!C7/12)) | AD27: =IF(OR(C27<>"Closed",D27="",F27=""),"",IF(AD11>D27,"",AC87*Loans!C7/12)) | AE27: =IF(OR(C27<>"Closed",D27="",F27=""),"",IF(AE11>D27,"",AD87*Loans!C7/12)) | AF27: =IF(OR(C27<>"Closed",D27="",F27=""),"",IF(AF11>D27,"",AE87*Loans!C7/12)) | AG27: =IF(OR(C27<>"Closed",D27="",F27=""),"",IF(AG11>D27,"",AF87*Loans!C7/12)) | AH27: =IF(OR(C27<>"Closed",D27="",F27=""),"",IF(AH11>D27,"",AG87*Loans!C7/12)) | AI27: =IF(OR(C27<>"Closed",D27="",F27=""),"",IF(AI11>D27,"",AH87*Loans!C7/12)) | AJ27: =IF(OR(C27<>"Closed",D27="",F27=""),"",IF(AJ11>D27,"",AI87*Loans!C7/12)) | AK27: =IF(OR(C27<>"Closed",D27="",F27=""),"",IF(AK11>D27,"",AJ87*Loans!C7/12)) | AL27: =IF(OR(C27<>"Closed",D27="",F27=""),"",IF(AL11>D27,"",AK87*Loans!C7/12)) | AM27: =IF(OR(C27<>"Closed",D27="",F27=""),"",IF(AM11>D27,"",AL87*Loans!C7/12)) | AN27: =IF(OR(C27<>"Closed",D27="",F27=""),"",IF(AN11>D27,"",AM87*Loans!C7/12)) | AO27: =IF(OR(C27<>"Closed",D27="",F27=""),"",IF(AO11>D27,"",AN87*Loans!C7/12)) | AP27: =IF(OR(C27<>"Closed",D27="",F27=""),"",IF(AP11>D27,"",AO87*Loans!C7/12)) | AQ27: =IF(OR(C27<>"Closed",D27="",F27=""),"",IF(AQ11>D27,"",AP87*Loans!C7/12)) | AR27: =IF(OR(C27<>"Closed",D27="",F27=""),"",IF(AR11>D27,"",AQ87*Loans!C7/12)) | AS27: =IF(OR(C27<>"Closed",D27="",F27=""),"",IF(AS11>D27,"",AR87*Loans!C7/12)) | AT27: =IF(OR(C27<>"Closed",D27="",F27=""),"",IF(AT11>D27,"",AS87*Loans!C7/12)) | AU27: =IF(OR(C27<>"Closed",D27="",F27=""),"",IF(AU11>D27,"",AT87*Loans!C7/12)) | AV27: =IF(OR(C27<>"Closed",D27="",F27=""),"",IF(AV11>D27,"",AU87*Loans!C7/12)) | AW27: =IF(OR(C27<>"Closed",D27="",F27=""),"",IF(AW11>D27,"",AV87*Loans!C7/12)) | AX27: =IF(OR(C27<>"Closed",D27="",F27=""),"",IF(AX11>D27,"",AW87*Loans!C7/12)) | AY27: =IF(OR(C27<>"Closed",D27="",F27=""),"",IF(AY11>D27,"",AX87*Loans!C7/12)) | AZ27: =IF(OR(C27<>"Closed",D27="",F27=""),"",IF(AZ11>D27,"",AY87*Loans!C7/12)) | BA27: =IF(OR(C27<>"Closed",D27="",F27=""),"",IF(BA11>D27,"",AZ87*Loans!C7/12)) | BB27: =IF(OR(C27<>"Closed",D27="",F27=""),"",IF(BB11>D27,"",BA87*Loans!C7/12)) | BC27: =IF(OR(C27<>"Closed",D27="",F27=""),"",IF(BC11>D27,"",BB87*Loans!C7/12)) | BD27: =IF(OR(C27<>"Closed",D27="",F27=""),"",IF(BD11>D27,"",BC87*Loans!C7/12)) | BE27: =IF(OR(C27<>"Closed",D27="",F27=""),"",IF(BE11>D27,"",BD87*Loans!C7/12)) | BF27: =IF(OR(C27<>"Closed",D27="",F27=""),"",IF(BF11>D27,"",BE87*Loans!C7/12)) | BG27: =IF(OR(C27<>"Closed",D27="",F27=""),"",IF(BG11>D27,"",BF87*Loans!C7/12)) | BH27: =IF(OR(C27<>"Closed",D27="",F27=""),"",IF(BH11>D27,"",BG87*Loans!C7/12)) | BI27: =IF(OR(C27<>"Closed",D27="",F27=""),"",IF(BI11>D27,"",BH87*Loans!C7/12)) | BJ27: =IF(OR(C27<>"Closed",D27="",F27=""),"",IF(BJ11>D27,"",BI87*Loans!C7/12)) | BK27: =IF(OR(C27<>"Closed",D27="",F27=""),"",IF(BK11>D27,"",BJ87*Loans!C7/12)) | BL27: =IF(OR(C27<>"Closed",D27="",F27=""),"",IF(BL11>D27,"",BK87*Loans!C7/12)) | BM27: =IF(OR(C27<>"Closed",D27="",F27=""),"",IF(BM11>D27,"",BL87*Loans!C7/12)) | BN27: =IF(OR(C27<>"Closed",D27="",F27=""),"",IF(BN11>D27,"",BM87*Loans!C7/12)) | BO27: =IF(OR(C27<>"Closed",D27="",F27=""),"",IF(BO11>D27,"",BN87*Loans!C7/12)) | BP27: =IF(OR(C27<>"Closed",D27="",F27=""),"",IF(BP11>D27,"",BO87*Loans!C7/12))
A28: =IF(Loans!A28="","",Loans!A28) | B28: =IF(Loans!B28="","",Loans!B28) | C28: =IF(Loans!C28="","",Loans!C28) | D28: =IF(Loans!I28="","",Loans!I28) | E28: =IF(Loans!E28="","",Loans!E28) | F28: =IF(Loans!F28="","",Loans!F28) | G28: =IF(OR(C28<>"Closed",D28="",F28=""),"",PMT(Loans!C7/12,D28,-F28)) | H28: =IF(C28<>"Closed","",SUM(I28:BP28)) | I28: =IF(OR(C28<>"Closed",D28="",F28=""),"",IF(I11>D28,"",F28*Loans!C7/12)) | J28: =IF(OR(C28<>"Closed",D28="",F28=""),"",IF(J11>D28,"",I88*Loans!C7/12)) | K28: =IF(OR(C28<>"Closed",D28="",F28=""),"",IF(K11>D28,"",J88*Loans!C7/12)) | L28: =IF(OR(C28<>"Closed",D28="",F28=""),"",IF(L11>D28,"",K88*Loans!C7/12)) | M28: =IF(OR(C28<>"Closed",D28="",F28=""),"",IF(M11>D28,"",L88*Loans!C7/12)) | N28: =IF(OR(C28<>"Closed",D28="",F28=""),"",IF(N11>D28,"",M88*Loans!C7/12)) | O28: =IF(OR(C28<>"Closed",D28="",F28=""),"",IF(O11>D28,"",N88*Loans!C7/12)) | P28: =IF(OR(C28<>"Closed",D28="",F28=""),"",IF(P11>D28,"",O88*Loans!C7/12)) | Q28: =IF(OR(C28<>"Closed",D28="",F28=""),"",IF(Q11>D28,"",P88*Loans!C7/12)) | R28: =IF(OR(C28<>"Closed",D28="",F28=""),"",IF(R11>D28,"",Q88*Loans!C7/12)) | S28: =IF(OR(C28<>"Closed",D28="",F28=""),"",IF(S11>D28,"",R88*Loans!C7/12)) | T28: =IF(OR(C28<>"Closed",D28="",F28=""),"",IF(T11>D28,"",S88*Loans!C7/12)) | U28: =IF(OR(C28<>"Closed",D28="",F28=""),"",IF(U11>D28,"",T88*Loans!C7/12)) | V28: =IF(OR(C28<>"Closed",D28="",F28=""),"",IF(V11>D28,"",U88*Loans!C7/12)) | W28: =IF(OR(C28<>"Closed",D28="",F28=""),"",IF(W11>D28,"",V88*Loans!C7/12)) | X28: =IF(OR(C28<>"Closed",D28="",F28=""),"",IF(X11>D28,"",W88*Loans!C7/12)) | Y28: =IF(OR(C28<>"Closed",D28="",F28=""),"",IF(Y11>D28,"",X88*Loans!C7/12)) | Z28: =IF(OR(C28<>"Closed",D28="",F28=""),"",IF(Z11>D28,"",Y88*Loans!C7/12)) | AA28: =IF(OR(C28<>"Closed",D28="",F28=""),"",IF(AA11>D28,"",Z88*Loans!C7/12)) | AB28: =IF(OR(C28<>"Closed",D28="",F28=""),"",IF(AB11>D28,"",AA88*Loans!C7/12)) | AC28: =IF(OR(C28<>"Closed",D28="",F28=""),"",IF(AC11>D28,"",AB88*Loans!C7/12)) | AD28: =IF(OR(C28<>"Closed",D28="",F28=""),"",IF(AD11>D28,"",AC88*Loans!C7/12)) | AE28: =IF(OR(C28<>"Closed",D28="",F28=""),"",IF(AE11>D28,"",AD88*Loans!C7/12)) | AF28: =IF(OR(C28<>"Closed",D28="",F28=""),"",IF(AF11>D28,"",AE88*Loans!C7/12)) | AG28: =IF(OR(C28<>"Closed",D28="",F28=""),"",IF(AG11>D28,"",AF88*Loans!C7/12)) | AH28: =IF(OR(C28<>"Closed",D28="",F28=""),"",IF(AH11>D28,"",AG88*Loans!C7/12)) | AI28: =IF(OR(C28<>"Closed",D28="",F28=""),"",IF(AI11>D28,"",AH88*Loans!C7/12)) | AJ28: =IF(OR(C28<>"Closed",D28="",F28=""),"",IF(AJ11>D28,"",AI88*Loans!C7/12)) | AK28: =IF(OR(C28<>"Closed",D28="",F28=""),"",IF(AK11>D28,"",AJ88*Loans!C7/12)) | AL28: =IF(OR(C28<>"Closed",D28="",F28=""),"",IF(AL11>D28,"",AK88*Loans!C7/12)) | AM28: =IF(OR(C28<>"Closed",D28="",F28=""),"",IF(AM11>D28,"",AL88*Loans!C7/12)) | AN28: =IF(OR(C28<>"Closed",D28="",F28=""),"",IF(AN11>D28,"",AM88*Loans!C7/12)) | AO28: =IF(OR(C28<>"Closed",D28="",F28=""),"",IF(AO11>D28,"",AN88*Loans!C7/12)) | AP28: =IF(OR(C28<>"Closed",D28="",F28=""),"",IF(AP11>D28,"",AO88*Loans!C7/12)) | AQ28: =IF(OR(C28<>"Closed",D28="",F28=""),"",IF(AQ11>D28,"",AP88*Loans!C7/12)) | AR28: =IF(OR(C28<>"Closed",D28="",F28=""),"",IF(AR11>D28,"",AQ88*Loans!C7/12)) | AS28: =IF(OR(C28<>"Closed",D28="",F28=""),"",IF(AS11>D28,"",AR88*Loans!C7/12)) | AT28: =IF(OR(C28<>"Closed",D28="",F28=""),"",IF(AT11>D28,"",AS88*Loans!C7/12)) | AU28: =IF(OR(C28<>"Closed",D28="",F28=""),"",IF(AU11>D28,"",AT88*Loans!C7/12)) | AV28: =IF(OR(C28<>"Closed",D28="",F28=""),"",IF(AV11>D28,"",AU88*Loans!C7/12)) | AW28: =IF(OR(C28<>"Closed",D28="",F28=""),"",IF(AW11>D28,"",AV88*Loans!C7/12)) | AX28: =IF(OR(C28<>"Closed",D28="",F28=""),"",IF(AX11>D28,"",AW88*Loans!C7/12)) | AY28: =IF(OR(C28<>"Closed",D28="",F28=""),"",IF(AY11>D28,"",AX88*Loans!C7/12)) | AZ28: =IF(OR(C28<>"Closed",D28="",F28=""),"",IF(AZ11>D28,"",AY88*Loans!C7/12)) | BA28: =IF(OR(C28<>"Closed",D28="",F28=""),"",IF(BA11>D28,"",AZ88*Loans!C7/12)) | BB28: =IF(OR(C28<>"Closed",D28="",F28=""),"",IF(BB11>D28,"",BA88*Loans!C7/12)) | BC28: =IF(OR(C28<>"Closed",D28="",F28=""),"",IF(BC11>D28,"",BB88*Loans!C7/12)) | BD28: =IF(OR(C28<>"Closed",D28="",F28=""),"",IF(BD11>D28,"",BC88*Loans!C7/12)) | BE28: =IF(OR(C28<>"Closed",D28="",F28=""),"",IF(BE11>D28,"",BD88*Loans!C7/12)) | BF28: =IF(OR(C28<>"Closed",D28="",F28=""),"",IF(BF11>D28,"",BE88*Loans!C7/12)) | BG28: =IF(OR(C28<>"Closed",D28="",F28=""),"",IF(BG11>D28,"",BF88*Loans!C7/12)) | BH28: =IF(OR(C28<>"Closed",D28="",F28=""),"",IF(BH11>D28,"",BG88*Loans!C7/12)) | BI28: =IF(OR(C28<>"Closed",D28="",F28=""),"",IF(BI11>D28,"",BH88*Loans!C7/12)) | BJ28: =IF(OR(C28<>"Closed",D28="",F28=""),"",IF(BJ11>D28,"",BI88*Loans!C7/12)) | BK28: =IF(OR(C28<>"Closed",D28="",F28=""),"",IF(BK11>D28,"",BJ88*Loans!C7/12)) | BL28: =IF(OR(C28<>"Closed",D28="",F28=""),"",IF(BL11>D28,"",BK88*Loans!C7/12)) | BM28: =IF(OR(C28<>"Closed",D28="",F28=""),"",IF(BM11>D28,"",BL88*Loans!C7/12)) | BN28: =IF(OR(C28<>"Closed",D28="",F28=""),"",IF(BN11>D28,"",BM88*Loans!C7/12)) | BO28: =IF(OR(C28<>"Closed",D28="",F28=""),"",IF(BO11>D28,"",BN88*Loans!C7/12)) | BP28: =IF(OR(C28<>"Closed",D28="",F28=""),"",IF(BP11>D28,"",BO88*Loans!C7/12))
A29: =IF(Loans!A29="","",Loans!A29) | B29: =IF(Loans!B29="","",Loans!B29) | C29: =IF(Loans!C29="","",Loans!C29) | D29: =IF(Loans!I29="","",Loans!I29) | E29: =IF(Loans!E29="","",Loans!E29) | F29: =IF(Loans!F29="","",Loans!F29) | G29: =IF(OR(C29<>"Closed",D29="",F29=""),"",PMT(Loans!C7/12,D29,-F29)) | H29: =IF(C29<>"Closed","",SUM(I29:BP29)) | I29: =IF(OR(C29<>"Closed",D29="",F29=""),"",IF(I11>D29,"",F29*Loans!C7/12)) | J29: =IF(OR(C29<>"Closed",D29="",F29=""),"",IF(J11>D29,"",I89*Loans!C7/12)) | K29: =IF(OR(C29<>"Closed",D29="",F29=""),"",IF(K11>D29,"",J89*Loans!C7/12)) | L29: =IF(OR(C29<>"Closed",D29="",F29=""),"",IF(L11>D29,"",K89*Loans!C7/12)) | M29: =IF(OR(C29<>"Closed",D29="",F29=""),"",IF(M11>D29,"",L89*Loans!C7/12)) | N29: =IF(OR(C29<>"Closed",D29="",F29=""),"",IF(N11>D29,"",M89*Loans!C7/12)) | O29: =IF(OR(C29<>"Closed",D29="",F29=""),"",IF(O11>D29,"",N89*Loans!C7/12)) | P29: =IF(OR(C29<>"Closed",D29="",F29=""),"",IF(P11>D29,"",O89*Loans!C7/12)) | Q29: =IF(OR(C29<>"Closed",D29="",F29=""),"",IF(Q11>D29,"",P89*Loans!C7/12)) | R29: =IF(OR(C29<>"Closed",D29="",F29=""),"",IF(R11>D29,"",Q89*Loans!C7/12)) | S29: =IF(OR(C29<>"Closed",D29="",F29=""),"",IF(S11>D29,"",R89*Loans!C7/12)) | T29: =IF(OR(C29<>"Closed",D29="",F29=""),"",IF(T11>D29,"",S89*Loans!C7/12)) | U29: =IF(OR(C29<>"Closed",D29="",F29=""),"",IF(U11>D29,"",T89*Loans!C7/12)) | V29: =IF(OR(C29<>"Closed",D29="",F29=""),"",IF(V11>D29,"",U89*Loans!C7/12)) | W29: =IF(OR(C29<>"Closed",D29="",F29=""),"",IF(W11>D29,"",V89*Loans!C7/12)) | X29: =IF(OR(C29<>"Closed",D29="",F29=""),"",IF(X11>D29,"",W89*Loans!C7/12)) | Y29: =IF(OR(C29<>"Closed",D29="",F29=""),"",IF(Y11>D29,"",X89*Loans!C7/12)) | Z29: =IF(OR(C29<>"Closed",D29="",F29=""),"",IF(Z11>D29,"",Y89*Loans!C7/12)) | AA29: =IF(OR(C29<>"Closed",D29="",F29=""),"",IF(AA11>D29,"",Z89*Loans!C7/12)) | AB29: =IF(OR(C29<>"Closed",D29="",F29=""),"",IF(AB11>D29,"",AA89*Loans!C7/12)) | AC29: =IF(OR(C29<>"Closed",D29="",F29=""),"",IF(AC11>D29,"",AB89*Loans!C7/12)) | AD29: =IF(OR(C29<>"Closed",D29="",F29=""),"",IF(AD11>D29,"",AC89*Loans!C7/12)) | AE29: =IF(OR(C29<>"Closed",D29="",F29=""),"",IF(AE11>D29,"",AD89*Loans!C7/12)) | AF29: =IF(OR(C29<>"Closed",D29="",F29=""),"",IF(AF11>D29,"",AE89*Loans!C7/12)) | AG29: =IF(OR(C29<>"Closed",D29="",F29=""),"",IF(AG11>D29,"",AF89*Loans!C7/12)) | AH29: =IF(OR(C29<>"Closed",D29="",F29=""),"",IF(AH11>D29,"",AG89*Loans!C7/12)) | AI29: =IF(OR(C29<>"Closed",D29="",F29=""),"",IF(AI11>D29,"",AH89*Loans!C7/12)) | AJ29: =IF(OR(C29<>"Closed",D29="",F29=""),"",IF(AJ11>D29,"",AI89*Loans!C7/12)) | AK29: =IF(OR(C29<>"Closed",D29="",F29=""),"",IF(AK11>D29,"",AJ89*Loans!C7/12)) | AL29: =IF(OR(C29<>"Closed",D29="",F29=""),"",IF(AL11>D29,"",AK89*Loans!C7/12)) | AM29: =IF(OR(C29<>"Closed",D29="",F29=""),"",IF(AM11>D29,"",AL89*Loans!C7/12)) | AN29: =IF(OR(C29<>"Closed",D29="",F29=""),"",IF(AN11>D29,"",AM89*Loans!C7/12)) | AO29: =IF(OR(C29<>"Closed",D29="",F29=""),"",IF(AO11>D29,"",AN89*Loans!C7/12)) | AP29: =IF(OR(C29<>"Closed",D29="",F29=""),"",IF(AP11>D29,"",AO89*Loans!C7/12)) | AQ29: =IF(OR(C29<>"Closed",D29="",F29=""),"",IF(AQ11>D29,"",AP89*Loans!C7/12)) | AR29: =IF(OR(C29<>"Closed",D29="",F29=""),"",IF(AR11>D29,"",AQ89*Loans!C7/12)) | AS29: =IF(OR(C29<>"Closed",D29="",F29=""),"",IF(AS11>D29,"",AR89*Loans!C7/12)) | AT29: =IF(OR(C29<>"Closed",D29="",F29=""),"",IF(AT11>D29,"",AS89*Loans!C7/12)) | AU29: =IF(OR(C29<>"Closed",D29="",F29=""),"",IF(AU11>D29,"",AT89*Loans!C7/12)) | AV29: =IF(OR(C29<>"Closed",D29="",F29=""),"",IF(AV11>D29,"",AU89*Loans!C7/12)) | AW29: =IF(OR(C29<>"Closed",D29="",F29=""),"",IF(AW11>D29,"",AV89*Loans!C7/12)) | AX29: =IF(OR(C29<>"Closed",D29="",F29=""),"",IF(AX11>D29,"",AW89*Loans!C7/12)) | AY29: =IF(OR(C29<>"Closed",D29="",F29=""),"",IF(AY11>D29,"",AX89*Loans!C7/12)) | AZ29: =IF(OR(C29<>"Closed",D29="",F29=""),"",IF(AZ11>D29,"",AY89*Loans!C7/12)) | BA29: =IF(OR(C29<>"Closed",D29="",F29=""),"",IF(BA11>D29,"",AZ89*Loans!C7/12)) | BB29: =IF(OR(C29<>"Closed",D29="",F29=""),"",IF(BB11>D29,"",BA89*Loans!C7/12)) | BC29: =IF(OR(C29<>"Closed",D29="",F29=""),"",IF(BC11>D29,"",BB89*Loans!C7/12)) | BD29: =IF(OR(C29<>"Closed",D29="",F29=""),"",IF(BD11>D29,"",BC89*Loans!C7/12)) | BE29: =IF(OR(C29<>"Closed",D29="",F29=""),"",IF(BE11>D29,"",BD89*Loans!C7/12)) | BF29: =IF(OR(C29<>"Closed",D29="",F29=""),"",IF(BF11>D29,"",BE89*Loans!C7/12)) | BG29: =IF(OR(C29<>"Closed",D29="",F29=""),"",IF(BG11>D29,"",BF89*Loans!C7/12)) | BH29: =IF(OR(C29<>"Closed",D29="",F29=""),"",IF(BH11>D29,"",BG89*Loans!C7/12)) | BI29: =IF(OR(C29<>"Closed",D29="",F29=""),"",IF(BI11>D29,"",BH89*Loans!C7/12)) | BJ29: =IF(OR(C29<>"Closed",D29="",F29=""),"",IF(BJ11>D29,"",BI89*Loans!C7/12)) | BK29: =IF(OR(C29<>"Closed",D29="",F29=""),"",IF(BK11>D29,"",BJ89*Loans!C7/12)) | BL29: =IF(OR(C29<>"Closed",D29="",F29=""),"",IF(BL11>D29,"",BK89*Loans!C7/12)) | BM29: =IF(OR(C29<>"Closed",D29="",F29=""),"",IF(BM11>D29,"",BL89*Loans!C7/12)) | BN29: =IF(OR(C29<>"Closed",D29="",F29=""),"",IF(BN11>D29,"",BM89*Loans!C7/12)) | BO29: =IF(OR(C29<>"Closed",D29="",F29=""),"",IF(BO11>D29,"",BN89*Loans!C7/12)) | BP29: =IF(OR(C29<>"Closed",D29="",F29=""),"",IF(BP11>D29,"",BO89*Loans!C7/12))
A30: =IF(Loans!A30="","",Loans!A30) | B30: =IF(Loans!B30="","",Loans!B30) | C30: =IF(Loans!C30="","",Loans!C30) | D30: =IF(Loans!I30="","",Loans!I30) | E30: =IF(Loans!E30="","",Loans!E30) | F30: =IF(Loans!F30="","",Loans!F30) | G30: =IF(OR(C30<>"Closed",D30="",F30=""),"",PMT(Loans!C7/12,D30,-F30)) | H30: =IF(C30<>"Closed","",SUM(I30:BP30)) | I30: =IF(OR(C30<>"Closed",D30="",F30=""),"",IF(I11>D30,"",F30*Loans!C7/12)) | J30: =IF(OR(C30<>"Closed",D30="",F30=""),"",IF(J11>D30,"",I90*Loans!C7/12)) | K30: =IF(OR(C30<>"Closed",D30="",F30=""),"",IF(K11>D30,"",J90*Loans!C7/12)) | L30: =IF(OR(C30<>"Closed",D30="",F30=""),"",IF(L11>D30,"",K90*Loans!C7/12)) | M30: =IF(OR(C30<>"Closed",D30="",F30=""),"",IF(M11>D30,"",L90*Loans!C7/12)) | N30: =IF(OR(C30<>"Closed",D30="",F30=""),"",IF(N11>D30,"",M90*Loans!C7/12)) | O30: =IF(OR(C30<>"Closed",D30="",F30=""),"",IF(O11>D30,"",N90*Loans!C7/12)) | P30: =IF(OR(C30<>"Closed",D30="",F30=""),"",IF(P11>D30,"",O90*Loans!C7/12)) | Q30: =IF(OR(C30<>"Closed",D30="",F30=""),"",IF(Q11>D30,"",P90*Loans!C7/12)) | R30: =IF(OR(C30<>"Closed",D30="",F30=""),"",IF(R11>D30,"",Q90*Loans!C7/12)) | S30: =IF(OR(C30<>"Closed",D30="",F30=""),"",IF(S11>D30,"",R90*Loans!C7/12)) | T30: =IF(OR(C30<>"Closed",D30="",F30=""),"",IF(T11>D30,"",S90*Loans!C7/12)) | U30: =IF(OR(C30<>"Closed",D30="",F30=""),"",IF(U11>D30,"",T90*Loans!C7/12)) | V30: =IF(OR(C30<>"Closed",D30="",F30=""),"",IF(V11>D30,"",U90*Loans!C7/12)) | W30: =IF(OR(C30<>"Closed",D30="",F30=""),"",IF(W11>D30,"",V90*Loans!C7/12)) | X30: =IF(OR(C30<>"Closed",D30="",F30=""),"",IF(X11>D30,"",W90*Loans!C7/12)) | Y30: =IF(OR(C30<>"Closed",D30="",F30=""),"",IF(Y11>D30,"",X90*Loans!C7/12)) | Z30: =IF(OR(C30<>"Closed",D30="",F30=""),"",IF(Z11>D30,"",Y90*Loans!C7/12)) | AA30: =IF(OR(C30<>"Closed",D30="",F30=""),"",IF(AA11>D30,"",Z90*Loans!C7/12)) | AB30: =IF(OR(C30<>"Closed",D30="",F30=""),"",IF(AB11>D30,"",AA90*Loans!C7/12)) | AC30: =IF(OR(C30<>"Closed",D30="",F30=""),"",IF(AC11>D30,"",AB90*Loans!C7/12)) | AD30: =IF(OR(C30<>"Closed",D30="",F30=""),"",IF(AD11>D30,"",AC90*Loans!C7/12)) | AE30: =IF(OR(C30<>"Closed",D30="",F30=""),"",IF(AE11>D30,"",AD90*Loans!C7/12)) | AF30: =IF(OR(C30<>"Closed",D30="",F30=""),"",IF(AF11>D30,"",AE90*Loans!C7/12)) | AG30: =IF(OR(C30<>"Closed",D30="",F30=""),"",IF(AG11>D30,"",AF90*Loans!C7/12)) | AH30: =IF(OR(C30<>"Closed",D30="",F30=""),"",IF(AH11>D30,"",AG90*Loans!C7/12)) | AI30: =IF(OR(C30<>"Closed",D30="",F30=""),"",IF(AI11>D30,"",AH90*Loans!C7/12)) | AJ30: =IF(OR(C30<>"Closed",D30="",F30=""),"",IF(AJ11>D30,"",AI90*Loans!C7/12)) | AK30: =IF(OR(C30<>"Closed",D30="",F30=""),"",IF(AK11>D30,"",AJ90*Loans!C7/12)) | AL30: =IF(OR(C30<>"Closed",D30="",F30=""),"",IF(AL11>D30,"",AK90*Loans!C7/12)) | AM30: =IF(OR(C30<>"Closed",D30="",F30=""),"",IF(AM11>D30,"",AL90*Loans!C7/12)) | AN30: =IF(OR(C30<>"Closed",D30="",F30=""),"",IF(AN11>D30,"",AM90*Loans!C7/12)) | AO30: =IF(OR(C30<>"Closed",D30="",F30=""),"",IF(AO11>D30,"",AN90*Loans!C7/12)) | AP30: =IF(OR(C30<>"Closed",D30="",F30=""),"",IF(AP11>D30,"",AO90*Loans!C7/12)) | AQ30: =IF(OR(C30<>"Closed",D30="",F30=""),"",IF(AQ11>D30,"",AP90*Loans!C7/12)) | AR30: =IF(OR(C30<>"Closed",D30="",F30=""),"",IF(AR11>D30,"",AQ90*Loans!C7/12)) | AS30: =IF(OR(C30<>"Closed",D30="",F30=""),"",IF(AS11>D30,"",AR90*Loans!C7/12)) | AT30: =IF(OR(C30<>"Closed",D30="",F30=""),"",IF(AT11>D30,"",AS90*Loans!C7/12)) | AU30: =IF(OR(C30<>"Closed",D30="",F30=""),"",IF(AU11>D30,"",AT90*Loans!C7/12)) | AV30: =IF(OR(C30<>"Closed",D30="",F30=""),"",IF(AV11>D30,"",AU90*Loans!C7/12)) | AW30: =IF(OR(C30<>"Closed",D30="",F30=""),"",IF(AW11>D30,"",AV90*Loans!C7/12)) | AX30: =IF(OR(C30<>"Closed",D30="",F30=""),"",IF(AX11>D30,"",AW90*Loans!C7/12)) | AY30: =IF(OR(C30<>"Closed",D30="",F30=""),"",IF(AY11>D30,"",AX90*Loans!C7/12)) | AZ30: =IF(OR(C30<>"Closed",D30="",F30=""),"",IF(AZ11>D30,"",AY90*Loans!C7/12)) | BA30: =IF(OR(C30<>"Closed",D30="",F30=""),"",IF(BA11>D30,"",AZ90*Loans!C7/12)) | BB30: =IF(OR(C30<>"Closed",D30="",F30=""),"",IF(BB11>D30,"",BA90*Loans!C7/12)) | BC30: =IF(OR(C30<>"Closed",D30="",F30=""),"",IF(BC11>D30,"",BB90*Loans!C7/12)) | BD30: =IF(OR(C30<>"Closed",D30="",F30=""),"",IF(BD11>D30,"",BC90*Loans!C7/12)) | BE30: =IF(OR(C30<>"Closed",D30="",F30=""),"",IF(BE11>D30,"",BD90*Loans!C7/12)) | BF30: =IF(OR(C30<>"Closed",D30="",F30=""),"",IF(BF11>D30,"",BE90*Loans!C7/12)) | BG30: =IF(OR(C30<>"Closed",D30="",F30=""),"",IF(BG11>D30,"",BF90*Loans!C7/12)) | BH30: =IF(OR(C30<>"Closed",D30="",F30=""),"",IF(BH11>D30,"",BG90*Loans!C7/12)) | BI30: =IF(OR(C30<>"Closed",D30="",F30=""),"",IF(BI11>D30,"",BH90*Loans!C7/12)) | BJ30: =IF(OR(C30<>"Closed",D30="",F30=""),"",IF(BJ11>D30,"",BI90*Loans!C7/12)) | BK30: =IF(OR(C30<>"Closed",D30="",F30=""),"",IF(BK11>D30,"",BJ90*Loans!C7/12)) | BL30: =IF(OR(C30<>"Closed",D30="",F30=""),"",IF(BL11>D30,"",BK90*Loans!C7/12)) | BM30: =IF(OR(C30<>"Closed",D30="",F30=""),"",IF(BM11>D30,"",BL90*Loans!C7/12)) | BN30: =IF(OR(C30<>"Closed",D30="",F30=""),"",IF(BN11>D30,"",BM90*Loans!C7/12)) | BO30: =IF(OR(C30<>"Closed",D30="",F30=""),"",IF(BO11>D30,"",BN90*Loans!C7/12)) | BP30: =IF(OR(C30<>"Closed",D30="",F30=""),"",IF(BP11>D30,"",BO90*Loans!C7/12))
A31: =IF(Loans!A31="","",Loans!A31) | B31: =IF(Loans!B31="","",Loans!B31) | C31: =IF(Loans!C31="","",Loans!C31) | D31: =IF(Loans!I31="","",Loans!I31) | E31: =IF(Loans!E31="","",Loans!E31) | F31: =IF(Loans!F31="","",Loans!F31) | G31: =IF(OR(C31<>"Closed",D31="",F31=""),"",PMT(Loans!C7/12,D31,-F31)) | H31: =IF(C31<>"Closed","",SUM(I31:BP31)) | I31: =IF(OR(C31<>"Closed",D31="",F31=""),"",IF(I11>D31,"",F31*Loans!C7/12)) | J31: =IF(OR(C31<>"Closed",D31="",F31=""),"",IF(J11>D31,"",I91*Loans!C7/12)) | K31: =IF(OR(C31<>"Closed",D31="",F31=""),"",IF(K11>D31,"",J91*Loans!C7/12)) | L31: =IF(OR(C31<>"Closed",D31="",F31=""),"",IF(L11>D31,"",K91*Loans!C7/12)) | M31: =IF(OR(C31<>"Closed",D31="",F31=""),"",IF(M11>D31,"",L91*Loans!C7/12)) | N31: =IF(OR(C31<>"Closed",D31="",F31=""),"",IF(N11>D31,"",M91*Loans!C7/12)) | O31: =IF(OR(C31<>"Closed",D31="",F31=""),"",IF(O11>D31,"",N91*Loans!C7/12)) | P31: =IF(OR(C31<>"Closed",D31="",F31=""),"",IF(P11>D31,"",O91*Loans!C7/12)) | Q31: =IF(OR(C31<>"Closed",D31="",F31=""),"",IF(Q11>D31,"",P91*Loans!C7/12)) | R31: =IF(OR(C31<>"Closed",D31="",F31=""),"",IF(R11>D31,"",Q91*Loans!C7/12)) | S31: =IF(OR(C31<>"Closed",D31="",F31=""),"",IF(S11>D31,"",R91*Loans!C7/12)) | T31: =IF(OR(C31<>"Closed",D31="",F31=""),"",IF(T11>D31,"",S91*Loans!C7/12)) | U31: =IF(OR(C31<>"Closed",D31="",F31=""),"",IF(U11>D31,"",T91*Loans!C7/12)) | V31: =IF(OR(C31<>"Closed",D31="",F31=""),"",IF(V11>D31,"",U91*Loans!C7/12)) | W31: =IF(OR(C31<>"Closed",D31="",F31=""),"",IF(W11>D31,"",V91*Loans!C7/12)) | X31: =IF(OR(C31<>"Closed",D31="",F31=""),"",IF(X11>D31,"",W91*Loans!C7/12)) | Y31: =IF(OR(C31<>"Closed",D31="",F31=""),"",IF(Y11>D31,"",X91*Loans!C7/12)) | Z31: =IF(OR(C31<>"Closed",D31="",F31=""),"",IF(Z11>D31,"",Y91*Loans!C7/12)) | AA31: =IF(OR(C31<>"Closed",D31="",F31=""),"",IF(AA11>D31,"",Z91*Loans!C7/12)) | AB31: =IF(OR(C31<>"Closed",D31="",F31=""),"",IF(AB11>D31,"",AA91*Loans!C7/12)) | AC31: =IF(OR(C31<>"Closed",D31="",F31=""),"",IF(AC11>D31,"",AB91*Loans!C7/12)) | AD31: =IF(OR(C31<>"Closed",D31="",F31=""),"",IF(AD11>D31,"",AC91*Loans!C7/12)) | AE31: =IF(OR(C31<>"Closed",D31="",F31=""),"",IF(AE11>D31,"",AD91*Loans!C7/12)) | AF31: =IF(OR(C31<>"Closed",D31="",F31=""),"",IF(AF11>D31,"",AE91*Loans!C7/12)) | AG31: =IF(OR(C31<>"Closed",D31="",F31=""),"",IF(AG11>D31,"",AF91*Loans!C7/12)) | AH31: =IF(OR(C31<>"Closed",D31="",F31=""),"",IF(AH11>D31,"",AG91*Loans!C7/12)) | AI31: =IF(OR(C31<>"Closed",D31="",F31=""),"",IF(AI11>D31,"",AH91*Loans!C7/12)) | AJ31: =IF(OR(C31<>"Closed",D31="",F31=""),"",IF(AJ11>D31,"",AI91*Loans!C7/12)) | AK31: =IF(OR(C31<>"Closed",D31="",F31=""),"",IF(AK11>D31,"",AJ91*Loans!C7/12)) | AL31: =IF(OR(C31<>"Closed",D31="",F31=""),"",IF(AL11>D31,"",AK91*Loans!C7/12)) | AM31: =IF(OR(C31<>"Closed",D31="",F31=""),"",IF(AM11>D31,"",AL91*Loans!C7/12)) | AN31: =IF(OR(C31<>"Closed",D31="",F31=""),"",IF(AN11>D31,"",AM91*Loans!C7/12)) | AO31: =IF(OR(C31<>"Closed",D31="",F31=""),"",IF(AO11>D31,"",AN91*Loans!C7/12)) | AP31: =IF(OR(C31<>"Closed",D31="",F31=""),"",IF(AP11>D31,"",AO91*Loans!C7/12)) | AQ31: =IF(OR(C31<>"Closed",D31="",F31=""),"",IF(AQ11>D31,"",AP91*Loans!C7/12)) | AR31: =IF(OR(C31<>"Closed",D31="",F31=""),"",IF(AR11>D31,"",AQ91*Loans!C7/12)) | AS31: =IF(OR(C31<>"Closed",D31="",F31=""),"",IF(AS11>D31,"",AR91*Loans!C7/12)) | AT31: =IF(OR(C31<>"Closed",D31="",F31=""),"",IF(AT11>D31,"",AS91*Loans!C7/12)) | AU31: =IF(OR(C31<>"Closed",D31="",F31=""),"",IF(AU11>D31,"",AT91*Loans!C7/12)) | AV31: =IF(OR(C31<>"Closed",D31="",F31=""),"",IF(AV11>D31,"",AU91*Loans!C7/12)) | AW31: =IF(OR(C31<>"Closed",D31="",F31=""),"",IF(AW11>D31,"",AV91*Loans!C7/12)) | AX31: =IF(OR(C31<>"Closed",D31="",F31=""),"",IF(AX11>D31,"",AW91*Loans!C7/12)) | AY31: =IF(OR(C31<>"Closed",D31="",F31=""),"",IF(AY11>D31,"",AX91*Loans!C7/12)) | AZ31: =IF(OR(C31<>"Closed",D31="",F31=""),"",IF(AZ11>D31,"",AY91*Loans!C7/12)) | BA31: =IF(OR(C31<>"Closed",D31="",F31=""),"",IF(BA11>D31,"",AZ91*Loans!C7/12)) | BB31: =IF(OR(C31<>"Closed",D31="",F31=""),"",IF(BB11>D31,"",BA91*Loans!C7/12)) | BC31: =IF(OR(C31<>"Closed",D31="",F31=""),"",IF(BC11>D31,"",BB91*Loans!C7/12)) | BD31: =IF(OR(C31<>"Closed",D31="",F31=""),"",IF(BD11>D31,"",BC91*Loans!C7/12)) | BE31: =IF(OR(C31<>"Closed",D31="",F31=""),"",IF(BE11>D31,"",BD91*Loans!C7/12)) | BF31: =IF(OR(C31<>"Closed",D31="",F31=""),"",IF(BF11>D31,"",BE91*Loans!C7/12)) | BG31: =IF(OR(C31<>"Closed",D31="",F31=""),"",IF(BG11>D31,"",BF91*Loans!C7/12)) | BH31: =IF(OR(C31<>"Closed",D31="",F31=""),"",IF(BH11>D31,"",BG91*Loans!C7/12)) | BI31: =IF(OR(C31<>"Closed",D31="",F31=""),"",IF(BI11>D31,"",BH91*Loans!C7/12)) | BJ31: =IF(OR(C31<>"Closed",D31="",F31=""),"",IF(BJ11>D31,"",BI91*Loans!C7/12)) | BK31: =IF(OR(C31<>"Closed",D31="",F31=""),"",IF(BK11>D31,"",BJ91*Loans!C7/12)) | BL31: =IF(OR(C31<>"Closed",D31="",F31=""),"",IF(BL11>D31,"",BK91*Loans!C7/12)) | BM31: =IF(OR(C31<>"Closed",D31="",F31=""),"",IF(BM11>D31,"",BL91*Loans!C7/12)) | BN31: =IF(OR(C31<>"Closed",D31="",F31=""),"",IF(BN11>D31,"",BM91*Loans!C7/12)) | BO31: =IF(OR(C31<>"Closed",D31="",F31=""),"",IF(BO11>D31,"",BN91*Loans!C7/12)) | BP31: =IF(OR(C31<>"Closed",D31="",F31=""),"",IF(BP11>D31,"",BO91*Loans!C7/12))
A32: =IF(Loans!A32="","",Loans!A32) | B32: =IF(Loans!B32="","",Loans!B32) | C32: =IF(Loans!C32="","",Loans!C32) | D32: =IF(Loans!I32="","",Loans!I32) | E32: =IF(Loans!E32="","",Loans!E32) | F32: =IF(Loans!F32="","",Loans!F32) | G32: =IF(OR(C32<>"Closed",D32="",F32=""),"",PMT(Loans!C7/12,D32,-F32)) | H32: =IF(C32<>"Closed","",SUM(I32:BP32)) | I32: =IF(OR(C32<>"Closed",D32="",F32=""),"",IF(I11>D32,"",F32*Loans!C7/12)) | J32: =IF(OR(C32<>"Closed",D32="",F32=""),"",IF(J11>D32,"",I92*Loans!C7/12)) | K32: =IF(OR(C32<>"Closed",D32="",F32=""),"",IF(K11>D32,"",J92*Loans!C7/12)) | L32: =IF(OR(C32<>"Closed",D32="",F32=""),"",IF(L11>D32,"",K92*Loans!C7/12)) | M32: =IF(OR(C32<>"Closed",D32="",F32=""),"",IF(M11>D32,"",L92*Loans!C7/12)) | N32: =IF(OR(C32<>"Closed",D32="",F32=""),"",IF(N11>D32,"",M92*Loans!C7/12)) | O32: =IF(OR(C32<>"Closed",D32="",F32=""),"",IF(O11>D32,"",N92*Loans!C7/12)) | P32: =IF(OR(C32<>"Closed",D32="",F32=""),"",IF(P11>D32,"",O92*Loans!C7/12)) | Q32: =IF(OR(C32<>"Closed",D32="",F32=""),"",IF(Q11>D32,"",P92*Loans!C7/12)) | R32: =IF(OR(C32<>"Closed",D32="",F32=""),"",IF(R11>D32,"",Q92*Loans!C7/12)) | S32: =IF(OR(C32<>"Closed",D32="",F32=""),"",IF(S11>D32,"",R92*Loans!C7/12)) | T32: =IF(OR(C32<>"Closed",D32="",F32=""),"",IF(T11>D32,"",S92*Loans!C7/12)) | U32: =IF(OR(C32<>"Closed",D32="",F32=""),"",IF(U11>D32,"",T92*Loans!C7/12)) | V32: =IF(OR(C32<>"Closed",D32="",F32=""),"",IF(V11>D32,"",U92*Loans!C7/12)) | W32: =IF(OR(C32<>"Closed",D32="",F32=""),"",IF(W11>D32,"",V92*Loans!C7/12)) | X32: =IF(OR(C32<>"Closed",D32="",F32=""),"",IF(X11>D32,"",W92*Loans!C7/12)) | Y32: =IF(OR(C32<>"Closed",D32="",F32=""),"",IF(Y11>D32,"",X92*Loans!C7/12)) | Z32: =IF(OR(C32<>"Closed",D32="",F32=""),"",IF(Z11>D32,"",Y92*Loans!C7/12)) | AA32: =IF(OR(C32<>"Closed",D32="",F32=""),"",IF(AA11>D32,"",Z92*Loans!C7/12)) | AB32: =IF(OR(C32<>"Closed",D32="",F32=""),"",IF(AB11>D32,"",AA92*Loans!C7/12)) | AC32: =IF(OR(C32<>"Closed",D32="",F32=""),"",IF(AC11>D32,"",AB92*Loans!C7/12)) | AD32: =IF(OR(C32<>"Closed",D32="",F32=""),"",IF(AD11>D32,"",AC92*Loans!C7/12)) | AE32: =IF(OR(C32<>"Closed",D32="",F32=""),"",IF(AE11>D32,"",AD92*Loans!C7/12)) | AF32: =IF(OR(C32<>"Closed",D32="",F32=""),"",IF(AF11>D32,"",AE92*Loans!C7/12)) | AG32: =IF(OR(C32<>"Closed",D32="",F32=""),"",IF(AG11>D32,"",AF92*Loans!C7/12)) | AH32: =IF(OR(C32<>"Closed",D32="",F32=""),"",IF(AH11>D32,"",AG92*Loans!C7/12)) | AI32: =IF(OR(C32<>"Closed",D32="",F32=""),"",IF(AI11>D32,"",AH92*Loans!C7/12)) | AJ32: =IF(OR(C32<>"Closed",D32="",F32=""),"",IF(AJ11>D32,"",AI92*Loans!C7/12)) | AK32: =IF(OR(C32<>"Closed",D32="",F32=""),"",IF(AK11>D32,"",AJ92*Loans!C7/12)) | AL32: =IF(OR(C32<>"Closed",D32="",F32=""),"",IF(AL11>D32,"",AK92*Loans!C7/12)) | AM32: =IF(OR(C32<>"Closed",D32="",F32=""),"",IF(AM11>D32,"",AL92*Loans!C7/12)) | AN32: =IF(OR(C32<>"Closed",D32="",F32=""),"",IF(AN11>D32,"",AM92*Loans!C7/12)) | AO32: =IF(OR(C32<>"Closed",D32="",F32=""),"",IF(AO11>D32,"",AN92*Loans!C7/12)) | AP32: =IF(OR(C32<>"Closed",D32="",F32=""),"",IF(AP11>D32,"",AO92*Loans!C7/12)) | AQ32: =IF(OR(C32<>"Closed",D32="",F32=""),"",IF(AQ11>D32,"",AP92*Loans!C7/12)) | AR32: =IF(OR(C32<>"Closed",D32="",F32=""),"",IF(AR11>D32,"",AQ92*Loans!C7/12)) | AS32: =IF(OR(C32<>"Closed",D32="",F32=""),"",IF(AS11>D32,"",AR92*Loans!C7/12)) | AT32: =IF(OR(C32<>"Closed",D32="",F32=""),"",IF(AT11>D32,"",AS92*Loans!C7/12)) | AU32: =IF(OR(C32<>"Closed",D32="",F32=""),"",IF(AU11>D32,"",AT92*Loans!C7/12)) | AV32: =IF(OR(C32<>"Closed",D32="",F32=""),"",IF(AV11>D32,"",AU92*Loans!C7/12)) | AW32: =IF(OR(C32<>"Closed",D32="",F32=""),"",IF(AW11>D32,"",AV92*Loans!C7/12)) | AX32: =IF(OR(C32<>"Closed",D32="",F32=""),"",IF(AX11>D32,"",AW92*Loans!C7/12)) | AY32: =IF(OR(C32<>"Closed",D32="",F32=""),"",IF(AY11>D32,"",AX92*Loans!C7/12)) | AZ32: =IF(OR(C32<>"Closed",D32="",F32=""),"",IF(AZ11>D32,"",AY92*Loans!C7/12)) | BA32: =IF(OR(C32<>"Closed",D32="",F32=""),"",IF(BA11>D32,"",AZ92*Loans!C7/12)) | BB32: =IF(OR(C32<>"Closed",D32="",F32=""),"",IF(BB11>D32,"",BA92*Loans!C7/12)) | BC32: =IF(OR(C32<>"Closed",D32="",F32=""),"",IF(BC11>D32,"",BB92*Loans!C7/12)) | BD32: =IF(OR(C32<>"Closed",D32="",F32=""),"",IF(BD11>D32,"",BC92*Loans!C7/12)) | BE32: =IF(OR(C32<>"Closed",D32="",F32=""),"",IF(BE11>D32,"",BD92*Loans!C7/12)) | BF32: =IF(OR(C32<>"Closed",D32="",F32=""),"",IF(BF11>D32,"",BE92*Loans!C7/12)) | BG32: =IF(OR(C32<>"Closed",D32="",F32=""),"",IF(BG11>D32,"",BF92*Loans!C7/12)) | BH32: =IF(OR(C32<>"Closed",D32="",F32=""),"",IF(BH11>D32,"",BG92*Loans!C7/12)) | BI32: =IF(OR(C32<>"Closed",D32="",F32=""),"",IF(BI11>D32,"",BH92*Loans!C7/12)) | BJ32: =IF(OR(C32<>"Closed",D32="",F32=""),"",IF(BJ11>D32,"",BI92*Loans!C7/12)) | BK32: =IF(OR(C32<>"Closed",D32="",F32=""),"",IF(BK11>D32,"",BJ92*Loans!C7/12)) | BL32: =IF(OR(C32<>"Closed",D32="",F32=""),"",IF(BL11>D32,"",BK92*Loans!C7/12)) | BM32: =IF(OR(C32<>"Closed",D32="",F32=""),"",IF(BM11>D32,"",BL92*Loans!C7/12)) | BN32: =IF(OR(C32<>"Closed",D32="",F32=""),"",IF(BN11>D32,"",BM92*Loans!C7/12)) | BO32: =IF(OR(C32<>"Closed",D32="",F32=""),"",IF(BO11>D32,"",BN92*Loans!C7/12)) | BP32: =IF(OR(C32<>"Closed",D32="",F32=""),"",IF(BP11>D32,"",BO92*Loans!C7/12))
A33: =IF(Loans!A33="","",Loans!A33) | B33: =IF(Loans!B33="","",Loans!B33) | C33: =IF(Loans!C33="","",Loans!C33) | D33: =IF(Loans!I33="","",Loans!I33) | E33: =IF(Loans!E33="","",Loans!E33) | F33: =IF(Loans!F33="","",Loans!F33) | G33: =IF(OR(C33<>"Closed",D33="",F33=""),"",PMT(Loans!C7/12,D33,-F33)) | H33: =IF(C33<>"Closed","",SUM(I33:BP33)) | I33: =IF(OR(C33<>"Closed",D33="",F33=""),"",IF(I11>D33,"",F33*Loans!C7/12)) | J33: =IF(OR(C33<>"Closed",D33="",F33=""),"",IF(J11>D33,"",I93*Loans!C7/12)) | K33: =IF(OR(C33<>"Closed",D33="",F33=""),"",IF(K11>D33,"",J93*Loans!C7/12)) | L33: =IF(OR(C33<>"Closed",D33="",F33=""),"",IF(L11>D33,"",K93*Loans!C7/12)) | M33: =IF(OR(C33<>"Closed",D33="",F33=""),"",IF(M11>D33,"",L93*Loans!C7/12)) | N33: =IF(OR(C33<>"Closed",D33="",F33=""),"",IF(N11>D33,"",M93*Loans!C7/12)) | O33: =IF(OR(C33<>"Closed",D33="",F33=""),"",IF(O11>D33,"",N93*Loans!C7/12)) | P33: =IF(OR(C33<>"Closed",D33="",F33=""),"",IF(P11>D33,"",O93*Loans!C7/12)) | Q33: =IF(OR(C33<>"Closed",D33="",F33=""),"",IF(Q11>D33,"",P93*Loans!C7/12)) | R33: =IF(OR(C33<>"Closed",D33="",F33=""),"",IF(R11>D33,"",Q93*Loans!C7/12)) | S33: =IF(OR(C33<>"Closed",D33="",F33=""),"",IF(S11>D33,"",R93*Loans!C7/12)) | T33: =IF(OR(C33<>"Closed",D33="",F33=""),"",IF(T11>D33,"",S93*Loans!C7/12)) | U33: =IF(OR(C33<>"Closed",D33="",F33=""),"",IF(U11>D33,"",T93*Loans!C7/12)) | V33: =IF(OR(C33<>"Closed",D33="",F33=""),"",IF(V11>D33,"",U93*Loans!C7/12)) | W33: =IF(OR(C33<>"Closed",D33="",F33=""),"",IF(W11>D33,"",V93*Loans!C7/12)) | X33: =IF(OR(C33<>"Closed",D33="",F33=""),"",IF(X11>D33,"",W93*Loans!C7/12)) | Y33: =IF(OR(C33<>"Closed",D33="",F33=""),"",IF(Y11>D33,"",X93*Loans!C7/12)) | Z33: =IF(OR(C33<>"Closed",D33="",F33=""),"",IF(Z11>D33,"",Y93*Loans!C7/12)) | AA33: =IF(OR(C33<>"Closed",D33="",F33=""),"",IF(AA11>D33,"",Z93*Loans!C7/12)) | AB33: =IF(OR(C33<>"Closed",D33="",F33=""),"",IF(AB11>D33,"",AA93*Loans!C7/12)) | AC33: =IF(OR(C33<>"Closed",D33="",F33=""),"",IF(AC11>D33,"",AB93*Loans!C7/12)) | AD33: =IF(OR(C33<>"Closed",D33="",F33=""),"",IF(AD11>D33,"",AC93*Loans!C7/12)) | AE33: =IF(OR(C33<>"Closed",D33="",F33=""),"",IF(AE11>D33,"",AD93*Loans!C7/12)) | AF33: =IF(OR(C33<>"Closed",D33="",F33=""),"",IF(AF11>D33,"",AE93*Loans!C7/12)) | AG33: =IF(OR(C33<>"Closed",D33="",F33=""),"",IF(AG11>D33,"",AF93*Loans!C7/12)) | AH33: =IF(OR(C33<>"Closed",D33="",F33=""),"",IF(AH11>D33,"",AG93*Loans!C7/12)) | AI33: =IF(OR(C33<>"Closed",D33="",F33=""),"",IF(AI11>D33,"",AH93*Loans!C7/12)) | AJ33: =IF(OR(C33<>"Closed",D33="",F33=""),"",IF(AJ11>D33,"",AI93*Loans!C7/12)) | AK33: =IF(OR(C33<>"Closed",D33="",F33=""),"",IF(AK11>D33,"",AJ93*Loans!C7/12)) | AL33: =IF(OR(C33<>"Closed",D33="",F33=""),"",IF(AL11>D33,"",AK93*Loans!C7/12)) | AM33: =IF(OR(C33<>"Closed",D33="",F33=""),"",IF(AM11>D33,"",AL93*Loans!C7/12)) | AN33: =IF(OR(C33<>"Closed",D33="",F33=""),"",IF(AN11>D33,"",AM93*Loans!C7/12)) | AO33: =IF(OR(C33<>"Closed",D33="",F33=""),"",IF(AO11>D33,"",AN93*Loans!C7/12)) | AP33: =IF(OR(C33<>"Closed",D33="",F33=""),"",IF(AP11>D33,"",AO93*Loans!C7/12)) | AQ33: =IF(OR(C33<>"Closed",D33="",F33=""),"",IF(AQ11>D33,"",AP93*Loans!C7/12)) | AR33: =IF(OR(C33<>"Closed",D33="",F33=""),"",IF(AR11>D33,"",AQ93*Loans!C7/12)) | AS33: =IF(OR(C33<>"Closed",D33="",F33=""),"",IF(AS11>D33,"",AR93*Loans!C7/12)) | AT33: =IF(OR(C33<>"Closed",D33="",F33=""),"",IF(AT11>D33,"",AS93*Loans!C7/12)) | AU33: =IF(OR(C33<>"Closed",D33="",F33=""),"",IF(AU11>D33,"",AT93*Loans!C7/12)) | AV33: =IF(OR(C33<>"Closed",D33="",F33=""),"",IF(AV11>D33,"",AU93*Loans!C7/12)) | AW33: =IF(OR(C33<>"Closed",D33="",F33=""),"",IF(AW11>D33,"",AV93*Loans!C7/12)) | AX33: =IF(OR(C33<>"Closed",D33="",F33=""),"",IF(AX11>D33,"",AW93*Loans!C7/12)) | AY33: =IF(OR(C33<>"Closed",D33="",F33=""),"",IF(AY11>D33,"",AX93*Loans!C7/12)) | AZ33: =IF(OR(C33<>"Closed",D33="",F33=""),"",IF(AZ11>D33,"",AY93*Loans!C7/12)) | BA33: =IF(OR(C33<>"Closed",D33="",F33=""),"",IF(BA11>D33,"",AZ93*Loans!C7/12)) | BB33: =IF(OR(C33<>"Closed",D33="",F33=""),"",IF(BB11>D33,"",BA93*Loans!C7/12)) | BC33: =IF(OR(C33<>"Closed",D33="",F33=""),"",IF(BC11>D33,"",BB93*Loans!C7/12)) | BD33: =IF(OR(C33<>"Closed",D33="",F33=""),"",IF(BD11>D33,"",BC93*Loans!C7/12)) | BE33: =IF(OR(C33<>"Closed",D33="",F33=""),"",IF(BE11>D33,"",BD93*Loans!C7/12)) | BF33: =IF(OR(C33<>"Closed",D33="",F33=""),"",IF(BF11>D33,"",BE93*Loans!C7/12)) | BG33: =IF(OR(C33<>"Closed",D33="",F33=""),"",IF(BG11>D33,"",BF93*Loans!C7/12)) | BH33: =IF(OR(C33<>"Closed",D33="",F33=""),"",IF(BH11>D33,"",BG93*Loans!C7/12)) | BI33: =IF(OR(C33<>"Closed",D33="",F33=""),"",IF(BI11>D33,"",BH93*Loans!C7/12)) | BJ33: =IF(OR(C33<>"Closed",D33="",F33=""),"",IF(BJ11>D33,"",BI93*Loans!C7/12)) | BK33: =IF(OR(C33<>"Closed",D33="",F33=""),"",IF(BK11>D33,"",BJ93*Loans!C7/12)) | BL33: =IF(OR(C33<>"Closed",D33="",F33=""),"",IF(BL11>D33,"",BK93*Loans!C7/12)) | BM33: =IF(OR(C33<>"Closed",D33="",F33=""),"",IF(BM11>D33,"",BL93*Loans!C7/12)) | BN33: =IF(OR(C33<>"Closed",D33="",F33=""),"",IF(BN11>D33,"",BM93*Loans!C7/12)) | BO33: =IF(OR(C33<>"Closed",D33="",F33=""),"",IF(BO11>D33,"",BN93*Loans!C7/12)) | BP33: =IF(OR(C33<>"Closed",D33="",F33=""),"",IF(BP11>D33,"",BO93*Loans!C7/12))
A34: =IF(Loans!A34="","",Loans!A34) | B34: =IF(Loans!B34="","",Loans!B34) | C34: =IF(Loans!C34="","",Loans!C34) | D34: =IF(Loans!I34="","",Loans!I34) | E34: =IF(Loans!E34="","",Loans!E34) | F34: =IF(Loans!F34="","",Loans!F34) | G34: =IF(OR(C34<>"Closed",D34="",F34=""),"",PMT(Loans!C7/12,D34,-F34)) | H34: =IF(C34<>"Closed","",SUM(I34:BP34)) | I34: =IF(OR(C34<>"Closed",D34="",F34=""),"",IF(I11>D34,"",F34*Loans!C7/12)) | J34: =IF(OR(C34<>"Closed",D34="",F34=""),"",IF(J11>D34,"",I94*Loans!C7/12)) | K34: =IF(OR(C34<>"Closed",D34="",F34=""),"",IF(K11>D34,"",J94*Loans!C7/12)) | L34: =IF(OR(C34<>"Closed",D34="",F34=""),"",IF(L11>D34,"",K94*Loans!C7/12)) | M34: =IF(OR(C34<>"Closed",D34="",F34=""),"",IF(M11>D34,"",L94*Loans!C7/12)) | N34: =IF(OR(C34<>"Closed",D34="",F34=""),"",IF(N11>D34,"",M94*Loans!C7/12)) | O34: =IF(OR(C34<>"Closed",D34="",F34=""),"",IF(O11>D34,"",N94*Loans!C7/12)) | P34: =IF(OR(C34<>"Closed",D34="",F34=""),"",IF(P11>D34,"",O94*Loans!C7/12)) | Q34: =IF(OR(C34<>"Closed",D34="",F34=""),"",IF(Q11>D34,"",P94*Loans!C7/12)) | R34: =IF(OR(C34<>"Closed",D34="",F34=""),"",IF(R11>D34,"",Q94*Loans!C7/12)) | S34: =IF(OR(C34<>"Closed",D34="",F34=""),"",IF(S11>D34,"",R94*Loans!C7/12)) | T34: =IF(OR(C34<>"Closed",D34="",F34=""),"",IF(T11>D34,"",S94*Loans!C7/12)) | U34: =IF(OR(C34<>"Closed",D34="",F34=""),"",IF(U11>D34,"",T94*Loans!C7/12)) | V34: =IF(OR(C34<>"Closed",D34="",F34=""),"",IF(V11>D34,"",U94*Loans!C7/12)) | W34: =IF(OR(C34<>"Closed",D34="",F34=""),"",IF(W11>D34,"",V94*Loans!C7/12)) | X34: =IF(OR(C34<>"Closed",D34="",F34=""),"",IF(X11>D34,"",W94*Loans!C7/12)) | Y34: =IF(OR(C34<>"Closed",D34="",F34=""),"",IF(Y11>D34,"",X94*Loans!C7/12)) | Z34: =IF(OR(C34<>"Closed",D34="",F34=""),"",IF(Z11>D34,"",Y94*Loans!C7/12)) | AA34: =IF(OR(C34<>"Closed",D34="",F34=""),"",IF(AA11>D34,"",Z94*Loans!C7/12)) | AB34: =IF(OR(C34<>"Closed",D34="",F34=""),"",IF(AB11>D34,"",AA94*Loans!C7/12)) | AC34: =IF(OR(C34<>"Closed",D34="",F34=""),"",IF(AC11>D34,"",AB94*Loans!C7/12)) | AD34: =IF(OR(C34<>"Closed",D34="",F34=""),"",IF(AD11>D34,"",AC94*Loans!C7/12)) | AE34: =IF(OR(C34<>"Closed",D34="",F34=""),"",IF(AE11>D34,"",AD94*Loans!C7/12)) | AF34: =IF(OR(C34<>"Closed",D34="",F34=""),"",IF(AF11>D34,"",AE94*Loans!C7/12)) | AG34: =IF(OR(C34<>"Closed",D34="",F34=""),"",IF(AG11>D34,"",AF94*Loans!C7/12)) | AH34: =IF(OR(C34<>"Closed",D34="",F34=""),"",IF(AH11>D34,"",AG94*Loans!C7/12)) | AI34: =IF(OR(C34<>"Closed",D34="",F34=""),"",IF(AI11>D34,"",AH94*Loans!C7/12)) | AJ34: =IF(OR(C34<>"Closed",D34="",F34=""),"",IF(AJ11>D34,"",AI94*Loans!C7/12)) | AK34: =IF(OR(C34<>"Closed",D34="",F34=""),"",IF(AK11>D34,"",AJ94*Loans!C7/12)) | AL34: =IF(OR(C34<>"Closed",D34="",F34=""),"",IF(AL11>D34,"",AK94*Loans!C7/12)) | AM34: =IF(OR(C34<>"Closed",D34="",F34=""),"",IF(AM11>D34,"",AL94*Loans!C7/12)) | AN34: =IF(OR(C34<>"Closed",D34="",F34=""),"",IF(AN11>D34,"",AM94*Loans!C7/12)) | AO34: =IF(OR(C34<>"Closed",D34="",F34=""),"",IF(AO11>D34,"",AN94*Loans!C7/12)) | AP34: =IF(OR(C34<>"Closed",D34="",F34=""),"",IF(AP11>D34,"",AO94*Loans!C7/12)) | AQ34: =IF(OR(C34<>"Closed",D34="",F34=""),"",IF(AQ11>D34,"",AP94*Loans!C7/12)) | AR34: =IF(OR(C34<>"Closed",D34="",F34=""),"",IF(AR11>D34,"",AQ94*Loans!C7/12)) | AS34: =IF(OR(C34<>"Closed",D34="",F34=""),"",IF(AS11>D34,"",AR94*Loans!C7/12)) | AT34: =IF(OR(C34<>"Closed",D34="",F34=""),"",IF(AT11>D34,"",AS94*Loans!C7/12)) | AU34: =IF(OR(C34<>"Closed",D34="",F34=""),"",IF(AU11>D34,"",AT94*Loans!C7/12)) | AV34: =IF(OR(C34<>"Closed",D34="",F34=""),"",IF(AV11>D34,"",AU94*Loans!C7/12)) | AW34: =IF(OR(C34<>"Closed",D34="",F34=""),"",IF(AW11>D34,"",AV94*Loans!C7/12)) | AX34: =IF(OR(C34<>"Closed",D34="",F34=""),"",IF(AX11>D34,"",AW94*Loans!C7/12)) | AY34: =IF(OR(C34<>"Closed",D34="",F34=""),"",IF(AY11>D34,"",AX94*Loans!C7/12)) | AZ34: =IF(OR(C34<>"Closed",D34="",F34=""),"",IF(AZ11>D34,"",AY94*Loans!C7/12)) | BA34: =IF(OR(C34<>"Closed",D34="",F34=""),"",IF(BA11>D34,"",AZ94*Loans!C7/12)) | BB34: =IF(OR(C34<>"Closed",D34="",F34=""),"",IF(BB11>D34,"",BA94*Loans!C7/12)) | BC34: =IF(OR(C34<>"Closed",D34="",F34=""),"",IF(BC11>D34,"",BB94*Loans!C7/12)) | BD34: =IF(OR(C34<>"Closed",D34="",F34=""),"",IF(BD11>D34,"",BC94*Loans!C7/12)) | BE34: =IF(OR(C34<>"Closed",D34="",F34=""),"",IF(BE11>D34,"",BD94*Loans!C7/12)) | BF34: =IF(OR(C34<>"Closed",D34="",F34=""),"",IF(BF11>D34,"",BE94*Loans!C7/12)) | BG34: =IF(OR(C34<>"Closed",D34="",F34=""),"",IF(BG11>D34,"",BF94*Loans!C7/12)) | BH34: =IF(OR(C34<>"Closed",D34="",F34=""),"",IF(BH11>D34,"",BG94*Loans!C7/12)) | BI34: =IF(OR(C34<>"Closed",D34="",F34=""),"",IF(BI11>D34,"",BH94*Loans!C7/12)) | BJ34: =IF(OR(C34<>"Closed",D34="",F34=""),"",IF(BJ11>D34,"",BI94*Loans!C7/12)) | BK34: =IF(OR(C34<>"Closed",D34="",F34=""),"",IF(BK11>D34,"",BJ94*Loans!C7/12)) | BL34: =IF(OR(C34<>"Closed",D34="",F34=""),"",IF(BL11>D34,"",BK94*Loans!C7/12)) | BM34: =IF(OR(C34<>"Closed",D34="",F34=""),"",IF(BM11>D34,"",BL94*Loans!C7/12)) | BN34: =IF(OR(C34<>"Closed",D34="",F34=""),"",IF(BN11>D34,"",BM94*Loans!C7/12)) | BO34: =IF(OR(C34<>"Closed",D34="",F34=""),"",IF(BO11>D34,"",BN94*Loans!C7/12)) | BP34: =IF(OR(C34<>"Closed",D34="",F34=""),"",IF(BP11>D34,"",BO94*Loans!C7/12))
